Workbook

Sheet Acerno_Cache_XXXXX

Sheet Resumen
A1: FIRMA | B1: REGIONAL | C1: NÚMERO PROCESOS AUDITADOS | D1: 10% DE PROCESOS AUDITADOS | E1: NÚMER PROCESOS CON ERROR | F1: PORCENTAJE PROCESOS CON ERROR | G1: CONCLUSIÓN
A2: JURISCOL ABOGADOS SAS | B2: BOGOTA | C2: =COUNTIF(BASE!A:A,A2) -> 87 | D2: =ROUNDUP(C2*0.1,0) -> 9 | E2: =COUNTIFS(BASE!AU:AU,"GENERA DESCUENTO",BASE!A:A,A2) -> 0 | F2: =IFERROR(E2/C2,0) -> 0 | G2: =IF(F2>=10%,"APLICAR DESCUENTO","NO APLICAR DESCUENTO") -> NO APLICAR DESCUENTO
A3: TABOR ASESORES LEGALES SAS | B3: BOGOTA | C3: =COUNTIF(BASE!A:A,A3) -> 183 | D3: =ROUNDUP(C3*0.1,0) -> 19 | E3: =COUNTIFS(BASE!AU:AU,"GENERA DESCUENTO",BASE!A:A,A3) -> 0 | F3: =IFERROR(E3/C3,0) -> 0 | G3: =IF(F3>=10%,"APLICAR DESCUENTO","NO APLICAR DESCUENTO") -> NO APLICAR DESCUENTO
A4: TRUJILLO POLANIA Y ASOCIADOS | B4: BOGOTA | C4: =COUNTIF(BASE!A:A,A4) -> 79 | D4: =ROUNDUP(C4*0.1,0) -> 8 | E4: =COUNTIFS(BASE!AU:AU,"GENERA DESCUENTO",BASE!A:A,A4) -> 0 | F4: =IFERROR(E4/C4,0) -> 0 | G4: =IF(F4>=10%,"APLICAR DESCUENTO","NO APLICAR DESCUENTO") -> NO APLICAR DESCUENTO
A5: VENCE SALAMANCA LAWYERS GROUP SAS | B5: BOGOTA | C5: =COUNTIF(BASE!A:A,A5) -> 139 | D5: =ROUNDUP(C5*0.1,0) -> 14 | E5: =COUNTIFS(BASE!AU:AU,"GENERA DESCUENTO",BASE!A:A,A5) -> 0 | F5: =IFERROR(E5/C5,0) -> 0 | G5: =IF(F5>=10%,"APLICAR DESCUENTO","NO APLICAR DESCUENTO") -> NO APLICAR DESCUENTO
A6: WORLD LEGAL CORPORATION SAS | B6: BOGOTA | C6: =COUNTIF(BASE!A:A,A6) -> 104 | D6: =ROUNDUP(C6*0.1,0) -> 11 | E6: =COUNTIFS(BASE!AU:AU,"GENERA DESCUENTO",BASE!A:A,A6) -> 0 | F6: =IFERROR(E6/C6,0) -> 0 | G6: =IF(F6>=10%,"APLICAR DESCUENTO","NO APLICAR DESCUENTO") -> NO APLICAR DESCUENTO

Sheet CON REPLICA
A1: FIRMA | B1: ID_PROCESOS | C1: NO_BIZAGI | D1: ID_EKOGUI | E1: DIGITOS_23 | F1: 21 DIG | G1: TIPO_PROCESO | H1: IDENTIFICACION_DEMANDANTE | I1: NOMBRE_DEMANDANTE | J1: DEMANDADO | K1: REGIONAL | L1: SENTIDO_FALLO_1INSTANCIA | M1: FECHA_FALLO_1INSTANCIA | N1: SENTIDO_FALLO_2INSTANCIA | O1: FECHA_FALLO_2INSTANCIA | P1: DEMANDA | Q1: OBSERVACIÓN DEMANDA | R1: ACTA_DE_AUDIENCIA | S1: OBSERVACIÓN ACTA_DE_AUDIENCIA | T1: CONTESTACION_DE_DEMANDA | U1: OBSERVACIÓN CONTESTACION_DE_DEMANDA | V1: SENTENCIA_PRIMERA_INSTANCIA | W1: OBSERVACIÓN SENTENCIA_PRIMERA_INSTANCIA | X1: SENTENCIA_SEGUNDA_INSTANCIA | Y1: OBSERVACIÓN SENTENCIA_SEGUNDA_INSTANCIA | Z1: DEMANDA | AA1: OBSERVACIÓN DEMANDA | AB1: MANDAMIENTO_DE_PAGO | AC1: OBSERVACIÓN MANDAMIENTO_DE_PAGO | AD1: EXCEPCIONES_CONTESTACION | AE1: OBSERVACIÓN EXCEPCIONES_CONTESTACION | AF1: AUTO_QUE_ORDENA_CONTINUAR/NO_CONTINUAR_CON _LA_EJECUCION | AG1: OBSERVACIÓN AUTO_QUE_ORDENA_CONTINUAR/NO_CONTINUAR_CON _LA_EJECUCION | AH1: VALIDACIÓN | AI1: OBSERVACIÓN ERROR | AJ1: PROCEDE / NO PROCEDE ERROR | AK1: RAZÓN POR LA CUAL NO PROCEDE | AL1: OBSERVACIÓN REGIONAL | AM1: CONCLUSIÓN | AN1: ENCARGADO | AO1: Responsables | AR1: REVISOR REGIONAL
A2: TABOR ASESORES LEGALES SAS | B2: ID_007159842 | C2: 2022_2383761 | D2: 2270960 | E2: 11001310501920210043700 | G2: ORDINARIO LABORAL DE PRIMERA INSTANCIA | H2: 19498167 | I2: JUAN CARLOS CASTELLANOS CRUZ | J2: Colpensiones | K2: BOGOTA | L2: DESFAVORABLE | M2: 25/06/2024 | N2: SIN FALLO | P2: SI | R2: SI | T2: SI | V2: SI | X2: NO | Y2: No se cargó en la plataforma ekogui la pieza procesal SENTENCIA. | AH2: ERROR | AI2: ////////No se cargó en la plataforma ekogui la pieza procesal SENTENCIA.//////// | AJ2: NO PROCEDE ERROR | AK2: EL DOCUMENTO SE ENCUENTRA CARGADO EN EKOGUI DESDE 2024/07/20 | AN2: ANA MARIA ROJAS | AQ2: X | AR2: ANA MARIA ROJAS
A3: WORLD LEGAL CORPORATION SAS | B3: ID_00611087 | C3: 2020_1463093 | D3: 1378379 | E3: 11001310500220180067700 | G3: ORDINARIO LABORAL DE PRIMERA INSTANCIA | H3: 212893 | I3: CARLOS HERNAN GONZALEZ POSADA | J3: Colpensiones | K3: BOGOTA | L3: FAVORABLE | M3: 5/09/2023 | N3: SIN FALLO | P3: NO | Q3: No se cargó en la plataforma ekogui la pieza procesal DEMANDA-ORDINARIA. | R3: SI | T3: SI | V3: SI | X3: NO | Y3: No se cargó en la plataforma ekogui la pieza procesal SENTENCIA. | AH3: ERROR | AI3: No se cargó en la plataforma ekogui la pieza procesal DEMANDA-ORDINARIA.////////No se cargó en la plataforma ekogui la pieza procesal SENTENCIA.//////// | AJ3: NO PROCEDE ERROR | AK3: LA SENTENCIA ESTA CARGADA DESDE 2024/07/23 -SENTENCIA- 11001310500220180067700.pdf | AN3: ANA MARIA ROJAS | AQ3: X | AR3: ANA MARIA ROJAS
A4: WORLD LEGAL CORPORATION SAS | B4: ID_007822556 | C4: 2025_5771852 | D4: 2633368 | E4: 11001310503520240032700 | G4: ORDINARIO LABORAL DE PRIMERA INSTANCIA | H4: 17135915 | I4: ANTONIO MARIA GOMEZ GARAY | J4: Colpensiones | K4: BOGOTA | L4: SIN FALLO | N4: SIN FALLO | P4: NO | Q4: No se cargó en la plataforma ekogui la pieza procesal DEMANDA-ORDINARIA. | T4: SI | AH4: ERROR | AI4: No se cargó en la plataforma ekogui la pieza procesal DEMANDA-ORDINARIA.//////////////// | AJ4: NO PROCEDE ERROR | AK4: LA PIEZA PROCESAL FUE CARGADA EN EKOGUI ANTES DE CORTE EL DIA: 2026/04/03 -NOTIFICACION AUTO ADMISORIO/MANDAMIENTO DE PAGO- DEMANDA.pdf | AN4: ANA MARIA ROJAS | AQ4: X | AR4: ANA MARIA ROJAS
A5: TRUJILLO POLANIA Y ASOCIADOS | B5: ID_00001239 | C5: SIN_BZ_1266 | D5: 1192223 | E5: 11001310500920120010300 | G5: EJECUTIVO LABORAL | H5: 17665468 | I5: JESUS MARIO LUJAN ARENAS | J5: COLPENSIONES | K5: BOGOTA | L5: CONTINUA CON LA EJECUCION | M5: 15/03/2013 | N5: SIN FALLO | Z5: NO | AA5: Se cargó en la plataforma ekogui la pieza procesal DEMANDA QUE DA ORIGEN AL MANDAMIENTO DE PAGO, pero es un comodín, pantallazo, o es otra pieza procesal. | AB5: NO | AC5: No se cargó en la plataforma ekogui la pieza procesal DEMANDA QUE DA ORIGEN AL MANDAMIENTO DE PAGO. | AH5: ERROR | AI5: //////////Se cargó en la plataforma ekogui la pieza procesal DEMANDA QUE DA ORIGEN AL MANDAMIENTO DE PAGO, pero es un comodín, pantallazo, o es otra pieza procesal.//No se cargó en la plataforma ekogui la pieza procesal DEMANDA QUE DA ORIGEN AL MANDAMIENTO DE PAGO.//// | AJ5: NO PROCEDE ERROR | AK5: EL CARGUE DE LA PIEZA MENCIONADA, NO SE DIO EN VIGENCIA DE LA FIRMA TRUJILLO POLANIA, SIN EMBARGO SE SOLICITA ACCESO AL EXPEDIENTE PARA DAR CORRECCION A LO SOLICITADO. (SE CARGAN TODAS LAS PIEZAS REQUERIDAS) | AN5: ANA MARIA ROJAS | AQ5: X | AR5: ANA MARIA ROJAS
A6: WORLD LEGAL CORPORATION SAS | B6: ID_007039569 | C6: 2021_8136033 | D6: 2217857 | E6: 11001310503520210019100 | G6: ORDINARIO LABORAL DE PRIMERA INSTANCIA | H6: 39781379 | I6: JACQUELINE MARGARET DANIEL SILVA | J6: Colpensiones | K6: BOGOTA | L6: DESFAVORABLE | M6: 7/07/2023 | N6: DESFAVORABLE | O6: 31/05/2024 | P6: SI | R6: SI | T6: SI | V6: NO | W6: Se cargó en la plataforma ekogui la pieza procesal SENTENCIA, pero es un comodín, pantallazo, o es otra pieza procesal. | AH6: ERROR | AI6: //////Se cargó en la plataforma ekogui la pieza procesal SENTENCIA, pero es un comodín, pantallazo, o es otra pieza procesal.////////// | AJ6: NO PROCEDE ERROR | AK6: EL ACTA REQUERIDA ES DE FECHA 07/07/2023, FECHA PARA LA CUAL LA FIRMA NO EJERCIA DEFENSA PARA LA ENTIDAD, POR LO TANTO GENERA COMPROMISO PERO NO DESCUENTO YA QUE LA OBLIGACION DEL CARGUE SE GENERO EN VIGENCIA DE OTRO CONTRATO | AN6: ANA MARIA ROJAS | AQ6: X | AR6: ANA MARIA ROJAS
A7: WORLD LEGAL CORPORATION SAS | B7: ID_007965549 | C7: 2025_22812760 | D7: 2691895 | E7: 11001310503420250010500 | G7: ORDINARIO LABORAL DE PRIMERA INSTANCIA | H7: 80351015 | I7: JOSE VICENTE NEUTA ZABALA | J7: Colpensiones | K7: BOGOTA | L7: SIN FALLO | N7: SIN FALLO | P7: NO | Q7: Se cargó en la plataforma ekogui la pieza procesal DEMANDA-ORDINARIA, pero es un comodín, pantallazo, o es otra pieza procesal. | AH7: ERROR | AI7: Se cargó en la plataforma ekogui la pieza procesal DEMANDA-ORDINARIA, pero es un comodín, pantallazo, o es otra pieza procesal.//////////////// | AJ7: NO PROCEDE ERROR | AK7: EL ARCHIVO DEMANDA ESTA CARGADO DESDE 2026/04/05 CON EL NOMBRE DE PDF: 01PROCESOORDINARIOLABORALDEPRIMERAINSTANCIADEMANDAYANEXOSJOSEVICENTENEUTAZABALA.pdf | AN7: ANA MARIA ROJAS | AQ7: X | AR7: ANA MARIA ROJAS
A8: WORLD LEGAL CORPORATION SAS | B8: ID_007321598 | C8: 2022_17249359 | D8: 2374270 | E8: 11001310500720220003800 | G8: ORDINARIO LABORAL DE PRIMERA INSTANCIA | H8: 17580855 | I8: MANUEL JOSE CAROPRESE MENDEZ | J8: Colpensiones | K8: BOGOTA | L8: DESFAVORABLE | M8: 4/03/2024 | N8: SIN FALLO | P8: SI | T8: SI | V8: NO | W8: Se cargó en la plataforma ekogui la pieza procesal SENTENCIA, pero es un comodín, pantallazo, o es otra pieza procesal. | AH8: ERROR | AI8: //////Se cargó en la plataforma ekogui la pieza procesal SENTENCIA, pero es un comodín, pantallazo, o es otra pieza procesal.////////// | AJ8: NO PROCEDE ERROR | AK8: EL ACTA REQUERIDA ES DE FECHA 04/03/2024, FECHA PARA LA CUAL LA FIRMA NO EJERCIA DEFENSA PARA LA ENTIDAD, POR LO TANTO GENERA COMPROMISO PERO NO DESCUENTO YA QUE LA OBLIGACION DEL CARGUE SE GENERO EN VIGENCIA DE OTRO CONTRATO | AN8: ANA MARIA ROJAS | AQ8: X | AR8: ANA MARIA ROJAS
A9: TRUJILLO POLANIA Y ASOCIADOS | B9: ID_00037146 | C9: ISS_34689 | D9: 238481 | E9: 11001310501420110046500 | G9: EJECUTIVO LABORAL | H9: 3115904 | I9: AGUSTIN FONSECA | J9: ISS | K9: BOGOTA | L9: CONTINUA CON LA EJECUCION | M9: 12/08/2011 | N9: SIN FALLO | Z9: NO | AA9: Se cargó en la plataforma ekogui la pieza procesal DEMANDA QUE DA ORIGEN AL MANDAMIENTO DE PAGO, pero es un comodín, pantallazo, o es otra pieza procesal. | AB9: SI | AD9: NO | AE9: No se cargó en la plataforma ekogui la pieza procesal EXCEPCIONES_CONTESTACION | AF9: NO | AG9: No se cargó en la plataforma ekogui la pieza procesal AUTO QUE ORDENA/NO ORDENA CONTINUAR CON LA EJECUCION. | AH9: ERROR | AI9: //////////Se cargó en la plataforma ekogui la pieza procesal DEMANDA QUE DA ORIGEN AL MANDAMIENTO DE PAGO, pero es un comodín, pantallazo, o es otra pieza procesal.////No se cargó en la plataforma ekogui la pieza procesal EXCEPCIONES_CONTESTACION//No se cargó en la plataforma ekogui la pieza procesal AUTO QUE ORDENA/NO ORDENA CONTINUAR CON LA EJECUCION. | AJ9: NO PROCEDE ERROR | AK9: EL CARGUE DE LA PIEZA MENCIONADA, NO SE DIO EN VIGENCIA DE LA FIRMA TRUJILLO POLANIA, SIN EMBARGO SE SOLICITA ACCESO AL EXPEDIENTE PARA DAR CORRECCION A LO SOLICITADO. (AUTO QUE LIBRA MANDAMIENTO DE PAGO CON FECHA DE 16/08/2011. | AN9: ANA MARIA ROJAS | AQ9: X | AR9: ANA MARIA ROJAS
A10: WORLD LEGAL CORPORATION SAS | B10: ID_007148863 | C10: 2022_1533276 | D10: 2265978 | E10: 11001310501120200025501 | G10: ORDINARIO LABORAL DE PRIMERA INSTANCIA | H10: 19307013 | I10: CESAR AUGUSTO MELO BELLO | J10: Colpensiones | K10: BOGOTA | L10: DESFAVORABLE | M10: 5/09/2023 | N10: DESFAVORABLE | O10: 31/05/2024 | P10: SI | T10: SI | V10: NO | W10: Se cargó en la plataforma ekogui la pieza procesal SENTENCIA de forma incompleta. | Y10: SI | AH10: ERROR | AI10: //////Se cargó en la plataforma ekogui la pieza procesal SENTENCIA de forma incompleta.//SI//////// | AJ10: NO PROCEDE ERROR | AK10: LA PIEZA PROCESAL ESTA CARGADA DESDE:2024/06/12 -SENTENCIA- 11001310501120200025501.pdf Y 2023/11/07-SENTENCIA- 11001310501120200025501.pdf// CABE INDICAR QUE LA PIEZA PROCESAS CARGADA EN SENTENCIA DE 1RA SE CARGO COMO REPOSA EN EL EXPEDIENTE, Y DE ESA MISMA FORMA SE REMITIO AL TRIBUNAL Y EL TRIBUNAL LE DIO TRAMITE SIN FIRMA | AN10: ANA MARIA ROJAS | AQ10: X | AR10: ANA MARIA ROJAS
A11: WORLD LEGAL CORPORATION SAS | B11: ID_00345507 | C11: 2017_7977748 | D11: 1050504 | E11: 11001310503520170004500 | G11: EJECUTIVO LABORAL | H11: 13004846 | I11: BENJAMIN GARRIDO TORRES | J11: Colpensiones | K11: BOGOTA | L11: CONTINUA CON LA EJECUCION | M11: 17/01/2018 | N11: SIN FALLO | Z11: NO | AA11: No se cargó en la plataforma ekogui la pieza procesal DEMANDA QUE DA ORIGEN AL MANDAMIENTO DE PAGO. | AB11: SI | AD11: SI | AF11: SI | AH11: ERROR | AI11: //////////No se cargó en la plataforma ekogui la pieza procesal DEMANDA QUE DA ORIGEN AL MANDAMIENTO DE PAGO.////// | AJ11: NO PROCEDE ERROR | AK11: LA DEMANDA EJECUTIVA ESTA CARGADA DESDE 01/08/2017 en el folio 6 y 7, en el pdf llamado: "PROCESO (MP)DTE: BENJAMIN GARRIDO TORRESDDO: COLPENSIONES .pdf" | AN11: ANA MARIA ROJAS | AQ11: X | AR11: ANA MARIA ROJAS
A12: TRUJILLO POLANIA Y ASOCIADOS | B12: ID_00086820 | C12: 2013_4144956 | D12: 1166392 | E12: 11001310501420130036600 | G12: EJECUTIVO LABORAL | H12: 20152709 | I12: MARGARITA ANGEL RINCON | J12: COLPENSIONES | K12: BOGOTA | L12: CONTINUA CON LA EJECUCION | M12: 27/06/2014 | N12: SIN FALLO | Z12: NO | AA12: Se cargó en la plataforma ekogui la pieza procesal DEMANDA QUE DA ORIGEN AL MANDAMIENTO DE PAGO, pero es un comodín, pantallazo, o es otra pieza procesal. | AB12: SI | AH12: ERROR | AI12: //////////Se cargó en la plataforma ekogui la pieza procesal DEMANDA QUE DA ORIGEN AL MANDAMIENTO DE PAGO, pero es un comodín, pantallazo, o es otra pieza procesal.////// | AJ12: NO PROCEDE ERROR | AK12: EL CARGUE DE LA PIEZA MENCIONADA, NO SE DIO EN VIGENCIA DE LA FIRMA TRUJILLO POLANIA, SIN EMBARGO SE SOLICITA ACCESO AL EXPEDIENTE PARA DAR CORRECCION A LO SOLICITADO. (SE CARGAN TODAS LAS PIEZAS REQUERIDAS) | AN12: ANA MARIA ROJAS | AQ12: X | AR12: ANA MARIA ROJAS
A13: TRUJILLO POLANIA Y ASOCIADOS | B13: ID_00111676 | C13: 2014_811518 | D13: 1222944 | E13: 11001310501420130054600 | G13: EJECUTIVO LABORAL | H13: 7934 | I13: GUILLERMO GARCIA GUAJE | J13: COLPENSIONES | K13: BOGOTA | L13: CONTINUA CON LA EJECUCION | M13: 8/05/2014 | N13: SIN FALLO | Z13: NO | AA13: No se cargó en la plataforma ekogui la pieza procesal DEMANDA QUE DA ORIGEN AL MANDAMIENTO DE PAGO. | AB13: SI | AH13: ERROR | AI13: //////////No se cargó en la plataforma ekogui la pieza procesal DEMANDA QUE DA ORIGEN AL MANDAMIENTO DE PAGO.////// | AJ13: NO PROCEDE ERROR | AK13: EL CARGUE DE LA PIEZA MENCIONADA, NO SE DIO EN VIGENCIA DE LA FIRMA TRUJILLO POLANIA, SIN EMBARGO SE SOLICITA ACCESO AL EXPEDIENTE PARA DAR CORRECCION A LO SOLICITADO. (SE CARGAN TODAS LAS PIEZAS REQUERIDAS) | AN13: ANA MARIA ROJAS | AQ13: X | AR13: ANA MARIA ROJAS
A14: TRUJILLO POLANIA Y ASOCIADOS | B14: ID_00113579 | C14: 2014_1180011 | D14: 1273211 | E14: 11001310500920100014500 | G14: EJECUTIVO LABORAL | H14: 41434053 | I14: AURA CECILIA RODRIGUEZ GARCIA | J14: COLPENSIONES | K14: BOGOTA | L14: CONTINUA CON LA EJECUCION | M14: 15/11/2011 | N14: SIN FALLO | Z14: NO | AA14: Se cargó en la plataforma ekogui la pieza procesal DEMANDA QUE DA ORIGEN AL MANDAMIENTO DE PAGO, pero es un comodín, pantallazo, o es otra pieza procesal. | AB14: NO | AC14: No se cargó en la plataforma ekogui la pieza procesal MANDAMIENTO DE PAGO. | AH14: ERROR | AI14: //////////Se cargó en la plataforma ekogui la pieza procesal DEMANDA QUE DA ORIGEN AL MANDAMIENTO DE PAGO, pero es un comodín, pantallazo, o es otra pieza procesal.//No se cargó en la plataforma ekogui la pieza procesal MANDAMIENTO DE PAGO.//// | AJ14: NO PROCEDE ERROR | AK14: EL CARGUE DE LA PIEZA MENCIONADA, NO SE DIO EN VIGENCIA DE LA FIRMA TRUJILLO POLANIA, SIN EMBARGO SE SOLICITA ACCESO AL EXPEDIENTE PARA DAR CORRECCION A LO SOLICITADO. (SE CARGAN TODAS LAS PIEZAS REQUERIDAS) | AN14: ANA MARIA ROJAS | AQ14: X | AR14: ANA MARIA ROJAS
A15: WORLD LEGAL CORPORATION SAS | B15: ID_007748075 | C15: 2024_23901420 | D15: 2598528 | E15: 11001310502720240109300 | G15: EJECUTIVO LABORAL | H15: 51623108 | I15: MARIA EUGENIA TIBASOSA GIL | J15: Colpensiones | K15: BOGOTA | L15: SIN FALLO | N15: SIN FALLO | Z15: NO | AA15: Se cargó en la plataforma ekogui la pieza procesal DEMANDA QUE DA ORIGEN AL MANDAMIENTO DE PAGO, pero es un comodín, pantallazo, o es otra pieza procesal. | AB15: SI | AD15: SI | AF15: NO | AG15: Se cargó en la plataforma ekogui la pieza procesal AUTO QUE ORDENA/NO ORDENA CONTINUAR CON LA EJECUCION, pero es un comodín, pantallazo, o es otra pieza procesal. | AH15: ERROR | AI15: //////////Se cargó en la plataforma ekogui la pieza procesal DEMANDA QUE DA ORIGEN AL MANDAMIENTO DE PAGO, pero es un comodín, pantallazo, o es otra pieza procesal.//////Se cargó en la plataforma ekogui la pieza procesal AUTO QUE ORDENA/NO ORDENA CONTINUAR CON LA EJECUCION, pero es un comodín, pantallazo, o es otra pieza procesal. | AJ15: NO PROCEDE ERROR | AK15: LA DEMANDA EJECUTIVA ESTA CARGADA DESDE 31/03/2026 CON EL PDF DE NOMBRE: "11001310502720240109300-DEMANDA.pdf"- Y LA SENTENCIA EJECUTIVA O AUTO DE SEGUIR ADELANTE SE ENCUENTRA CARGADO DESDE EL 31/03/2026 CON EL PDF "8. ANEXO - AUTO QUE ORDENA CONTINUAR CON LA EJECUCIÓN (4).pdf" | AN15: ANA MARIA ROJAS | AQ15: X | AR15: ANA MARIA ROJAS
A16: JURISCOL ABOGADOS SAS | B16: ID_007422193 | C16: 2023_8774502 | D16: 2376987 | E16: 11001310502620220038300 | G16: ORDINARIO LABORAL DE PRIMERA INSTANCIA | H16: 4228527 | I16: JOSE ROBINSON SOTELO PAEZ | J16: Colpensiones | K16: BOGOTA | L16: FAVORABLE | M16: 26/09/2025 | N16: SIN FALLO | P16: SI | T16: SI | V16: SI | X16: NO | Y16: Se cargó en la plataforma ekogui la pieza procesal SENTENCIA de forma incompleta. | AH16: ERROR | AI16: ////////Se cargó en la plataforma ekogui la pieza procesal SENTENCIA de forma incompleta.//////// | AJ16: NO PROCEDE ERROR | AK16: NO SE HA CARGADO PIEZA PROCESAL TODA VEZ QUE NO SE HA SURTIDO SENTENCIA DE SEGUNDA INSTANCIA | AN16: ANA MARIA ROJAS | AQ16: X | AR16: ANA MARIA ROJAS
A17: WORLD LEGAL CORPORATION SAS | B17: ID_00405778 | C17: 2018_1797709 | D17: 1157695 | E17: 11001310501120170005900 | G17: EJECUTIVO LABORAL | H17: 17184679 | I17: GERMAN CEPEDA SIERRA | J17: Colpensiones | K17: BOGOTA | L17: CONTINUA CON LA EJECUCION | M17: 25/10/2019 | N17: SIN FALLO | Z17: SI | AB17: SI | AD17: NO | AE17: No se cargó en la plataforma ekogui la pieza procesal EXCEPCIONES_CONTESTACION. | AF17: NO | AG17: No se cargó en la plataforma ekogui la pieza procesal AUTO_QUE_ORDENA_CONTINUAR/NO_CONTINUAR_CON _LA_EJECUCION | AH17: ERROR | AI17: //////////////No se cargó en la plataforma ekogui la pieza procesal EXCEPCIONES_CONTESTACION.//No se cargó en la plataforma ekogui la pieza procesal AUTO_QUE_ORDENA_CONTINUAR/NO_CONTINUAR_CON _LA_EJECUCION | AJ17: NO PROCEDE ERROR | AK17: EL ARCHIVO DE EXCEPCIONES DEL EJECUTIVO ESTA CARGADO EL DIA 03/12/2021 CON EL PDF LLAMADO "11001310501120170005900 LIQUIDACIÓN CREDITO.pdf" Y EL ARCHIVO DE SENTENCIA ESTA CARGADO EL DIA 27/05/2024 CON EL PDF LLAMADO: "11001310501120170005900 - SENTENCIA.pdf" | AN17: ANA MARIA ROJAS | AQ17: X | AR17: ANA MARIA ROJAS
A18: WORLD LEGAL CORPORATION SAS | B18: ID_007248323 | C18: 2022_10261598 | D18: 2322183 | E18: 11001310503420200013200 | G18: ORDINARIO LABORAL DE PRIMERA INSTANCIA | H18: 19377551 | I18: HUMBERTO MADRID ALARCON | J18: Colpensiones | K18: BOGOTA | L18: DESFAVORABLE | M18: 4/12/2024 | N18: SIN FALLO | P18: SI | T18: SI | V18: SI | X18: NO | Y18: No se cargó en la plataforma ekogui la pieza procesal SENTENCIA. | AH18: ERROR | AI18: ////////No se cargó en la plataforma ekogui la pieza procesal SENTENCIA.//////// | AJ18: NO PROCEDE ERROR | AK18: LA PIEZA PROCESAL SENTENCIA ESTA CARGADA DESDE 19/12/2024 CON EL PDF LLAMADO: 11001310503420200013200.pdf | AN18: ANA MARIA ROJAS | AQ18: X | AR18: ANA MARIA ROJAS
A19: TRUJILLO POLANIA Y ASOCIADOS | B19: ID_00137526 | C19: 2014_5632011 | D19: 627890 | E19: 11001310500820140009800 | G19: EJECUTIVO LABORAL | H19: 4321352 | I19: JUAN DE DIOS OCHOA DAZA | J19: COLPENSIONES | K19: BOGOTA | L19: CONTINUA CON LA EJECUCION | M19: 17/08/2017 | N19: SIN FALLO | Z19: SI | AB19: NO | AC19: No se cargó en la plataforma ekogui la pieza procesal MANDAMIENTO DE PAGO. | AD19: NO | AE19: No se cargó en la plataforma ekogui la pieza procesal EXCEPCIONES_CONTESTACION | AF19: NO | AG19: No se cargó en la plataforma ekogui la pieza procesal AUTO_QUE_ORDENA_CONTINUAR/NO_CONTINUAR_CON _LA_EJECUCION | AH19: ERROR | AI19: ////////////No se cargó en la plataforma ekogui la pieza procesal MANDAMIENTO DE PAGO.//No se cargó en la plataforma ekogui la pieza procesal EXCEPCIONES_CONTESTACION//No se cargó en la plataforma ekogui la pieza procesal AUTO_QUE_ORDENA_CONTINUAR/NO_CONTINUAR_CON _LA_EJECUCION | AJ19: NO PROCEDE ERROR | AK19: EL CARGUE DE LA PIEZA MENCIONADA, NO SE DIO EN VIGENCIA DE LA FIRMA TRUJILLO POLANIA, SIN EMBARGO SE SOLICITA ACCESO AL EXPEDIENTE PARA DAR CORRECCION A LO SOLICITADO. (SE CARGAN TODAS LAS PIEZAS REQUERIDAS) | AN19: ANA MARIA ROJAS | AQ19: X | AR19: ANA MARIA ROJAS
A20: VENCE SALAMANCA LAWYERS GROUP SAS | B20: ID_007442143 | C20: 2023_11219374 | D20: 2451719 | E20: 11001310504020210044700 | G20: ORDINARIO LABORAL DE PRIMERA INSTANCIA | H20: 35331445 | I20: MARIA LIDA ESPERANZA HERNANDEZ ESCOBAR | J20: Colpensiones | K20: BOGOTA | L20: SIN FALLO | N20: SIN FALLO | P20: SI | R20: NO | S20: No se cargó en la plataforma ekogui la pieza procesal ACTA DE AUDIENCIA. | T20: SI | V20: NO | W20: No se cargó en la plataforma ekogui la pieza procesal SENTENCIA. | AH20: ERROR | AI20: //No se cargó en la plataforma ekogui la pieza procesal ACTA DE AUDIENCIA.////No se cargó en la plataforma ekogui la pieza procesal SENTENCIA.////////// | AJ20: NO PROCEDE ERROR | AK20: LA PIEZA PROCESAL "ACTA DE AUDIENCIA" NO ESTÁ EN LOS LINEAMIENTOS DE LA ANS2 Y NO ES OBJETO DE AUDITORIA, EN EL PROCESO NO SE PROFIRIÓ SENTENCIA, TERMINÓ ANORMALMENTE MEDIANTE AUTO | AM20: GENERA DESCUENTO | AN20: ANA MARIA ROJAS | AQ20: X | AR20: ANA MARIA ROJAS
A21: TRUJILLO POLANIA Y ASOCIADOS | B21: ID_00146806 | C21: 2014_7093360 | D21: 626545 | E21: 11001310500920070098700 | G21: EJECUTIVO LABORAL | H21: 17089621 | I21: JOSE VICENTE ROJAS MORENO | J21: COLPENSIONES | K21: BOGOTA | L21: CONTINUA CON LA EJECUCION | M21: 25/11/2010 | N21: SIN FALLO | Z21: NO | AA21: No se cargó en la plataforma ekogui la pieza procesal DEMANDA QUE DA ORIGEN AL MANDAMIENTO DE PAGO. | AB21: SI | AD21: NO | AE21: No se cargó en la plataforma ekogui la pieza procesal EXCEPCIONES_CONTESTACION | AF21: NO | AG21: No se cargó en la plataforma ekogui la pieza procesal AUTO_QUE_ORDENA_CONTINUAR/NO_CONTINUAR_CON _LA_EJECUCION | AH21: ERROR | AI21: //////////No se cargó en la plataforma ekogui la pieza procesal DEMANDA QUE DA ORIGEN AL MANDAMIENTO DE PAGO.////No se cargó en la plataforma ekogui la pieza procesal EXCEPCIONES_CONTESTACION//No se cargó en la plataforma ekogui la pieza procesal AUTO_QUE_ORDENA_CONTINUAR/NO_CONTINUAR_CON _LA_EJECUCION | AJ21: NO PROCEDE ERROR | AK21: EL CARGUE DE LA PIEZA MENCIONADA, NO SE DIO EN VIGENCIA DE LA FIRMA TRUJILLO POLANIA, SIN EMBARGO SE SOLICITA ACCESO AL EXPEDIENTE PARA DAR CORRECCION A LO SOLICITADO. (SE CARGAN TODAS LAS PIEZAS REQUERIDAS) | AN21: ANA MARIA ROJAS | AQ21: X | AR21: ANA MARIA ROJAS
A22: TABOR ASESORES LEGALES SAS | B22: ID_007594810 | C22: 2024_5871472 | D22: 2460415 | E22: 11001310500120230009200 | G22: ORDINARIO LABORAL DE PRIMERA INSTANCIA | H22: 12533791 | I22: CESAR AUGUSTO BOJATO PEREZ | J22: Colpensiones | K22: BOGOTA | L22: SIN FALLO | N22: SIN FALLO | P22: NO | Q22: Se cargó en la plataforma ekogui la pieza procesal DEMANDA-ORDINARIA, pero no fue cargada por parte de firma que representa a Colpensiones. | T22: SI | AH22: ERROR | AI22: Se cargó en la plataforma ekogui la pieza procesal DEMANDA-ORDINARIA, pero no fue cargada por parte de firma que representa a Colpensiones.//////////////// | AJ22: NO PROCEDE ERROR | AK22: EL PROCESO FUE CREADO EN EKOGUI 2023-08-13, COLPENSIONES FUE NOTIFICADO 2024-04-02. LO QUE SIGNIFICA QUE COLPENSIONES NO LE ES POSIBLE CREAR OTRO PROCESO EN EL APLICATIVO, SINO QUE SE VINCULA ES MAS NO ES POSIBLE NI EDITAR EL DOCUMENTO | AN22: ANA MARIA ROJAS | AQ22: X | AR22: ANA MARIA ROJAS
A23: WORLD LEGAL CORPORATION SAS | B23: ID_007993968 | C23: 2025_25870069 | D23: 2706234 | E23: 11001310503320190038900 | G23: EJECUTIVO LABORAL | H23: 4191189 | I23: JOSE SAUL FLECHAS VELASCO | J23: Colpensiones | K23: BOGOTA | L23: SIN FALLO | N23: SIN FALLO | Z23: SI | AB23: NO | AC23: Se cargó en la plataforma ekogui la pieza procesal MANDAMIENTO DE PAGO, pero es un comodín, pantallazo, o es otra pieza procesal. | AD23: SI | AH23: ERROR | AI23: ////////////Se cargó en la plataforma ekogui la pieza procesal MANDAMIENTO DE PAGO, pero es un comodín, pantallazo, o es otra pieza procesal.//// | AJ23: NO PROCEDE ERROR | AK23: EL ARCHIVO MANDAMIENTO DE PAGO ESTA CARGADO DESDE EL DIA 17/12/2025 CON EL PDF LLAMADO: " 2025_25870069-NOTIFICACION.pdf" | AN23: ANA MARIA ROJAS | AQ23: X | AR23: ANA MARIA ROJAS
A24: TRUJILLO POLANIA Y ASOCIADOS | B24: ID_00174266 | C24: 2015_2212576 | D24: 638321 | E24: 11001310500920140052400 | G24: EJECUTIVO LABORAL | H24: 8999990823 | I24: GRUPO ENERGÍA DE BOGOTA SA ESP | J24: COLPENSIONES | K24: BOGOTA | L24: CONTINUA CON LA EJECUCION | M24: 17/09/2015 | N24: SIN FALLO | Z24: SI | AB24: NO | AC24: Se cargó en la plataforma ekogui la pieza procesal MANDAMIENTO DE PAGO, pero es un comodín, pantallazo, o es otra pieza procesal. | AD24: NO | AE24: No se cargó en la plataforma ekogui la pieza procesal EXCEPCIONES_CONTESTACION | AF24: NO | AG24: No se cargó en la plataforma ekogui la pieza procesal AUTO_QUE_ORDENA_CONTINUAR/NO_CONTINUAR_CON _LA_EJECUCION | AH24: ERROR | AI24: ////////////Se cargó en la plataforma ekogui la pieza procesal MANDAMIENTO DE PAGO, pero es un comodín, pantallazo, o es otra pieza procesal.//No se cargó en la plataforma ekogui la pieza procesal EXCEPCIONES_CONTESTACION//No se cargó en la plataforma ekogui la pieza procesal AUTO_QUE_ORDENA_CONTINUAR/NO_CONTINUAR_CON _LA_EJECUCION | AJ24: NO PROCEDE ERROR | AK24: EL CARGUE DE LA PIEZA MENCIONADA, NO SE DIO EN VIGENCIA DE LA FIRMA TRUJILLO POLANIA, SIN EMBARGO SE SOLICITA ACCESO AL EXPEDIENTE PARA DAR CORRECCION A LO SOLICITADO. (SE CARGAN TODAS LAS PIEZAS REQUERIDAS) | AN24: ANA MARIA ROJAS | AQ24: X | AR24: ANA MARIA ROJAS
A25: TRUJILLO POLANIA Y ASOCIADOS | B25: ID_00183076 | C25: 2015_3957368 | D25: 1144539 | E25: 11001310501620130057500 | G25: EJECUTIVO LABORAL | H25: 26053 | I25: DOMINGO TORRES CASTEBLANCO | J25: COLPENSIONES | K25: BOGOTA | L25: CONTINUA CON LA EJECUCION | M25: 24/07/2015 | N25: SIN FALLO | Z25: SI | AB25: NO | AC25: Se cargó en la plataforma ekogui la pieza procesal MANDAMIENTO DE PAGO, pero es un comodín, pantallazo, o es otra pieza procesal. | AD25: NO | AE25: No se cargó en la plataforma ekogui la pieza procesal EXCEPCIONES_CONTESTACION | AF25: NO | AG25: No se cargó en la plataforma ekogui la pieza procesal AUTO_QUE_ORDENA_CONTINUAR/NO_CONTINUAR_CON _LA_EJECUCION | AH25: ERROR | AI25: ////////////Se cargó en la plataforma ekogui la pieza procesal MANDAMIENTO DE PAGO, pero es un comodín, pantallazo, o es otra pieza procesal.//No se cargó en la plataforma ekogui la pieza procesal EXCEPCIONES_CONTESTACION//No se cargó en la plataforma ekogui la pieza procesal AUTO_QUE_ORDENA_CONTINUAR/NO_CONTINUAR_CON _LA_EJECUCION | AJ25: NO PROCEDE ERROR | AK25: EL CARGUE DE LA PIEZA MENCIONADA, NO SE DIO EN VIGENCIA DE LA FIRMA TRUJILLO POLANIA, SIN EMBARGO SE SOLICITA ACCESO AL EXPEDIENTE PARA DAR CORRECCION A LO SOLICITADO. (SE CARGAN TODAS LAS PIEZAS REQUERIDAS) | AN25: ANA MARIA ROJAS | AQ25: X | AR25: ANA MARIA ROJAS
A26: TABOR ASESORES LEGALES SAS | B26: ID_007084909 | C26: 2021_11469493 | D26: 2238406 | E26: 11001310500420210042500 | G26: ORDINARIO LABORAL DE PRIMERA INSTANCIA | H26: 73095252 | I26: EFRAIN OROZCO PEREZ | J26: Colpensiones | K26: BOGOTA | L26: DESFAVORABLE | M26: 30/05/2023 | N26: DESFAVORABLE | O26: 29/04/2025 | P26: SI | T26: NO | U26: No se cargó en la plataforma ekogui la pieza procesal CONTESTACION DE LA DEMANDA. | V26: NO | W26: No se cargó en la plataforma ekogui la pieza procesal SENTENCIA. | X26: SI | AH26: ERROR | AI26: ////No se cargó en la plataforma ekogui la pieza procesal CONTESTACION DE LA DEMANDA.//No se cargó en la plataforma ekogui la pieza procesal SENTENCIA.////////// | AJ26: NO PROCEDE ERROR | AK26: NO ES SUSCEPTIBLE DE AUDITORIA POR CUANTO SE ENCUENTRA TERMINADO EN EKOGUI DESDE EL 2025-12-18 | AN26: ANA MARIA ROJAS | AQ26: X | AR26: ANA MARIA ROJAS
A27: TRUJILLO POLANIA Y ASOCIADOS | B27: ID_00185855 | C27: 2015_4519342 | D27: 922861 | E27: 11001310500820140054600 | G27: EJECUTIVO LABORAL | H27: 19218195 | I27: HECTOR EMILIO RAMIREZ PEÑALOZA | J27: COLPENSIONES | K27: BOGOTA | L27: CONTINUA CON LA EJECUCION | M27: 15/12/2015 | N27: SIN FALLO | Z27: NO | AA27: Se cargó en la plataforma ekogui la pieza procesal DEMANDA QUE DA ORIGEN AL MANDAMIENTO DE PAGO, pero es un comodín, pantallazo, o es otra pieza procesal. | AB27: SI | AD27: SI | AF27: SI | AH27: ERROR | AI27: //////////Se cargó en la plataforma ekogui la pieza procesal DEMANDA QUE DA ORIGEN AL MANDAMIENTO DE PAGO, pero es un comodín, pantallazo, o es otra pieza procesal.////// | AJ27: NO PROCEDE ERROR | AK27: EL CARGUE DE LA PIEZA MENCIONADA, NO SE DIO EN VIGENCIA DE LA FIRMA TRUJILLO POLANIA, SIN EMBARGO SE SOLICITA ACCESO AL EXPEDIENTE PARA DAR CORRECCION A LO SOLICITADO. (SE CARGAN TODAS LAS PIEZAS REQUERIDAS) | AN27: ANA MARIA ROJAS | AQ27: X | AR27: ANA MARIA ROJAS
A28: WORLD LEGAL CORPORATION SAS | B28: ID_007711265 | C28: 2024_19050121 | D28: 2443540 | E28: 11001310501120230005600 | G28: ORDINARIO LABORAL DE PRIMERA INSTANCIA | H28: 9655381 | I28: JAVIER MAURICIO ANGARITA VALDERRAMA | J28: Colpensiones | K28: BOGOTA | L28: SIN FALLO | N28: SIN FALLO | P28: SI | R28: NO | S28: Se cargó en la plataforma ekogui la pieza procesal ACTA DE AUDIENCIA, pero no fue cargada por parte de firma que representa a Colpensiones. | T28: SI | V28: SI | AH28: ERROR | AI28: //Se cargó en la plataforma ekogui la pieza procesal ACTA DE AUDIENCIA, pero no fue cargada por parte de firma que representa a Colpensiones.////////////// | AJ28: NO PROCEDE ERROR | AK28: LA PIEZA PROCESAL DE ACTA DE AUDIENCIA DONDE SE LLEVO A CABO EL FALLO ESTA CARGADO DESDE: 2026/04/05 -SENTENCIA- 11001310501120230005600 - XIMENA RAYO CALDERON.pdf// FECHA ANTES DE CORTE | AN28: ANA MARIA ROJAS | AQ28: X | AR28: ANA MARIA ROJAS
A29: VENCE SALAMANCA LAWYERS GROUP SAS | B29: ID_007374304 | C29: 2023_3831234 | D29: 2410884 | E29: 11001333704020220027900 | G29: ACCION DE NULIDAD Y RESTABLECIMIENTO DEL DERECHO | H29: 9001562642 | I29: NUEVA EMPRESA PROMOTORA DE SALUD S.A. | J29: Colpensiones | K29: BOGOTA | L29: DESFAVORABLE | M29: 18/10/2023 | N29: SIN FALLO | P29: NO | Q29: NO CARGA LA DEMANDA | T29: OK | V29: OK | X29: NO | Y29: NO SE ENCUENTRA CARGA LA SENTENCIA | AH29: ERROR | AI29: NO CARGA LA DEMANDA ////////NO SE ENCUENTRA CARGA LA SENTENCIA //////// | AJ29: NO PROCEDE ERROR | AK29: DEMANDA CARGADA DESDE EL 10/3/2023, SENTENCIA DE SEGUNDA INSTANCIA CARGADA EL 27/03/2026 | AM29: GENERA DESCUENTO | AN29: JAIME GUZMAN | AQ29: X | AR29: JAIME GUZMAN
A30: WORLD LEGAL CORPORATION SAS | B30: ID_007674554 | C30: 2024_14916127 | D30: 2560957 | E30: 11001310501120230045500 | G30: ORDINARIO LABORAL DE PRIMERA INSTANCIA | H30: 17061329 | I30: FERNANDO URIBE RODRIGUEZ | J30: Colpensiones | K30: BOGOTA | L30: DESFAVORABLE | M30: 30/10/2024 | N30: SIN FALLO | P30: OK | T30: NO | U30: Se cargó en la plataforma ekogui la pieza procesal CONTESTACION DE LA DEMANDA, pero no corresponde al proceso actual. | V30: NO | W30: Se cargó en la plataforma ekogui la pieza procesal SENTENCIA, pero no corresponde al proceso actual. | AH30: ERROR | AI30: ////Se cargó en la plataforma ekogui la pieza procesal CONTESTACION DE LA DEMANDA, pero no corresponde al proceso actual.//Se cargó en la plataforma ekogui la pieza procesal SENTENCIA, pero no corresponde al proceso actual.////////// | AJ30: NO PROCEDE ERROR | AK30: LA CONTESTACION ESTA CARGADA DESDE: 2024/08/08 -CONTESTACION DE LA DEMANDA- 11001310501120230045500.pdf Y LA SENTENCIA ESTA CARGADA DESDE 2026/04/05 -SENTENCIA- 11001310501120230045500 (1).pdf, LA SENTENCIA SE CARGO ANTES DE LA FECHA DE CORTE | AN30: JAIME GUZMAN | AQ30: X | AR30: JAIME GUZMAN
A31: VENCE SALAMANCA LAWYERS GROUP SAS | B31: ID_007635646 | C31: 2024_10673705 | D31: 2544274 | E31: 11001333704120240008400 | G31: ACCION DE NULIDAD Y RESTABLECIMIENTO DEL DERECHO | H31: 9010974735 | I31: MEDIMAS EPS SAS EN LIQUIDACION | J31: Colpensiones | K31: BOGOTA | L31: SIN FALLO | N31: SIN FALLO | P31: OK | T31: NO | U31: Se cargó en la plataforma ekogui la pieza procesal CONTESTACION DE LA DEMANDA en archivo dañado o no legible. | AH31: ERROR | AI31: ////Se cargó en la plataforma ekogui la pieza procesal CONTESTACION DE LA DEMANDA en archivo dañado o no legible.//////////// | AJ31: NO PROCEDE ERROR | AK31: CONTESTACION DE DEMANDA CARGADA Y LEGIBLE EN EKOGUI | AM31: GENERA DESCUENTO | AN31: JAIME GUZMAN | AQ31: X | AR31: JAIME GUZMAN
A32: WORLD LEGAL CORPORATION SAS | B32: ID_007822970 | C32: 2025_5791004 | D32: 2633355 | E32: 11001310503420240022800 | G32: ORDINARIO LABORAL DE PRIMERA INSTANCIA | H32: 37926344 | I32: MARIA ESTHER JEREZ CAICEDO | J32: Colpensiones | K32: BOGOTA | L32: SIN FALLO | N32: SIN FALLO | P32: NO | Q32: No se cargó en la plataforma ekogui la pieza procesal DEMANDA-ORDINARIA. | T32: OK | AH32: ERROR | AI32: No se cargó en la plataforma ekogui la pieza procesal DEMANDA-ORDINARIA.//////////////// | AJ32: NO PROCEDE ERROR | AK32: LA DEMANDA ESTA CARGADA EN EKOGUI DESDE : 2025/03/30 -DEMANDA- 2025_5791004-TRASLADO.pdf | AN32: JAIME GUZMAN | AQ32: X | AR32: JAIME GUZMAN
A33: WORLD LEGAL CORPORATION SAS | B33: ID_007864366 | C33: 2025_10941536 | D33: 2658086 | E33: 11001310502720251003900 | G33: EJECUTIVO LABORAL | H33: 63295596 | I33: MARIA CLARA NIÑO GOMEZ | J33: Colpensiones | K33: BOGOTA | L33: SIN FALLO | N33: SIN FALLO | Z33: NO | AA33: No se cargó en la plataforma ekogui la pieza procesal MANDAMIENTO DE PAGO. | AB33: OK | AD33: OK | AH33: ERROR | AI33: //////////No se cargó en la plataforma ekogui la pieza procesal MANDAMIENTO DE PAGO.////// | AJ33: NO PROCEDE ERROR | AK33: LA PIEZA MANDAMIENTO DE PAGO ESTA CARGADA DESDE 28/06/2025 CON EL NOMBRE DE PDF "2025_10941536-MANDAMIENTO DE PAGO.pdf" | AN33: JAIME GUZMAN | AQ33: X | AR33: JAIME GUZMAN
A34: WORLD LEGAL CORPORATION SAS | B34: ID_00648519 | C34: 2020_8034817 | D34: 2142929 | E34: 11001310502220190069400 | G34: EJECUTIVO LABORAL | H34: 21224119 | I34: ANA CECILIA GAMEZ FORERO | J34: Colpensiones | K34: BOGOTA | L34: CONTINUA CON LA EJECUCION | M34: 11/05/2022 | N34: SIN FALLO | Z34: NO | AA34: No se cargó en la plataforma ekogui la pieza procesal MANDAMIENTO DE PAGO. | AB34: OK | AD34: OK | AF34: OK | AH34: ERROR | AI34: //////////No se cargó en la plataforma ekogui la pieza procesal MANDAMIENTO DE PAGO.////// | AJ34: NO PROCEDE ERROR | AK34: LA PIEZA MANDAMIENTO DE PAGO ESTA CARGADA DESDE 28/08/2020 CON EL NOMBRE DE PDF "11001310502220190069400 - AUTO QUE LIBRA MANDAMIENTO.pdf" | AN34: JAIME GUZMAN | AQ34: X | AR34: JAIME GUZMAN
A35: TABOR ASESORES LEGALES SAS | B35: ID_00467580 | C35: 2018_10129949 | D35: 1290401 | E35: 11001310501820180019900 | G35: EJECUTIVO LABORAL | H35: 19228099 | I35: GILBERTO TIQUE ARAGON | J35: Colpensiones | K35: BOGOTA | L35: CONTINUA CON LA EJECUCION | M35: 25/01/2019 | N35: SIN FALLO | Z35: NO | AA35: No se cargó en la plataforma ekogui la pieza procesal DEMANDA QUE DA ORIGEN AL MANDAMIENTO DE PAGO. | AB35: OK | AD35: OK | AF35: OK | AH35: ERROR | AI35: //////////No se cargó en la plataforma ekogui la pieza procesal DEMANDA QUE DA ORIGEN AL MANDAMIENTO DE PAGO.////// | AJ35: NO PROCEDE ERROR | AK35: EL DOCUMENTO SE ENCUENTRA CARGADO Y SE DENOMINA " Demanda Anexo del radicado 20181031630822.pdf" FECHA DE CARGUE 2019/04/16 AL ABRIR EL DOCUMENTO HACE MENCION A QUE SE LIBRE MANDAMIENTO DE PAGO | AN35: JAIME GUZMAN | AQ35: X | AR35: JAIME GUZMAN
A36: VENCE SALAMANCA LAWYERS GROUP SAS | B36: ID_007921716 | C36: 2025_18056188 | D36: 2674583 | E36: 11001333501420190039800 | G36: ADMINISTRATIVO EJECUTIVO | H36: 19195127 | I36: DIEGO DE JESUS ALFONSO VENEGAS | J36: Colpensiones | K36: BOGOTA | L36: SIN FALLO | N36: SIN FALLO | Z36: NO | AA36: No se cargó en la plataforma ekogui la pieza procesal MANDAMIENTO DE PAGO. | AB36: OK | AH36: ERROR | AI36: //////////No se cargó en la plataforma ekogui la pieza procesal MANDAMIENTO DE PAGO.////// | AJ36: NO PROCEDE ERROR | AK36: MANDAMIENTO DE PAGO CARGADO EN EKOGUI DESDE EL 28/8/2025 | AM36: GENERA DESCUENTO | AN36: JAIME GUZMAN | AQ36: X | AR36: JAIME GUZMAN
A37: WORLD LEGAL CORPORATION SAS | B37: ID_007427355 | C37: 2023_9374629 | D37: 2441729 | E37: 11001310503320220061000 | G37: ORDINARIO LABORAL DE PRIMERA INSTANCIA | H37: 91214442 | I37: LUIS ADENIX PARRA BARRAGAN | J37: Colpensiones | K37: BOGOTA | L37: SIN FALLO | N37: SIN FALLO | P37: OK | T37: NO | U37: No se cargó en la plataforma ekogui la pieza procesal CONTESTACION DE LA DEMANDA. | AH37: ERROR | AI37: ////No se cargó en la plataforma ekogui la pieza procesal CONTESTACION DE LA DEMANDA.//////////// | AJ37: NO PROCEDE ERROR | AK37: SE OBSERVA EN RAMA QUE LA CONTESTACION DE LA DEMANDA SE DIO EL 30/06/2023 FECHA PARA LA CUAL LA FIRMA NO EJERCIA DEFENSA PARA LA ENTIDAD, NO OBSTANTE GENERA COMPROMISO PERO NO DESCUENTO DADO A QUE LA OBLIGACION DEL CARGUE FUE EN VIGENCIA DE OTRO CONTRATO | AN37: JAIME GUZMAN | AQ37: X | AR37: JAIME GUZMAN
A38: WORLD LEGAL CORPORATION SAS | B38: ID_007387730 | C38: 2023_5041810 | D38: 2418449 | E38: 11001310502720220027000 | G38: ORDINARIO LABORAL DE PRIMERA INSTANCIA | H38: 73082056 | I38: EUGENIO LOZANO LECOMPTE | J38: Colpensiones | K38: BOGOTA | L38: SIN FALLO | N38: SIN FALLO | P38: OK | T38: OK | V38: NO | W38: No se cargó en la plataforma ekogui la pieza procesal SENTENCIA. | X38: NO | Y38: No se cargó en la plataforma ekogui la pieza procesal SENTENCIA. | AH38: ERROR | AI38: //////No se cargó en la plataforma ekogui la pieza procesal SENTENCIA.//No se cargó en la plataforma ekogui la pieza procesal SENTENCIA.//////// | AJ38: NO PROCEDE ERROR | AK38: PROCESO SIN FALLO DE 1RA INSTANCIA, ESTA EN TRIBUNAL POR APELACION DE AUTO | AN38: JAIME GUZMAN | AQ38: X | AR38: JAIME GUZMAN
A39: VENCE SALAMANCA LAWYERS GROUP SAS | B39: ID_007496757 | C39: 2023_16712536 | D39: 2481971 | E39: 11001310504120220010000 | G39: ORDINARIO LABORAL DE PRIMERA INSTANCIA | H39: 41691019 | I39: VENTURA BARRERA DIAZ | J39: Colpensiones | K39: BOGOTA | L39: SIN FALLO | N39: SIN FALLO | P39: OK | T39: OK | V39: NO | W39: No se cargó en la plataforma ekogui la pieza procesal SENTENCIA. | AH39: ERROR | AI39: //////No se cargó en la plataforma ekogui la pieza procesal SENTENCIA.////////// | AJ39: NO PROCEDE ERROR | AK39: SENTENCIA CARGADA EN EKOGUI DENTRO DEL PERIODO DE FACTURACION EL 07/04/2026 | AM39: GENERA DESCUENTO | AN39: JAIME GUZMAN | AQ39: X | AR39: JAIME GUZMAN
A40: WORLD LEGAL CORPORATION SAS | B40: ID_007396404 | C40: 2023_5842142 | D40: 2418490 | E40: 11001310502020220037001 | G40: ORDINARIO LABORAL DE PRIMERA INSTANCIA | H40: 79355995 | I40: EDGAR FERNANDO ALONSO MASMELA | J40: Colpensiones | K40: BOGOTA | L40: DESFAVORABLE | M40: 13/03/2024 | N40: SIN FALLO | P40: OK | T40: OK | V40: OK | X40: NO | Y40: No se cargó en la plataforma ekogui la pieza procesal SENTENCIA. | AH40: ERROR | AI40: ////////No se cargó en la plataforma ekogui la pieza procesal SENTENCIA.//////// | AJ40: NO PROCEDE ERROR | AK40: LA PIEZA PROCESAL SENTENCIA ESTA CARGADA DESDE 2024/04/23 CON EL PDF LLAMADO: 11001310502020220037001.pdf | AN40: JAIME GUZMAN | AQ40: X | AR40: JAIME GUZMAN
A41: TRUJILLO POLANIA Y ASOCIADOS | B41: ID_00256791 | C41: 2016_5053164 | D41: 922917 | E41: 11001310500820150028300 | G41: EJECUTIVO LABORAL | H41: 19468151 | I41: EDGAR HERNANDO CUBIDES CRUZ | J41: COLPENSIONES | K41: BOGOTA | L41: CONTINUA CON LA EJECUCION | M41: 10/07/2017 | N41: CONTINUA CON LA EJECUCION | O41: 17/04/2018 | Z41: NO | AA41: No se cargó en la plataforma ekogui la pieza procesal DEMANDA QUE DA ORIGEN AL MANDAMIENTO DE PAGO. | AB41: NO | AC41: No se cargó en la plataforma ekogui la pieza procesal MANDAMIENTO DE PAGO. | AF41: OK | AH41: ERROR | AI41: //////////No se cargó en la plataforma ekogui la pieza procesal DEMANDA QUE DA ORIGEN AL MANDAMIENTO DE PAGO.//No se cargó en la plataforma ekogui la pieza procesal MANDAMIENTO DE PAGO.//// | AJ41: NO PROCEDE ERROR | AK41: EL CARGUE DE LA PIEZA MENCIONADA, NO SE DIO EN VIGENCIA DE LA FIRMA TRUJILLO POLANIA, SIN EMBARGO SE SOLICITA ACCESO AL EXPEDIENTE PARA DAR CORRECCION A LO SOLICITADO. (SE CARGAN TODAS LAS PIEZAS REQUERIDAS) | AN41: JAIME GUZMAN | AQ41: X | AR41: JAIME GUZMAN
A42: TRUJILLO POLANIA Y ASOCIADOS | B42: ID_00256796 | C42: 2016_5048680 | D42: 922589 | E42: 11001310500820150056500 | G42: EJECUTIVO LABORAL | H42: 17066903 | I42: MANUEL FRANCISCO TELLEZ MORENO | J42: COLPENSIONES | K42: BOGOTA | L42: CONTINUA CON LA EJECUCION | M42: 5/07/2017 | N42: SIN FALLO | Z42: NO | AA42: No se cargó en la plataforma ekogui la pieza procesal DEMANDA QUE DA ORIGEN AL MANDAMIENTO DE PAGO. | AB42: OK | AD42: NO | AE42: No se cargó en la plataforma ekogui la pieza procesal Excepciones. | AF42: OK | AH42: ERROR | AI42: //////////No se cargó en la plataforma ekogui la pieza procesal DEMANDA QUE DA ORIGEN AL MANDAMIENTO DE PAGO.////No se cargó en la plataforma ekogui la pieza procesal Excepciones. // | AJ42: NO PROCEDE ERROR | AK42: EL CARGUE DE LA PIEZA MENCIONADA, NO SE DIO EN VIGENCIA DE LA FIRMA TRUJILLO POLANIA, SIN EMBARGO SE SOLICITA ACCESO AL EXPEDIENTE PARA DAR CORRECCION A LO SOLICITADO. (SE CARGAN TODAS LAS PIEZAS REQUERIDAS) | AN42: JAIME GUZMAN | AQ42: X | AR42: JAIME GUZMAN
A43: VENCE SALAMANCA LAWYERS GROUP SAS | B43: ID_008051005 | C43: 2026_4187921 | D43: 2702346 | E43: 11001333501220230009800 | G43: ACCION DE NULIDAD Y RESTABLECIMIENTO DEL DERECHO | H43: 11280277 | I43: ARISTOBULO RAMON VEGA ALVAREZ | J43: Colpensiones | K43: BOGOTA | P43: NO | Q43: No se cargó en la plataforma ekogui la pieza procesal DEMANDA-ORDINARIA. | T43: NO | U43: No se cargó en la plataforma ekogui la pieza procesal CONTESTACION DE LA DEMANDA. | AH43: ERROR | AI43: No se cargó en la plataforma ekogui la pieza procesal DEMANDA-ORDINARIA.////No se cargó en la plataforma ekogui la pieza procesal CONTESTACION DE LA DEMANDA.//////////// | AJ43: NO PROCEDE ERROR | AK43: DEMANDA CARGADA DESDE EL 05/12/2025, CONTESTACION AUN EN TÉRMINOS | AM43: GENERA DESCUENTO | AN43: JAIME GUZMAN | AQ43: X | AR43: JAIME GUZMAN
A44: VENCE SALAMANCA LAWYERS GROUP SAS | B44: ID_00636323 | C44: 2020_7007115 | D44: 2139202 | E44: 25000234200020180250600 | G44: ACCION DE NULIDAD Y RESTABLECIMIENTO DEL DERECHO | H44: 3226980 | I44: FRANCISCO CARLOS JOSE ESCOBAR HENRIQUEZ | J44: Colpensiones | K44: BOGOTA | L44: DESFAVORABLE | M44: 28/06/2024 | N44: SIN FALLO | P44: OK | T44: NO | U44: No se cargó en la plataforma ekogui la pieza procesal CONTESTACION DE LA DEMANDA. | V44: OK | X44: NO | Y44: No se cargó en la plataforma ekogui la pieza procesal SENTENCIA. | AH44: ERROR | AI44: ////No se cargó en la plataforma ekogui la pieza procesal CONTESTACION DE LA DEMANDA.////No se cargó en la plataforma ekogui la pieza procesal SENTENCIA.//////// | AJ44: NO PROCEDE ERROR | AK44: NO SE CONTESTÓ LA DEMANDA POR LO CUAL NO EXISTE PIEZA PARA CARGAR, SENTENCIA CARGADA EN EKOGUI DENTRO DEL PERIODO DE FACTURACION EL 07/04/2026 | AM44: GENERA DESCUENTO | AN44: JAIME GUZMAN | AQ44: X | AR44: JAIME GUZMAN
A45: TABOR ASESORES LEGALES SAS | B45: ID_00497722 | C45: 2018_15096094 | D45: 1351275 | E45: 11001310501920160047100 | G45: EJECUTIVO LABORAL | H45: 2922522 | I45: JUAN ELIECER PANADERO | J45: Colpensiones | K45: BOGOTA | L45: CONTINUA CON LA EJECUCION | M45: 14/11/2019 | N45: SIN FALLO | Z45: NO | AA45: No se cargó en la plataforma ekogui la pieza procesal DEMANDA QUE DA ORIGEN AL MANDAMIENTO DE PAGO. | AB45: NO | AC45: No se cargó en la plataforma ekogui la pieza procesal MANDAMIENTO DE PAGO. | AD45: NO | AE45: No se cargó en la plataforma ekogui la pieza procesal EXCEPCIONES | AF45: OK | AH45: ERROR | AI45: //////////No se cargó en la plataforma ekogui la pieza procesal DEMANDA QUE DA ORIGEN AL MANDAMIENTO DE PAGO.//No se cargó en la plataforma ekogui la pieza procesal MANDAMIENTO DE PAGO.//No se cargó en la plataforma ekogui la pieza procesal EXCEPCIONES// | AJ45: NO PROCEDE ERROR | AK45: PROCESO CREADO POR EKOGUI AUTOMATICAMENTE, POR LO QUE LA PIEZA PROCESAL SE ENCUENTRA CARGADA EN LA ETAPA DE NOTIFICACION Y EL ARCHIVO SE DENOMINA " NOTIFICACION 11001310501920160047100.pdf" CARGADO DESDE EL 2020/05/11 | AN45: JAIME GUZMAN | AQ45: X | AR45: JAIME GUZMAN
A46: TRUJILLO POLANIA Y ASOCIADOS | B46: ID_00259158 | C46: 2016_5735368 | D46: 1172930 | E46: 11001310500920150061300 | G46: EJECUTIVO LABORAL | H46: 2355160 | I46: RAMON LOZANO TAPIERO | J46: COLPENSIONES | K46: BOGOTA | L46: SIN FALLO | N46: SIN FALLO | Z46: NO | AB46: OK | AC46: No se cargó en la plataforma ekogui la pieza procesal MANDAMIENTO DE PAGO. | AH46: ERROR | AI46: ////////////No se cargó en la plataforma ekogui la pieza procesal MANDAMIENTO DE PAGO.//// | AJ46: NO PROCEDE ERROR | AK46: EL CARGUE DE LA PIEZA MENCIONADA, NO SE DIO EN VIGENCIA DE LA FIRMA TRUJILLO POLANIA, SIN EMBARGO SE SOLICITA ACCESO AL EXPEDIENTE PARA DAR CORRECCION A LO SOLICITADO. (SE CARGAN TODAS LAS PIEZAS REQUERIDAS) | AN46: JAIME GUZMAN | AQ46: X | AR46: JAIME GUZMAN
A47: WORLD LEGAL CORPORATION SAS | B47: ID_00575105 | C47: 2019_11685676 | D47: 2071772 | E47: 11001310500720190053000 | G47: ORDINARIO LABORAL DE PRIMERA INSTANCIA | H47: 19149940 | I47: HORACIO ENRIQUE CARDENAS LINARES | J47: Colpensiones | K47: BOGOTA | L47: DESFAVORABLE | M47: 10/10/2025 | N47: SIN FALLO | P47: OK | T47: OK | V47: NO | W47: No se cargó en la plataforma ekogui la pieza procesal SENTENCIA. | AH47: ERROR | AI47: //////No se cargó en la plataforma ekogui la pieza procesal SENTENCIA.////////// | AJ47: NO PROCEDE ERROR | AK47: LA PIEZA PROCESAL ESTA CARGADA DESDE 30/03/2026 CON EL PDF DE NOMBRE: 11001310500720190053000. .pdf | AN47: JAIME GUZMAN | AQ47: X | AR47: JAIME GUZMAN
A48: TRUJILLO POLANIA Y ASOCIADOS | B48: ID_00267279 | C48: 2016_8355772 | D48: 922541 | E48: 11001310500820150021700 | G48: EJECUTIVO LABORAL | H48: 3175569 | I48: GUILLERMO PEREZ BARRERO | J48: COLPENSIONES | K48: BOGOTA | L48: CONTINUA CON LA EJECUCION | M48: 17/08/2017 | N48: SIN FALLO | Z48: NO | AA48: No se cargó en la plataforma ekogui la pieza procesal MANDAMIENTO DE PAGO. | AB48: OK | AD48: NO | AE48: No se cargó en la plataforma ekogui la pieza procesal EXCEPCIONES. | AF48: NO | AG48: No se cargó en la plataforma ekogui la pieza procesal AUTO QUE ORDENA/NO ORDENA CONTINUAR CON LA EJECUCION. | AH48: ERROR | AI48: //////////No se cargó en la plataforma ekogui la pieza procesal MANDAMIENTO DE PAGO.////No se cargó en la plataforma ekogui la pieza procesal EXCEPCIONES.//No se cargó en la plataforma ekogui la pieza procesal AUTO QUE ORDENA/NO ORDENA CONTINUAR CON LA EJECUCION. | AJ48: NO PROCEDE ERROR | AK48: EL CARGUE DE LA PIEZA MENCIONADA, NO SE DIO EN VIGENCIA DE LA FIRMA TRUJILLO POLANIA, SIN EMBARGO SE SOLICITA ACCESO AL EXPEDIENTE PARA DAR CORRECCION A LO SOLICITADO. (SE CARGAN TODAS LAS PIEZAS REQUERIDAS) | AN48: JAIME GUZMAN | AQ48: X | AR48: JAIME GUZMAN
A49: TABOR ASESORES LEGALES SAS | B49: ID_006911491 | C49: 2020_11647084 | D49: 2161944 | E49: 11001310503020190084200 | G49: ORDINARIO LABORAL DE PRIMERA INSTANCIA | H49: 43499526 | I49: ADRIANA MARIA HENAO VANEGAS | J49: Colpensiones | K49: BOGOTA | L49: DESFAVORABLE | M49: 8/05/2023 | N49: DESFAVORABLE | O49: 11/09/2024 | P49: NO | Q49: Se cargó en la plataforma ekogui la pieza procesal DEMANDA-ORDINARIA de forma incompleta. | T49: OK | V49: OK | X49: OK | AH49: ERROR | AI49: Se cargó en la plataforma ekogui la pieza procesal DEMANDA-ORDINARIA de forma incompleta.//////////////// | AJ49: NO PROCEDE ERROR | AK49: LA DEMANDA SE ENCUENTRA CARGADA COMPLETA CON 19 PAGINAS Y SE DENOMINA " 11001310503020190084200 DEMANDA.pdf" CARGADA DESDE EL 2020/11/23 | AN49: JAIME GUZMAN | AQ49: X | AR49: JAIME GUZMAN
A50: TABOR ASESORES LEGALES SAS | B50: ID_007377278 | C50: 2023_4085590 | D50: 2409728 | E50: 11001310500420220050700 | G50: ORDINARIO LABORAL DE PRIMERA INSTANCIA | H50: 51870570 | I50: SONIA RAMOS PULIDO | J50: Colpensiones | K50: BOGOTA | L50: DESFAVORABLE | M50: 10/12/2024 | N50: DESFAVORABLE | O50: 29/08/2025 | P50: OK | T50: OK | V50: OK | X50: NO | Y50: No se cargó en la plataforma ekogui la pieza procesal SENTENCIA. | AH50: ERROR | AI50: ////////No se cargó en la plataforma ekogui la pieza procesal SENTENCIA.//////// | AJ50: NO PROCEDE ERROR | AK50: LA SENTENCIA SE ENCUENTRA CARGADA DESDE EL 2025/08/30 Y EL ARCHIVO SE LLAMA " 32ActaAudiencia20241210.pdf" | AN50: JAIME GUZMAN | AQ50: X | AR50: JAIME GUZMAN
A51: TRUJILLO POLANIA Y ASOCIADOS | B51: ID_00280471 | C51: 2016_11995080 | D51: 894814 | E51: 11001310502820160048400 | G51: ORDINARIO LABORAL DE PRIMERA INSTANCIA | H51: 41745028 | I51: FLOR ALBA CHISABA DE RINCON | J51: COLPENSIONES | K51: BOGOTA | L51: FAVORABLE | M51: 20/02/2024 | N51: FAVORABLE | O51: 30/09/2024 | P51: OK | T51: NO | U51: No se cargó en la plataforma ekogui la pieza procesal CONTESTACION DE LA DEMANDA. | V51: OK | X51: OK | AH51: ERROR | AI51: ////No se cargó en la plataforma ekogui la pieza procesal CONTESTACION DE LA DEMANDA.//////////// | AJ51: NO PROCEDE ERROR | AK51: EL CARGUE DE LA PIEZA MENCIONADA, NO SE DIO EN VIGENCIA DE LA FIRMA TRUJILLO POLANIA, SIN EMBARGO SE SOLICITA ACCESO AL EXPEDIENTE PARA DAR CORRECCION A LO SOLICITADO. (SE CARGAN TODAS LAS PIEZAS REQUERIDAS) | AN51: JAIME GUZMAN | AQ51: X | AR51: JAIME GUZMAN
A52: TRUJILLO POLANIA Y ASOCIADOS | B52: ID_00285471 | C52: 2016_12875488 | D52: 935203 | E52: 11001310500920160053700 | G52: ORDINARIO LABORAL DE PRIMERA INSTANCIA | H52: 79396215 | I52: VICTOR HUGO MARTINEZ HERRERA | J52: COLPENSIONES | K52: BOGOTA | L52: FAVORABLE | M52: 9/12/2025 | N52: SIN FALLO | P52: SI | T52: NO | U52: Se cargó en la plataforma ekogui la pieza procesal CONTESTACION DE LA DEMANDA, sin sello de radicación ante despacho judicial. | V52: SI | AH52: ERROR | AI52: ////Se cargó en la plataforma ekogui la pieza procesal CONTESTACION DE LA DEMANDA, sin sello de radicación ante despacho judicial.//////////// | AJ52: NO PROCEDE ERROR | AK52: EL CARGUE DE LA PIEZA MENCIONADA, NO SE DIO EN VIGENCIA DE LA FIRMA TRUJILLO POLANIA, SIN EMBARGO SE SOLICITA ACCESO AL EXPEDIENTE PARA DAR CORRECCION A LO SOLICITADO. (SE CARGAN TODAS LAS PIEZAS REQUERIDAS) | AN52: LAURA RODRIGUEZ | AQ52: X | AR52: LAURA RODRIGUEZ
A53: WORLD LEGAL CORPORATION SAS | B53: ID_007107853 | C53: 2021_13364928 | D53: 2247861 | E53: 11001310500720210033900 | G53: ORDINARIO LABORAL DE PRIMERA INSTANCIA | H53: 79253608 | I53: MANUEL GUILLERMO MALAGON AREVALO | J53: Colpensiones | K53: BOGOTA | L53: DESFAVORABLE | M53: 12/09/2023 | N53: SIN FALLO | P53: SI | T53: SI | V53: NO | W53: Se cargó en la plataforma ekogui la pieza procesal SENTENCIA, pero es un comodín, pantallazo, o es otra pieza procesal. | AH53: ERROR | AI53: //////Se cargó en la plataforma ekogui la pieza procesal SENTENCIA, pero es un comodín, pantallazo, o es otra pieza procesal.////////// | AJ53: NO PROCEDE ERROR | AK53: EL ACTA REQUERIDA ES DE FECHA 19/02/2023, FECHA PARA LA CUAL LA FIRMA NO EJERCIA DEFENSA PARA LA ENTIDAD, POR LO TANTO GENERA COMPROMISO PERO NO DESCUENTO YA QUE LA OBLIGACION DEL CARGUE SE GENERO EN VIGENCIA DE OTRO CONTRATO | AN53: LAURA RODRIGUEZ | AQ53: X | AR53: LAURA RODRIGUEZ
A54: TRUJILLO POLANIA Y ASOCIADOS | B54: ID_00293085 | C54: 2016_14433100 | D54: 972766 | E54: 11001310500920150031200 | G54: EJECUTIVO LABORAL | H54: 6075087 | I54: ROMULO CAMPO VICTORIA | J54: COLPENSIONES | K54: BOGOTA | L54: CONTINUA CON LA EJECUCION | M54: 14/08/2017 | N54: SIN FALLO | Z54: NO | AA54: Se cargó en la plataforma ekogui la pieza procesal DEMANDA QUE DA ORIGEN AL MANDAMIENTO DE PAGO, pero es un comodín, pantallazo, o es otra pieza procesal. | AB54: SI | AD54: NO | AE54: No se cargó en la plataforma ekogui la pieza procesal EXCEPCIONES_CONTESTACION | AF54: SI | AH54: ERROR | AI54: //////////Se cargó en la plataforma ekogui la pieza procesal DEMANDA QUE DA ORIGEN AL MANDAMIENTO DE PAGO, pero es un comodín, pantallazo, o es otra pieza procesal.////No se cargó en la plataforma ekogui la pieza procesal EXCEPCIONES_CONTESTACION// | AJ54: NO PROCEDE ERROR | AK54: EL CARGUE DE LA PIEZA MENCIONADA, NO SE DIO EN VIGENCIA DE LA FIRMA TRUJILLO POLANIA, SIN EMBARGO SE SOLICITA ACCESO AL EXPEDIENTE PARA DAR CORRECCION A LO SOLICITADO. (SE CARGAN TODAS LAS PIEZAS REQUERIDAS) | AN54: LAURA RODRIGUEZ | AQ54: X | AR54: LAURA RODRIGUEZ
A55: TRUJILLO POLANIA Y ASOCIADOS | B55: ID_00293097 | C55: 2016_14432529 | D55: 1023907 | E55: 11001310500920150067600 | G55: EJECUTIVO LABORAL | H55: 41601792 | I55: ANADELINA FONTECHA VELASCO | J55: COLPENSIONES | K55: BOGOTA | L55: CONTINUA CON LA EJECUCION | M55: 24/01/2018 | N55: SIN FALLO | Z55: NO | AA55: Se cargó en la plataforma ekogui la pieza procesal DEMANDA QUE DA ORIGEN AL MANDAMIENTO DE PAGO, pero es un comodín, pantallazo, o es otra pieza procesal. | AB55: SI | AD55: NO | AE55: No se cargó en la plataforma ekogui la pieza procesal EXCEPCIONES_CONTESTACION | AF55: SI | AH55: ERROR | AI55: //////////Se cargó en la plataforma ekogui la pieza procesal DEMANDA QUE DA ORIGEN AL MANDAMIENTO DE PAGO, pero es un comodín, pantallazo, o es otra pieza procesal.////No se cargó en la plataforma ekogui la pieza procesal EXCEPCIONES_CONTESTACION// | AJ55: NO PROCEDE ERROR | AK55: EL CARGUE DE LA PIEZA MENCIONADA, NO SE DIO EN VIGENCIA DE LA FIRMA TRUJILLO POLANIA, SIN EMBARGO SE SOLICITA ACCESO AL EXPEDIENTE PARA DAR CORRECCION A LO SOLICITADO. (SE CARGAN TODAS LAS PIEZAS REQUERIDAS) | AN55: LAURA RODRIGUEZ | AQ55: X | AR55: LAURA RODRIGUEZ
A56: TRUJILLO POLANIA Y ASOCIADOS | B56: ID_00294336 | C56: 2013_3759315 | D56: 2121046 | E56: 11001310500920010073500 | G56: EJECUTIVO LABORAL | H56: 35320393 | I56: MARIA CRISTINA FERNANDEZ DE CUBILLOS | J56: COLPENSIONES | K56: BOGOTA | L56: CONTINUA CON LA EJECUCION | M56: 5/03/2020 | N56: SIN FALLO | Z56: NO | AA56: Se cargó en la plataforma ekogui la pieza procesal DEMANDA QUE DA ORIGEN AL MANDAMIENTO DE PAGO, pero es un comodín, pantallazo, o es otra pieza procesal. | AB56: SI | AD56: NO | AE56: No se cargó en la plataforma ekogui la pieza procesal EXCEPCIONES_CONTESTACION | AF56: SI | AH56: ERROR | AI56: //////////Se cargó en la plataforma ekogui la pieza procesal DEMANDA QUE DA ORIGEN AL MANDAMIENTO DE PAGO, pero es un comodín, pantallazo, o es otra pieza procesal.////No se cargó en la plataforma ekogui la pieza procesal EXCEPCIONES_CONTESTACION// | AJ56: NO PROCEDE ERROR | AK56: EL CARGUE DE LA PIEZA MENCIONADA, NO SE DIO EN VIGENCIA DE LA FIRMA TRUJILLO POLANIA, SIN EMBARGO SE SOLICITA ACCESO AL EXPEDIENTE PARA DAR CORRECCION A LO SOLICITADO. (SE CARGAN TODAS LAS PIEZAS REQUERIDAS) | AN56: LAURA RODRIGUEZ | AQ56: X | AR56: LAURA RODRIGUEZ
A57: TRUJILLO POLANIA Y ASOCIADOS | B57: ID_00307281 | C57: 2017_1274709 | D57: 1164522 | E57: 11001310501620160009700 | G57: ORDINARIO LABORAL DE PRIMERA INSTANCIA | H57: 8020076706 | I57: ELECTRIFICADORA DEL CARIBE S.A. E.S.P. | J57: COLPENSIONES | K57: BOGOTA | L57: DESFAVORABLE | M57: 18/10/2024 | N57: SIN FALLO | P57: SI | T57: NO | U57: Se cargó en la plataforma ekogui la pieza procesal CONTESTACION DE LA DEMANDA, pero en formato Word, sin firmas y sello. | V57: SI | AH57: ERROR | AI57: ////Se cargó en la plataforma ekogui la pieza procesal CONTESTACION DE LA DEMANDA, pero en formato Word, sin firmas y sello.//////////// | AJ57: NO PROCEDE ERROR | AK57: EL CARGUE DE LA PIEZA MENCIONADA, NO SE DIO EN VIGENCIA DE LA FIRMA TRUJILLO POLANIA, SIN EMBARGO SE SOLICITA ACCESO AL EXPEDIENTE PARA DAR CORRECCION A LO SOLICITADO. | AN57: LAURA RODRIGUEZ | AQ57: X | AR57: LAURA RODRIGUEZ
A58: TRUJILLO POLANIA Y ASOCIADOS | B58: ID_00309786 | C58: 2017_1841495 | D58: 976356 | E58: 11001310502820170003000 | G58: ORDINARIO LABORAL DE PRIMERA INSTANCIA | H58: 15916320 | I58: HECTOR DARIO TRUJILLO CORREA | J58: COLPENSIONES | K58: BOGOTA | L58: DESFAVORABLE | M58: 24/11/2022 | N58: DESFAVORABLE | O58: 30/09/2024 | P58: SI | R58: SI | T58: NO | U58: No se cargó en la plataforma ekogui la pieza procesal CONTESTACION DE LA DEMANDA. | V58: SI | X58: SI | AH58: ERROR | AI58: ////No se cargó en la plataforma ekogui la pieza procesal CONTESTACION DE LA DEMANDA.//////////// | AJ58: NO PROCEDE ERROR | AK58: EL CARGUE DE LA PIEZA MENCIONADA, NO SE DIO EN VIGENCIA DE LA FIRMA TRUJILLO POLANIA, SIN EMBARGO SE SOLICITA ACCESO AL EXPEDIENTE PARA DAR CORRECCION A LO SOLICITADO. | AN58: LAURA RODRIGUEZ | AQ58: X | AR58: LAURA RODRIGUEZ
A59: TRUJILLO POLANIA Y ASOCIADOS | B59: ID_00317396 | C59: 2017_2694378 | D59: 987315 | E59: 11001310503920160090100 | G59: ORDINARIO LABORAL DE PRIMERA INSTANCIA | H59: 19145928 | I59: ELIECER BALLESTEROS | J59: COLPENSIONES | K59: BOGOTA | L59: DESFAVORABLE | M59: 8/02/2024 | N59: SIN FALLO | P59: SI | T59: NO | U59: No se cargó en la plataforma ekogui la pieza procesal CONTESTACION DE LA DEMANDA. | V59: SI | AH59: ERROR | AI59: ////No se cargó en la plataforma ekogui la pieza procesal CONTESTACION DE LA DEMANDA.//////////// | AJ59: NO PROCEDE ERROR | AK59: EL CARGUE DE LA PIEZA MENCIONADA, NO SE DIO EN VIGENCIA DE LA FIRMA TRUJILLO POLANIA, SIN EMBARGO SE SOLICITA ACCESO AL EXPEDIENTE PARA DAR CORRECCION A LO SOLICITADO. (SE CARGAN TODAS LAS PIEZAS REQUERIDAS) | AN59: LAURA RODRIGUEZ | AQ59: X | AR59: LAURA RODRIGUEZ
A60: TRUJILLO POLANIA Y ASOCIADOS | B60: ID_00324515 | C60: 2017_4085575 | D60: 1216873 | E60: 11001310502820160005000 | G60: EJECUTIVO LABORAL | H60: 41536963 | I60: SANDRA SANGAMA DE SANTOS | J60: COLPENSIONES | K60: BOGOTA | L60: CONTINUA CON LA EJECUCION | M60: 9/05/2018 | N60: SIN FALLO | Z60: NO | AA60: No se cargó en la plataforma ekogui la pieza procesal DEMANDA-ORDINARIA. | AB60: SI | AD60: NO | AE60: No se cargó en la plataforma ekogui la pieza procesal EXCEPCIONES_CONTESTACION | AF60: NO | AG60: No se cargó en la plataforma ekogui la pieza procesal AUTO QUE ORDENA/NO ORDENA CONTINUAR CON LA EJECUCION. | AH60: ERROR | AI60: //////////No se cargó en la plataforma ekogui la pieza procesal DEMANDA-ORDINARIA.////No se cargó en la plataforma ekogui la pieza procesal EXCEPCIONES_CONTESTACION//No se cargó en la plataforma ekogui la pieza procesal AUTO QUE ORDENA/NO ORDENA CONTINUAR CON LA EJECUCION. | AJ60: NO PROCEDE ERROR | AK60: EL CARGUE DE LA PIEZA MENCIONADA, NO SE DIO EN VIGENCIA DE LA FIRMA TRUJILLO POLANIA, SIN EMBARGO SE SOLICITA ACCESO AL EXPEDIENTE PARA DAR CORRECCION A LO SOLICITADO. | AN60: LAURA RODRIGUEZ | AQ60: X | AR60: LAURA RODRIGUEZ
A61: TRUJILLO POLANIA Y ASOCIADOS | B61: ID_00324764 | C61: 2017_4128085 | D61: 1000179 | E61: 11001310501020170008600 | G61: ORDINARIO LABORAL DE PRIMERA INSTANCIA | H61: 6751006 | I61: MARCO FIDEL OTALORA IBAÑEZ | J61: COLPENSIONES | K61: BOGOTA | L61: DESFAVORABLE | M61: 23/09/2020 | N61: DESFAVORABLE | O61: 29/11/2024 | P61: SI | T61: NO | U61: Se cargó en la plataforma ekogui la pieza procesal CONTESTACION DE LA DEMANDA, pero en formato Word, sin firmas y sello. | V61: SI | X61: SI | AH61: ERROR | AI61: ////Se cargó en la plataforma ekogui la pieza procesal CONTESTACION DE LA DEMANDA, pero en formato Word, sin firmas y sello.//////////// | AJ61: NO PROCEDE ERROR | AK61: EL CARGUE DE LA PIEZA MENCIONADA, NO SE DIO EN VIGENCIA DE LA FIRMA TRUJILLO POLANIA, SIN EMBARGO SE SOLICITA ACCESO AL EXPEDIENTE PARA DAR CORRECCION A LO SOLICITADO. (SE CARGAN TODAS LAS PIEZAS REQUERIDAS) | AN61: LAURA RODRIGUEZ | AQ61: X | AR61: LAURA RODRIGUEZ
A62: TRUJILLO POLANIA Y ASOCIADOS | B62: ID_00331033 | C62: 2017_5689504 | D62: 1024397 | E62: 11001310500920160030100 | G62: EJECUTIVO LABORAL | H62: 17161643 | I62: ANTONIO MARIA RUIZ CASASBUENAS | J62: COLPENSIONES | K62: BOGOTA | L62: CONTINUA CON LA EJECUCION | M62: 24/01/2018 | N62: SIN FALLO | Z62: NO | AA62: No se cargó en la plataforma ekogui la pieza procesal DEMANDA QUE DA ORIGEN AL MANDAMIENTO DE PAGO. | AB62: SI | AD62: NO | AE62: No se cargó en la plataforma ekogui la pieza procesal EXCEPCIONES_CONTESTACION | AF62: NO | AG62: No se cargó en la plataforma ekogui la pieza procesal AUTO QUE ORDENA/NO ORDENA CONTINUAR CON LA EJECUCION. | AH62: ERROR | AI62: //////////No se cargó en la plataforma ekogui la pieza procesal DEMANDA QUE DA ORIGEN AL MANDAMIENTO DE PAGO.////No se cargó en la plataforma ekogui la pieza procesal EXCEPCIONES_CONTESTACION//No se cargó en la plataforma ekogui la pieza procesal AUTO QUE ORDENA/NO ORDENA CONTINUAR CON LA EJECUCION. | AJ62: NO PROCEDE ERROR | AK62: EL CARGUE DE LA PIEZA MENCIONADA, NO SE DIO EN VIGENCIA DE LA FIRMA TRUJILLO POLANIA, SIN EMBARGO SE SOLICITA ACCESO AL EXPEDIENTE PARA DAR CORRECCION A LO SOLICITADO. (SE CARGAN TODAS LAS PIEZAS REQUERIDAS) | AN62: LAURA RODRIGUEZ | AQ62: X | AR62: LAURA RODRIGUEZ
A63: TRUJILLO POLANIA Y ASOCIADOS | B63: ID_00334605 | C63: 2017_6483364 | D63: 1167985 | E63: 11001310500820150093200 | G63: EJECUTIVO LABORAL | H63: 94430 | I63: PEDRO PABLO MORALES RUBIO | J63: COLPENSIONES | K63: BOGOTA | L63: CONTINUA CON LA EJECUCION | M63: 18/04/2018 | N63: SIN FALLO | Z63: NO | AA63: No se cargó en la plataforma ekogui la pieza procesal DEMANDA QUE DA ORIGEN AL MANDAMIENTO DE PAGO. | AB63: SI | AD63: NO | AE63: No se cargó en la plataforma ekogui la pieza procesal EXCEPCIONES_CONTESTACION | AF63: SI | AH63: ERROR | AI63: //////////No se cargó en la plataforma ekogui la pieza procesal DEMANDA QUE DA ORIGEN AL MANDAMIENTO DE PAGO.////No se cargó en la plataforma ekogui la pieza procesal EXCEPCIONES_CONTESTACION// | AJ63: NO PROCEDE ERROR | AK63: EL CARGUE DE LA PIEZA MENCIONADA, NO SE DIO EN VIGENCIA DE LA FIRMA TRUJILLO POLANIA, SIN EMBARGO SE SOLICITA ACCESO AL EXPEDIENTE PARA DAR CORRECCION A LO SOLICITADO. (SE CARGAN TODAS LAS PIEZAS REQUERIDAS) | AN63: LAURA RODRIGUEZ | AQ63: X | AR63: LAURA RODRIGUEZ
A64: TRUJILLO POLANIA Y ASOCIADOS | B64: ID_00340785 | C64: 2017_7382806 | D64: 1167881 | E64: 11001310500820160063200 | G64: EJECUTIVO LABORAL | H64: 31643047 | I64: ADRIANA VASQUEZ TORRES | J64: Colpensiones | K64: BOGOTA | L64: CONTINUA CON LA EJECUCION | M64: 8/06/2018 | N64: SIN FALLO | Z64: NO | AA64: No se cargó en la plataforma ekogui la pieza procesal DEMANDA QUE DA ORIGEN AL MANDAMIENTO DE PAGO. | AB64: SI | AD64: NO | AE64: No se cargó en la plataforma ekogui la pieza procesal EXCEPCIONES_CONTESTACION | AF64: NO | AG64: No se cargó en la plataforma ekogui la pieza procesal AUTO QUE ORDENA/NO ORDENA CONTINUAR CON LA EJECUCION. | AH64: ERROR | AI64: //////////No se cargó en la plataforma ekogui la pieza procesal DEMANDA QUE DA ORIGEN AL MANDAMIENTO DE PAGO.////No se cargó en la plataforma ekogui la pieza procesal EXCEPCIONES_CONTESTACION//No se cargó en la plataforma ekogui la pieza procesal AUTO QUE ORDENA/NO ORDENA CONTINUAR CON LA EJECUCION. | AJ64: NO PROCEDE ERROR | AK64: EL CARGUE DE LA PIEZA MENCIONADA, NO SE DIO EN VIGENCIA DE LA FIRMA TRUJILLO POLANIA, SIN EMBARGO SE SOLICITA ACCESO AL EXPEDIENTE PARA DAR CORRECCION A LO SOLICITADO. (SE CARGAN TODAS LAS PIEZAS REQUERIDAS) | AN64: LAURA RODRIGUEZ | AQ64: X | AR64: LAURA RODRIGUEZ
A65: TRUJILLO POLANIA Y ASOCIADOS | B65: ID_00346314 | C65: 2017_8091522 | D65: 1193246 | E65: 11001310500920150108300 | G65: EJECUTIVO LABORAL | H65: 2863240 | I65: RAMIRO RUIZ CASTIBLANCO | J65: Colpensiones | K65: BOGOTA | L65: CONTINUA CON LA EJECUCION | M65: 18/05/2018 | N65: SIN FALLO | Z65: NO | AA65: No se cargó en la plataforma ekogui la pieza procesal DEMANDA QUE DA ORIGEN AL MANDAMIENTO DE PAGO. | AB65: SI | AD65: NO | AE65: No se cargó en la plataforma ekogui la pieza procesal EXCEPCIONES_CONTESTACION | AF65: SI | AH65: ERROR | AI65: //////////No se cargó en la plataforma ekogui la pieza procesal DEMANDA QUE DA ORIGEN AL MANDAMIENTO DE PAGO.////No se cargó en la plataforma ekogui la pieza procesal EXCEPCIONES_CONTESTACION// | AJ65: NO PROCEDE ERROR | AK65: EL CARGUE DE LA PIEZA MENCIONADA, NO SE DIO EN VIGENCIA DE LA FIRMA TRUJILLO POLANIA, SIN EMBARGO SE SOLICITA ACCESO AL EXPEDIENTE PARA DAR CORRECCION A LO SOLICITADO. (SE CARGAN TODAS LAS PIEZAS REQUERIDAS) | AN65: LAURA RODRIGUEZ | AQ65: X | AR65: LAURA RODRIGUEZ
A66: JURISCOL ABOGADOS SAS | B66: ID_007975071 | C66: 2025_23871811 | D66: 2695041 | E66: 11001310500520251016400 | G66: EJECUTIVO LABORAL | H66: 19247632 | I66: GERMAN ARTURO MELENDEZ ACUÑA | J66: Colpensiones | K66: BOGOTA | L66: SIN FALLO | N66: SIN FALLO | Z66: NO | AA66: Se cargó en la plataforma ekogui la pieza procesal DEMANDA-ORDINARIA, pero es un comodín, pantallazo, o es otra pieza procesal. | AB66: SI | AD66: SI | AH66: ERROR | AI66: //////////Se cargó en la plataforma ekogui la pieza procesal DEMANDA-ORDINARIA, pero es un comodín, pantallazo, o es otra pieza procesal.////// | AJ66: NO PROCEDE ERROR | AK66: LA DEMANDA SE ENCUENTRA DEBIDAMENTE CARGADA DESDE EL 30/03/2026 Y CORRESPONDE A LAS PARTES DEL PROCESO | AN66: MAGDA CUARTAS | AQ66: X | AR66: MAGDA CUARTAS
A67: WORLD LEGAL CORPORATION SAS | B67: ID_007528684 | C67: 2023_19307747 | D67: 2497579 | E67: 11001310503320210017600 | G67: EJECUTIVO LABORAL | H67: 41429929 | I67: ANA LUCIA PACHON DE GONZALEZ | J67: Colpensiones | K67: BOGOTA | L67: CONTINUA CON LA EJECUCION | M67: 4/10/2023 | N67: SIN FALLO | Z67: NO | AA67: Se cargó en la plataforma ekogui la pieza procesal MANDAMIENTO DE PAGO, pero es un comodín, pantallazo, o es otra pieza procesal. | AB67: SI | AF67: SI | AH67: ERROR | AI67: //////////Se cargó en la plataforma ekogui la pieza procesal MANDAMIENTO DE PAGO, pero es un comodín, pantallazo, o es otra pieza procesal.////// | AJ67: NO PROCEDE ERROR | AK67: EL MANDAMIENTO DE PAGO ESTA CARGADO DESDE 30/11/2023 CON PDF DE NOMBRE: 11001310503320210017600 - MANDAMIENTO.pdf | AN67: MAGDA CUARTAS | AQ67: X | AR67: MAGDA CUARTAS
A68: TRUJILLO POLANIA Y ASOCIADOS | B68: ID_00349793 | C68: 2017_8554096 | D68: 1194233 | E68: 11001310500820170025400 | G68: EJECUTIVO LABORAL | H68: 35400931 | I68: MARIA EDILMA MARTINEZ MARTINEZ | J68: Colpensiones | K68: BOGOTA | L68: CONTINUA CON LA EJECUCION | M68: 18/04/2018 | N68: SIN FALLO | Z68: NO | AA68: Se cargó en la plataforma ekogui la pieza procesal DEMANDA QUE DA ORIGEN AL MANDAMIENTO DE PAGO, pero es un comodín, pantallazo, o es otra pieza procesal. | AB68: SI | AD68: NO | AE68: No se cargó en la plataforma ekogui la pieza procesal EXCEPCIONES-CONTESTACION AL MANDAMIENTO DE PAGO. | AF68: SI | AH68: ERROR | AI68: //////////Se cargó en la plataforma ekogui la pieza procesal DEMANDA QUE DA ORIGEN AL MANDAMIENTO DE PAGO, pero es un comodín, pantallazo, o es otra pieza procesal.////No se cargó en la plataforma ekogui la pieza procesal EXCEPCIONES-CONTESTACION AL MANDAMIENTO DE PAGO.// | AJ68: NO PROCEDE ERROR | AK68: EL CARGUE DE LA PIEZA MENCIONADA, NO SE DIO EN VIGENCIA DE LA FIRMA TRUJILLO POLANIA, SIN EMBARGO SE SOLICITA ACCESO AL EXPEDIENTE PARA DAR CORRECCION A LO SOLICITADO. (SE CARGAN TODAS LAS PIEZAS REQUERIDAS) | AN68: MAGDA CUARTAS | AQ68: X | AR68: MAGDA CUARTAS
A69: WORLD LEGAL CORPORATION SAS | B69: ID_007661891 | C69: 2024_13519112 | D69: 2555541 | E69: 11001310503520240006700 | G69: ORDINARIO LABORAL DE PRIMERA INSTANCIA | H69: 46357422 | I69: ROSA OMAIRA ORDUZ RODRIGUEZ | J69: Colpensiones | K69: BOGOTA | L69: SIN FALLO | N69: SIN FALLO | P69: SI | T69: SI | V69: NO | W69: No se cargó en la plataforma ekogui la pieza procesal SENTENCIA. | X69: NO | Y69: No se cargó en la plataforma ekogui la pieza procesal SENTENCIA. | AH69: ERROR | AI69: //////No se cargó en la plataforma ekogui la pieza procesal SENTENCIA.//No se cargó en la plataforma ekogui la pieza procesal SENTENCIA.//////// | AJ69: NO PROCEDE ERROR | AK69: LA PIEZA PROCESAL ESTA CARGADA DESDE: 2026/03/30 - SENTENCIA - 11001310503520240006700-55ACTAAUDIENCIAART80.pdf | AN69: MAGDA CUARTAS | AQ69: X | AR69: MAGDA CUARTAS
A70: TRUJILLO POLANIA Y ASOCIADOS | B70: ID_00359537 | C70: 2017_9676655 | D70: 1072306 | E70: 11001310500920170034800 | G70: EJECUTIVO LABORAL | H70: 19118274 | I70: JAIME OSWALDO SOSSA | J70: Colpensiones | K70: BOGOTA | L70: CONTINUA CON LA EJECUCION | M70: 8/06/2018 | N70: SIN FALLO | Z70: SI | AB70: NO | AC70: No se cargó en la plataforma ekogui la pieza procesal MANDAMIENTO DE PAGO. | AD70: NO | AE70: No se cargó en la plataforma ekogui la pieza procesal EXCEPCIONES-CONTESTACION AL MANDAMIENTO DE PAGO. | AF70: NO | AG70: No se cargó en la plataforma ekogui la pieza procesal AUTO QUE ORDENA/NO ORDENA CONTINUAR CON LA EJECUCION. | AH70: ERROR | AI70: ////////////No se cargó en la plataforma ekogui la pieza procesal MANDAMIENTO DE PAGO.//No se cargó en la plataforma ekogui la pieza procesal EXCEPCIONES-CONTESTACION AL MANDAMIENTO DE PAGO.//No se cargó en la plataforma ekogui la pieza procesal AUTO QUE ORDENA/NO ORDENA CONTINUAR CON LA EJECUCION. | AJ70: NO PROCEDE ERROR | AK70: EL CARGUE DE LA PIEZA MENCIONADA, NO SE DIO EN VIGENCIA DE LA FIRMA TRUJILLO POLANIA, SIN EMBARGO SE SOLICITA ACCESO AL EXPEDIENTE PARA DAR CORRECCION A LO SOLICITADO. (SE CARGAN TODAS LAS PIEZAS REQUERIDAS) | AN70: MAGDA CUARTAS | AQ70: X | AR70: MAGDA CUARTAS
A71: WORLD LEGAL CORPORATION SAS | B71: ID_007014002 | C71: 2021_6392931 | D71: 2206764 | E71: 11001310502720200020000 | G71: ORDINARIO LABORAL DE PRIMERA INSTANCIA | H71: 13950816 | I71: LUIS ALBERTO MORALES LESMES | J71: Colpensiones | K71: BOGOTA | L71: DESFAVORABLE | M71: 30/04/2024 | N71: SIN FALLO | P71: SI | R71: SI | T71: SI | V71: SI | X71: NO | Y71: No se cargó en la plataforma ekogui la pieza procesal DEMANDA QUE DA ORIGEN AL MANDAMIENTO DE PAGO. | AH71: ERROR | AI71: ////////No se cargó en la plataforma ekogui la pieza procesal DEMANDA QUE DA ORIGEN AL MANDAMIENTO DE PAGO.//////// | AJ71: NO PROCEDE ERROR | AK71: EL PROCESO CORRESPONDE A UN ORDINARIO NO EJECUTIVO, POR LO TANTO LA PIEZA SOLICITADA NO CORRESPONDE AL PROCESO | AN71: MAGDA CUARTAS | AQ71: X | AR71: MAGDA CUARTAS
A72: TRUJILLO POLANIA Y ASOCIADOS | B72: ID_00368742 | C72: 2017_10702294 | D72: 1084373 | E72: 11001310501420170045100 | G72: EJECUTIVO LABORAL | H72: 1032467415 | I72: LUISA FERNANDA ARCHILA CELY | J72: Colpensiones | K72: BOGOTA | L72: CONTINUA CON LA EJECUCION | M72: 4/09/2017 | N72: SIN FALLO | Z72: SI | AB72: NO | AC72: No se cargó en la plataforma ekogui la pieza procesal MANDAMIENTO DE PAGO. | AD72: SI | AF72: SI | AH72: ERROR | AI72: ////////////No se cargó en la plataforma ekogui la pieza procesal MANDAMIENTO DE PAGO.//// | AJ72: NO PROCEDE ERROR | AK72: EL CARGUE DE LA PIEZA MENCIONADA, NO SE DIO EN VIGENCIA DE LA FIRMA TRUJILLO POLANIA, SIN EMBARGO SE SOLICITA ACCESO AL EXPEDIENTE PARA DAR CORRECCION A LO SOLICITADO. (SE CARGAN TODAS LAS PIEZAS REQUERIDAS) | AN72: MAGDA CUARTAS | AQ72: X | AR72: MAGDA CUARTAS
A73: TRUJILLO POLANIA Y ASOCIADOS | B73: ID_00378895 | C73: 2017_11790620 | D73: 1101220 | E73: 11001310500920170031100 | G73: EJECUTIVO LABORAL | H73: 16468352 | I73: SEGUNDO CELESTINO RODRIGUEZ ORTIZ | J73: Colpensiones | K73: BOGOTA | L73: CONTINUA CON LA EJECUCION | M73: 5/06/2018 | N73: SIN FALLO | Z73: SI | AB73: NO | AC73: No se cargó en la plataforma ekogui la pieza procesal MANDAMIENTO DE PAGO. | AD73: NO | AE73: No se cargó en la plataforma ekogui la pieza procesal EXCEPCIONES-CONTESTACION AL MANDAMIENTO DE PAGO. | AF73: SI | AH73: ERROR | AI73: ////////////No se cargó en la plataforma ekogui la pieza procesal MANDAMIENTO DE PAGO.//No se cargó en la plataforma ekogui la pieza procesal EXCEPCIONES-CONTESTACION AL MANDAMIENTO DE PAGO.// | AJ73: NO PROCEDE ERROR | AK73: EL CARGUE DE LA PIEZA MENCIONADA, NO SE DIO EN VIGENCIA DE LA FIRMA TRUJILLO POLANIA, SIN EMBARGO SE SOLICITA ACCESO AL EXPEDIENTE PARA DAR CORRECCION A LO SOLICITADO. (SE CARGAN TODAS LAS PIEZAS REQUERIDAS) | AN73: MAGDA CUARTAS | AQ73: X | AR73: MAGDA CUARTAS
A74: TRUJILLO POLANIA Y ASOCIADOS | B74: ID_00386761 | C74: 2017_12669609 | D74: 1113557 | E74: 11001310500920170037300 | G74: EJECUTIVO LABORAL | H74: 28575062 | I74: LUZ DARY BOLAÑOS LUNA | J74: Colpensiones | K74: BOGOTA | L74: CONTINUA CON LA EJECUCION | M74: 1/08/2018 | N74: SIN FALLO | Z74: SI | AB74: NO | AC74: No se cargó en la plataforma ekogui la pieza procesal MANDAMIENTO DE PAGO. | AD74: NO | AE74: No se cargó en la plataforma ekogui la pieza procesal EXCEPCIONES-CONTESTACION AL MANDAMIENTO DE PAGO. | AF74: NO | AG74: Se cargó en la plataforma ekogui la pieza procesal AUTO QUE ORDENA/NO ORDENA CONTINUAR CON LA EJECUCION, pero es un comodín, pantallazo, o es otra pieza procesal. | AH74: ERROR | AI74: ////////////No se cargó en la plataforma ekogui la pieza procesal MANDAMIENTO DE PAGO.//No se cargó en la plataforma ekogui la pieza procesal EXCEPCIONES-CONTESTACION AL MANDAMIENTO DE PAGO.//Se cargó en la plataforma ekogui la pieza procesal AUTO QUE ORDENA/NO ORDENA CONTINUAR CON LA EJECUCION, pero es un comodín, pantallazo, o es otra pieza procesal. | AJ74: NO PROCEDE ERROR | AK74: EL CARGUE DE LA PIEZA MENCIONADA, NO SE DIO EN VIGENCIA DE LA FIRMA TRUJILLO POLANIA, SIN EMBARGO SE SOLICITA ACCESO AL EXPEDIENTE PARA DAR CORRECCION A LO SOLICITADO. (SE CARGAN TODAS LAS PIEZAS REQUERIDAS) | AN74: MAGDA CUARTAS | AQ74: X | AR74: MAGDA CUARTAS
A75: TRUJILLO POLANIA Y ASOCIADOS | B75: ID_00393615 | C75: 2018_405062 | D75: 1138709 | E75: 11001310500820170040600 | G75: ORDINARIO LABORAL DE PRIMERA INSTANCIA | H75: 210827 | I75: JAIME CHOCONTA GOMEZ | J75: Colpensiones | K75: BOGOTA | L75: DESFAVORABLE | M75: 2/05/2024 | N75: SIN FALLO | P75: NO | Q75: Se cargó en la plataforma ekogui la pieza procesal DEMANDA-ORDINARIA, pero no corresponde al proceso actual. | T75: SI | V75: NO | W75: No se cargó en la plataforma ekogui la pieza procesal SENTENCIA. | AH75: ERROR | AI75: Se cargó en la plataforma ekogui la pieza procesal DEMANDA-ORDINARIA, pero no corresponde al proceso actual.//////No se cargó en la plataforma ekogui la pieza procesal SENTENCIA.////////// | AJ75: NO PROCEDE ERROR | AK75: EL CARGUE DE LA PIEZA MENCIONADA, NO SE DIO EN VIGENCIA DE LA FIRMA TRUJILLO POLANIA, SIN EMBARGO SE SOLICITA ACCESO AL EXPEDIENTE PARA DAR CORRECCION A LO SOLICITADO. (SE CARGAN TODAS LAS PIEZAS REQUERIDAS) | AN75: MAGDA CUARTAS | AQ75: X | AR75: MAGDA CUARTAS
A76: TRUJILLO POLANIA Y ASOCIADOS | B76: ID_00393666 | C76: 2018_403827 | D76: 2170282 | E76: 11001310500820160056700 | G76: EJECUTIVO LABORAL | H76: 41572549 | I76: GILMA DEL CARMEN DIAZ CHAPARRO | J76: Colpensiones | K76: BOGOTA | L76: CONTINUA CON LA EJECUCION | M76: 7/05/2018 | N76: SIN FALLO | Z76: NO | AA76: Se cargó en la plataforma ekogui la pieza procesal DEMANDA QUE DA ORIGEN AL MANDAMIENTO DE PAGO, pero es un comodín, pantallazo, o es otra pieza procesal. | AB76: SI | AD76: NO | AE76: No se cargó en la plataforma ekogui la pieza procesal EXCEPCIONES-CONTESTACION AL MANDAMIENTO DE PAGO. | AF76: SI | AH76: ERROR | AI76: //////////Se cargó en la plataforma ekogui la pieza procesal DEMANDA QUE DA ORIGEN AL MANDAMIENTO DE PAGO, pero es un comodín, pantallazo, o es otra pieza procesal.////No se cargó en la plataforma ekogui la pieza procesal EXCEPCIONES-CONTESTACION AL MANDAMIENTO DE PAGO.// | AJ76: NO PROCEDE ERROR | AK76: EL CARGUE DE LA PIEZA MENCIONADA, NO SE DIO EN VIGENCIA DE LA FIRMA TRUJILLO POLANIA, SIN EMBARGO SE SOLICITA ACCESO AL EXPEDIENTE PARA DAR CORRECCION A LO SOLICITADO. (SE CARGAN TODAS LAS PIEZAS REQUERIDAS) | AN76: MAGDA CUARTAS | AQ76: X | AR76: MAGDA CUARTAS
A77: TRUJILLO POLANIA Y ASOCIADOS | B77: ID_00398144 | C77: 2018_933282 | D77: 1134981 | E77: 11001310501420120057000 | G77: EJECUTIVO LABORAL | H77: 41522767 | I77: NIDIA PEÑA SOLORZA | J77: Colpensiones | K77: BOGOTA | L77: CONTINUA CON LA EJECUCION | M77: 20/03/2018 | N77: SIN FALLO | Z77: SI | AB77: NO | AC77: No se cargó en la plataforma ekogui la pieza procesal MANDAMIENTO DE PAGO. | AD77: NO | AE77: No se cargó en la plataforma ekogui la pieza procesal EXCEPCIONES-CONTESTACION AL MANDAMIENTO DE PAGO. | AH77: ERROR | AI77: ////////////No se cargó en la plataforma ekogui la pieza procesal MANDAMIENTO DE PAGO.//No se cargó en la plataforma ekogui la pieza procesal EXCEPCIONES-CONTESTACION AL MANDAMIENTO DE PAGO.// | AJ77: NO PROCEDE ERROR | AK77: EL CARGUE DE LA PIEZA MENCIONADA, NO SE DIO EN VIGENCIA DE LA FIRMA TRUJILLO POLANIA, SIN EMBARGO SE SOLICITA ACCESO AL EXPEDIENTE PARA DAR CORRECCION A LO SOLICITADO. (SE CARGAN TODAS LAS PIEZAS REQUERIDAS) | AN77: MAGDA CUARTAS | AQ77: X | AR77: MAGDA CUARTAS
A78: TABOR ASESORES LEGALES SAS | B78: ID_007709182 | C78: 2024_18803117 | D78: 2581340 | E78: 11001410501220240034100 | G78: ORDINARIO LABORAL DE UNICA INSTANCIA | H78: 23606567 | I78: MARINA LEON VELA | J78: Colpensiones | K78: BOGOTA | L78: FAVORABLE | M78: 23/01/2025 | N78: DESFAVORABLE | O78: 16/01/2026 | P78: SI | T78: SI | V78: SI | X78: NO | Y78: No se cargó en la plataforma ekogui la pieza procesal SENTENCIA. | AH78: ERROR | AI78: ////////No se cargó en la plataforma ekogui la pieza procesal SENTENCIA.//////// | AJ78: NO PROCEDE ERROR | AK78: LA SENTENCIA SE ENCUENTRA CARGADA DESDE EL 2025/02/14 Y EL ARCHIVO SE DENOMINA " 11001410501220240034100.pdf" | AN78: MAGDA CUARTAS | AQ78: X | AR78: MAGDA CUARTAS
A79: TABOR ASESORES LEGALES SAS | B79: ID_007407996 | C79: 2023_7127694 | D79: 2430249 | E79: 11001310502420220050800 | G79: ORDINARIO LABORAL DE PRIMERA INSTANCIA | H79: 41575163 | I79: CELINA TERESA FORERO ALMANZA | J79: Colpensiones | K79: BOGOTA | L79: DESFAVORABLE | M79: 22/11/2024 | N79: DESFAVORABLE | O79: 31/10/2025 | P79: SI | R79: SI | T79: SI | V79: NO | W79: Se cargó en la plataforma ekogui la pieza procesal DEMANDA-ORDINARIA, pero no corresponde al proceso actual. | X79: SI | AH79: ERROR | AI79: //////Se cargó en la plataforma ekogui la pieza procesal DEMANDA-ORDINARIA, pero no corresponde al proceso actual.////////// | AJ79: NO PROCEDE ERROR | AK79: EL ARCHIVO DE DEMANDA PERTENCE AL PROCESO DE LA DEMANDANTE CELINA TERESA FORERO ALMANZA Y CORRESPONDE A LA CAUSA DESCONOCIMIENTO DE TRASLADO DE REGIMEN. ARCHIVO CARGADO DESDE 2023/05/18 DENOMINADO "CELINA TERESA FORERO ALMANZA-5-20.pdf" | AN79: MAGDA CUARTAS | AQ79: X | AR79: MAGDA CUARTAS
A80: WORLD LEGAL CORPORATION SAS | B80: ID_007676645 | C80: 2024_15081643 | D80: 2562126 | E80: 11001310502020240015800 | G80: ORDINARIO LABORAL DE PRIMERA INSTANCIA | H80: 255665 | I80: ARMANDO SARMIENTO ALFONSO | J80: Colpensiones | K80: BOGOTA | L80: SIN FALLO | N80: SIN FALLO | P80: SI | R80: SI | T80: NO | U80: Se cargó en la plataforma ekogui la pieza procesal CONTESTACION DE LA DEMANDA de forma incompleta. | AH80: ERROR | AI80: ////Se cargó en la plataforma ekogui la pieza procesal CONTESTACION DE LA DEMANDA de forma incompleta.//////////// | AJ80: NO PROCEDE ERROR | AK80: LA CONTESTACION ESTA CARGADA DESDE: 2024/08/12 -CONTESTACION DE LA DEMANDA- 11001310502020240015800.pdf | AN80: MAGDA CUARTAS | AQ80: X | AR80: MAGDA CUARTAS
A81: TABOR ASESORES LEGALES SAS | B81: ID_007284512 | C81: 2022_13601633 | D81: 2349719 | E81: 11001310503820180061900 | G81: EJECUTIVO LABORAL | H81: 41698691 | I81: MARIA OLIVA PABON OVALLE | J81: Colpensiones | K81: BOGOTA | L81: CONTINUA CON LA EJECUCION | M81: 15/07/2025 | N81: SIN FALLO | Z81: SI | AB81: SI | AD81: SI | AF81: NO | AG81: Se cargó en la plataforma ekogui la pieza procesal AUTO QUE ORDENA/NO ORDENA CONTINUAR CON LA EJECUCION, pero es un comodín, pantallazo, o es otra pieza procesal. | AH81: ERROR | AI81: ////////////////Se cargó en la plataforma ekogui la pieza procesal AUTO QUE ORDENA/NO ORDENA CONTINUAR CON LA EJECUCION, pero es un comodín, pantallazo, o es otra pieza procesal. | AJ81: NO PROCEDE ERROR | AK81: LA PIEZA MENCIONADA NO SE ENCUENTRA CARGADA, SOLO HAY 3 ARCHIVOS Y NINGUNO ES EL MENCIONADO COMO ERROR | AN81: MAGDA CUARTAS | AQ81: X | AR81: MAGDA CUARTAS
A82: WORLD LEGAL CORPORATION SAS | B82: ID_00322674 | C82: 2017_3588607 | D82: 1275916 | E82: 11001310500220170002800 | G82: EJECUTIVO LABORAL | H82: 41769587 | I82: ALICIA FANDIÑO DE CHINCHILLA | J82: COLPENSIONES | K82: BOGOTA | L82: CONTINUA CON LA EJECUCION | M82: 23/06/2017 | N82: SIN FALLO | Z82: NO | AA82: Se cargó en la plataforma ekogui la pieza procesal MANDAMIENTO DE PAGO, pero es un comodín, pantallazo, o es otra pieza procesal. | AB82: SI | AD82: NO | AE82: No se cargó en la plataforma ekogui la pieza procesal EXCEPCIONES-CONTESTACION AL MANDAMIENTO DE PAGO. | AF82: SI | AH82: ERROR | AI82: //////////Se cargó en la plataforma ekogui la pieza procesal MANDAMIENTO DE PAGO, pero es un comodín, pantallazo, o es otra pieza procesal.////No se cargó en la plataforma ekogui la pieza procesal EXCEPCIONES-CONTESTACION AL MANDAMIENTO DE PAGO.// | AJ82: NO PROCEDE ERROR | AK82: EL MP SE LIBRO EL 14/02/2017, LAS PIEZAS REQUERIDAS OBEDECEN A LA MISMA VIGENCIA 2017, FECHA PARA LA CUAL LA FIRMA NO EJERCIA DEFENSA PARA LA ENTIDAD, NO OBSTANTE GENERA COMPROMISO PERO NO DESCUENTO DADO A QUE LA OBLIGACION DEL CARGUE ESTABA EN CABEZA DE OTRA FIRMA | AN82: MAGDA CUARTAS | AQ82: X | AR82: MAGDA CUARTAS
A83: TABOR ASESORES LEGALES SAS | B83: ID_008043618 | C83: 2026_3671795 | D83: 2718419 | E83: 11001310501920251016200 | G83: EJECUTIVO LABORAL | H83: 41656821 | I83: MARIA VICTORIA SANZ ALVAREZ | J83: Colpensiones | K83: BOGOTA | L83: SIN FALLO | N83: SIN FALLO | Z83: NO | AA83: Se cargó en la plataforma ekogui la pieza procesal DEMANDA QUE DA ORIGEN AL MANDAMIENTO DE PAGO, pero es un comodín, pantallazo, o es otra pieza procesal. | AB83: SI | AD83: SI | AF83: SI | AH83: ERROR | AI83: //////////Se cargó en la plataforma ekogui la pieza procesal DEMANDA QUE DA ORIGEN AL MANDAMIENTO DE PAGO, pero es un comodín, pantallazo, o es otra pieza procesal.////// | AJ83: NO PROCEDE ERROR | AK83: EN EL ARCHIVO CARGADO Y DENOMINADO "DemandaAnexos PAG 28.pdf" EN LA PAGINA 26 SE ENCUENTRA LA SOLICITUD DE LIBRAR MANDAMIENTO CON FIRMA DEL APODERADO DEL DEMANDANTE | AN83: MAGDA CUARTAS | AQ83: X | AR83: MAGDA CUARTAS
A84: TRUJILLO POLANIA Y ASOCIADOS | B84: ID_00425811 | C84: 2018_4398340 | D84: 1210682 | E84: 11001310500920170050200 | G84: EJECUTIVO LABORAL | H84: 41733564 | I84: JANETH DEL PILAR MARTINEZ DE ROZO | J84: Colpensiones | K84: BOGOTA | L84: CONTINUA CON LA EJECUCION | M84: 21/02/2019 | N84: SIN FALLO | Z84: SI | AB84: SI | AD84: NO | AE84: No se cargó en la plataforma ekogui la pieza procesal EXCEPCIONES-CONTESTACION AL MANDAMIENTO DE PAGO. | AF84: NO | AG84: Se cargó en la plataforma ekogui la pieza procesal AUTO QUE ORDENA/NO ORDENA CONTINUAR CON LA EJECUCION, pero es un comodín, pantallazo, o es otra pieza procesal. | AH84: ERROR | AI84: //////////////No se cargó en la plataforma ekogui la pieza procesal EXCEPCIONES-CONTESTACION AL MANDAMIENTO DE PAGO.//Se cargó en la plataforma ekogui la pieza procesal AUTO QUE ORDENA/NO ORDENA CONTINUAR CON LA EJECUCION, pero es un comodín, pantallazo, o es otra pieza procesal. | AJ84: NO PROCEDE ERROR | AK84: EL CARGUE DE LA PIEZA MENCIONADA, NO SE DIO EN VIGENCIA DE LA FIRMA TRUJILLO POLANIA, SIN EMBARGO SE SOLICITA ACCESO AL EXPEDIENTE PARA DAR CORRECCION A LO SOLICITADO. (SE CARGAN TODAS LAS PIEZAS REQUERIDAS) | AN84: MAGDA CUARTAS | AQ84: X | AR84: MAGDA CUARTAS
A85: TRUJILLO POLANIA Y ASOCIADOS | B85: ID_00428796 | C85: 2018_4734469 | D85: 1217900 | E85: 11001310500820160062900 | G85: EJECUTIVO LABORAL | H85: 24133433 | I85: EUDELIA AURORA OBANDO SIERRA | J85: Colpensiones | K85: BOGOTA | L85: CONTINUA CON LA EJECUCION | M85: 20/02/2024 | N85: SIN FALLO | Z85: NO | AA85: Se cargó en la plataforma ekogui la pieza procesal DEMANDA QUE DA ORIGEN AL MANDAMIENTO DE PAGO, pero es un comodín, pantallazo, o es otra pieza procesal. | AB85: SI | AD85: SI | AF85: SI | AH85: ERROR | AI85: //////////Se cargó en la plataforma ekogui la pieza procesal DEMANDA QUE DA ORIGEN AL MANDAMIENTO DE PAGO, pero es un comodín, pantallazo, o es otra pieza procesal.////// | AJ85: NO PROCEDE ERROR | AK85: EL CARGUE DE LA PIEZA MENCIONADA, NO SE DIO EN VIGENCIA DE LA FIRMA TRUJILLO POLANIA, SIN EMBARGO SE SOLICITA ACCESO AL EXPEDIENTE PARA DAR CORRECCION A LO SOLICITADO. (SE CARGAN TODAS LAS PIEZAS REQUERIDAS) | AN85: MAGDA CUARTAS | AQ85: X | AR85: MAGDA CUARTAS
A86: TRUJILLO POLANIA Y ASOCIADOS | B86: ID_00435764 | C86: 2018_5554701 | D86: 1229141 | E86: 11001310500920180001800 | G86: EJECUTIVO LABORAL | H86: 35485822 | I86: MARIA GRACILIANA SANTOS SALAMANCA | J86: Colpensiones | K86: BOGOTA | L86: CONTINUA CON LA EJECUCION | M86: 11/10/2018 | N86: SIN FALLO | Z86: SI | AB86: SI | AD86: NO | AE86: No se cargó en la plataforma ekogui la pieza procesal EXCEPCIONES-CONTESTACION AL MANDAMIENTO DE PAGO. | AF86: NO | AG86: Se cargó en la plataforma ekogui la pieza procesal AUTO QUE ORDENA/NO ORDENA CONTINUAR CON LA EJECUCION, pero es un comodín, pantallazo, o es otra pieza procesal. | AH86: ERROR | AI86: //////////////No se cargó en la plataforma ekogui la pieza procesal EXCEPCIONES-CONTESTACION AL MANDAMIENTO DE PAGO.//Se cargó en la plataforma ekogui la pieza procesal AUTO QUE ORDENA/NO ORDENA CONTINUAR CON LA EJECUCION, pero es un comodín, pantallazo, o es otra pieza procesal. | AJ86: NO PROCEDE ERROR | AK86: EL CARGUE DE LA PIEZA MENCIONADA, NO SE DIO EN VIGENCIA DE LA FIRMA TRUJILLO POLANIA, SIN EMBARGO SE SOLICITA ACCESO AL EXPEDIENTE PARA DAR CORRECCION A LO SOLICITADO. (SE CARGAN TODAS LAS PIEZAS REQUERIDAS) | AN86: MAGDA CUARTAS | AQ86: X | AR86: MAGDA CUARTAS
A87: TABOR ASESORES LEGALES SAS | B87: ID_007736992 | C87: 2024_22646373 | D87: 2566283 | E87: 11001310501920230005800 | G87: ORDINARIO LABORAL DE PRIMERA INSTANCIA | H87: 25868443 | I87: BENITA ISABEL YANEZ MONTES | J87: Colpensiones | K87: BOGOTA | L87: DESFAVORABLE | M87: 26/05/2025 | N87: DESFAVORABLE | O87: 30/09/2025 | P87: SI | T87: NO | U87: No se cargó en la plataforma ekogui la pieza procesal DEMANDA-ORDINARIA. | V87: SI | X87: SI | AH87: ERROR | AI87: ////No se cargó en la plataforma ekogui la pieza procesal DEMANDA-ORDINARIA.//////////// | AJ87: NO PROCEDE ERROR | AK87: LA DEMANDA SE ENCUENTRA CARGADA DESDE EL 2024/08/09 EL ARCHIVO DENOMINADO " BENITA ISABEL YANEZ MONTES DEMANDA.pdf" | AN87: ZULEIMA PARRA | AQ87: X | AR87: ZULEIMA BARROS
A88: TRUJILLO POLANIA Y ASOCIADOS | B88: ID_00455943 | C88: 2018_8319307 | D88: 1264881 | E88: 11001310501620160042000 | G88: EJECUTIVO LABORAL | H88: 41596453 | I88: NERY DEL CARMEN IPUZ DE REYES | J88: Colpensiones | K88: BOGOTA | L88: CONTINUA CON LA EJECUCION | M88: 28/06/2019 | N88: SIN FALLO | Z88: SI | AB88: NO | AC88: Se cargó en la plataforma ekogui la pieza procesal MANDAMIENTO DE PAGO de forma incompleta. | AH88: ERROR | AI88: ////////////Se cargó en la plataforma ekogui la pieza procesal MANDAMIENTO DE PAGO de forma incompleta.//// | AJ88: NO PROCEDE ERROR | AK88: EL CARGUE DE LA PIEZA MENCIONADA, NO SE DIO EN VIGENCIA DE LA FIRMA TRUJILLO POLANIA, SIN EMBARGO SE SOLICITA ACCESO AL EXPEDIENTE PARA DAR CORRECCION A LO SOLICITADO. (SE CARGAN TODAS LAS PIEZAS REQUERIDAS) | AN88: ZULEIMA PARRA | AQ88: X | AR88: ZULEIMA BARROS
A89: TRUJILLO POLANIA Y ASOCIADOS | B89: ID_00457892 | C89: 2018_8507175 | D89: 1273231 | E89: 11001310500920180003100 | G89: ORDINARIO LABORAL DE PRIMERA INSTANCIA | H89: 21153192 | I89: BLANCA AZUCENA MOLINA PACHON | J89: Colpensiones | K89: BOGOTA | L89: SIN FALLO | N89: SIN FALLO | P89: NO | Q89: Se cargó en la plataforma ekogui la pieza procesal DEMANDA-ORDINARIA, pero es un comodín, pantallazo, o es otra pieza procesal. | T89: NO | U89: No se cargó en la plataforma ekogui la pieza procesal DEMANDA-ORDINARIA. | AH89: ERROR | AI89: Se cargó en la plataforma ekogui la pieza procesal DEMANDA-ORDINARIA, pero es un comodín, pantallazo, o es otra pieza procesal.////No se cargó en la plataforma ekogui la pieza procesal DEMANDA-ORDINARIA.//////////// | AJ89: NO PROCEDE ERROR | AK89: EL CARGUE DE LA PIEZA MENCIONADA, NO SE DIO EN VIGENCIA DE LA FIRMA TRUJILLO POLANIA, SIN EMBARGO SE SOLICITA ACCESO AL EXPEDIENTE PARA DAR CORRECCION A LO SOLICITADO. (SE CARGAN TODAS LAS PIEZAS REQUERIDAS) | AN89: ZULEIMA PARRA | AQ89: X | AR89: ZULEIMA BARROS
A90: TRUJILLO POLANIA Y ASOCIADOS | B90: ID_00475582 | C90: 2018_11581138 | D90: 1310063 | E90: 11001310500920180020600 | G90: ORDINARIO LABORAL DE PRIMERA INSTANCIA | H90: 6864815 | I90: VIRINO MANUEL VELASQUEZ GUERRA | J90: Colpensiones | K90: BOGOTA | L90: DESFAVORABLE | M90: 16/09/2024 | N90: FAVORABLE | O90: 28/02/2025 | P90: SI | T90: NO | U90: No se cargó en la plataforma ekogui la pieza procesal CONTESTACION DE LA DEMANDA. | V90: SI | X90: SI | AH90: ERROR | AI90: ////No se cargó en la plataforma ekogui la pieza procesal CONTESTACION DE LA DEMANDA.//////////// | AJ90: NO PROCEDE ERROR | AK90: EL CARGUE DE LA PIEZA MENCIONADA, NO SE DIO EN VIGENCIA DE LA FIRMA TRUJILLO POLANIA, SIN EMBARGO SE SOLICITA ACCESO AL EXPEDIENTE PARA DAR CORRECCION A LO SOLICITADO. (SE CARGAN TODAS LAS PIEZAS REQUERIDAS) | AN90: ZULEIMA PARRA | AQ90: X | AR90: ZULEIMA BARROS
A91: TRUJILLO POLANIA Y ASOCIADOS | B91: ID_00509244 | C91: 2019_1151300 | D91: 1356863 | E91: 11001310503920160039800 | G91: ORDINARIO LABORAL DE PRIMERA INSTANCIA | H91: 24048537 | I91: ANA JULIETA SILVA TIBADUIZA | J91: Colpensiones | K91: BOGOTA | L91: SIN FALLO | N91: SIN FALLO | P91: SI | T91: NO | U91: No se cargó en la plataforma ekogui la pieza procesal DEMANDA-ORDINARIA. | AH91: ERROR | AI91: ////No se cargó en la plataforma ekogui la pieza procesal DEMANDA-ORDINARIA.//////////// | AJ91: NO PROCEDE ERROR | AK91: EL CARGUE DE LA PIEZA MENCIONADA, NO SE DIO EN VIGENCIA DE LA FIRMA TRUJILLO POLANIA, SIN EMBARGO SE SOLICITA ACCESO AL EXPEDIENTE PARA DAR CORRECCION A LO SOLICITADO. | AN91: ZULEIMA PARRA | AQ91: X | AR91: ZULEIMA BARROS
A92: TRUJILLO POLANIA Y ASOCIADOS | B92: ID_00523590 | C92: 2019_3264088 | D92: 1388884 | E92: 11001310501020180063800 | G92: ORDINARIO LABORAL DE PRIMERA INSTANCIA | H92: 890300279 | I92: BANCO DE OCCIDENTE | J92: COLPENSIONES | K92: BOGOTA | L92: FAVORABLE | M92: 8/02/2024 | N92: SIN FALLO | P92: SI | R92: SI | T92: NO | U92: No se cargó en la plataforma ekogui la pieza procesal CONTESTACION DE LA DEMANDA. | AH92: ERROR | AI92: ////No se cargó en la plataforma ekogui la pieza procesal CONTESTACION DE LA DEMANDA.//////////// | AJ92: NO PROCEDE ERROR | AK92: EL CARGUE DE LA PIEZA MENCIONADA, NO SE DIO EN VIGENCIA DE LA FIRMA TRUJILLO POLANIA, SIN EMBARGO SE SOLICITA ACCESO AL EXPEDIENTE PARA DAR CORRECCION A LO SOLICITADO. (SE CARGAN TODAS LAS PIEZAS REQUERIDAS) | AN92: ZULEIMA PARRA | AQ92: X | AR92: ZULEIMA BARROS
A93: TRUJILLO POLANIA Y ASOCIADOS | B93: ID_00523600 | C93: 2019_3265225 | D93: 1389142 | E93: 11001310501020180066900 | G93: ORDINARIO LABORAL DE PRIMERA INSTANCIA | H93: 35505921 | I93: MARITZA ELIZABETH CEBALLOS SAAVEDRA | J93: COLPENSIONES | K93: BOGOTA | L93: SIN FALLO | N93: SIN FALLO | P93: SI | T93: NO | U93: No se cargó en la plataforma ekogui la pieza procesal CONTESTACION DE LA DEMANDA. | AH93: ERROR | AI93: ////No se cargó en la plataforma ekogui la pieza procesal CONTESTACION DE LA DEMANDA.//////////// | AJ93: NO PROCEDE ERROR | AK93: EL CARGUE DE LA PIEZA MENCIONADA, NO SE DIO EN VIGENCIA DE LA FIRMA TRUJILLO POLANIA, SIN EMBARGO SE SOLICITA ACCESO AL EXPEDIENTE PARA DAR CORRECCION A LO SOLICITADO. (SE CARGAN TODAS LAS PIEZAS REQUERIDAS) | AN93: ZULEIMA PARRA | AQ93: X | AR93: ZULEIMA BARROS
A94: TRUJILLO POLANIA Y ASOCIADOS | B94: ID_00524985 | C94: 2019_3509227 | D94: 1389068 | E94: 11001310501420180069800 | G94: EJECUTIVO LABORAL | H94: 3093397 | I94: JOSE PARMENIO PATIÑO BARRERA | J94: Colpensiones | K94: BOGOTA | L94: CONTINUA CON LA EJECUCION | M94: 15/10/2019 | N94: SIN FALLO | Z94: NO | AA94: Se cargó en la plataforma ekogui la pieza procesal DEMANDA QUE DA ORIGEN AL MANDAMIENTO DE PAGO, pero es un comodín, pantallazo, o es otra pieza procesal. | AB94: NO | AC94: No se cargó en la plataforma ekogui la pieza procesal MANDAMIENTO DE PAGO. | AF94: NO | AG94: No se cargó en la plataforma ekogui la pieza procesal AUTO QUE ORDENA/NO ORDENA CONTINUAR CON LA EJECUCION. | AH94: ERROR | AI94: //////////Se cargó en la plataforma ekogui la pieza procesal DEMANDA QUE DA ORIGEN AL MANDAMIENTO DE PAGO, pero es un comodín, pantallazo, o es otra pieza procesal.//No se cargó en la plataforma ekogui la pieza procesal MANDAMIENTO DE PAGO.////No se cargó en la plataforma ekogui la pieza procesal AUTO QUE ORDENA/NO ORDENA CONTINUAR CON LA EJECUCION. | AJ94: NO PROCEDE ERROR | AK94: EL CARGUE DE LA PIEZA MENCIONADA, NO SE DIO EN VIGENCIA DE LA FIRMA TRUJILLO POLANIA, SIN EMBARGO SE SOLICITA ACCESO AL EXPEDIENTE PARA DAR CORRECCION A LO SOLICITADO. (SE CARGAN TODAS LAS PIEZAS REQUERIDAS) | AN94: ZULEIMA PARRA | AQ94: X | AR94: ZULEIMA BARROS
A95: TRUJILLO POLANIA Y ASOCIADOS | B95: ID_00525554 | C95: 2019_3632283 | D95: 2010051 | E95: 11001310503920180046800 | G95: EJECUTIVO LABORAL | H95: 429914 | I95: GERARDO HERNANDEZ MORENO | J95: Colpensiones | K95: BOGOTA | L95: CONTINUA CON LA EJECUCION | M95: 29/01/2020 | N95: SIN FALLO | Z95: SI | AB95: NO | AC95: No se cargó en la plataforma ekogui la pieza procesal MANDAMIENTO DE PAGO. | AH95: ERROR | AI95: ////////////No se cargó en la plataforma ekogui la pieza procesal MANDAMIENTO DE PAGO.//// | AJ95: NO PROCEDE ERROR | AK95: EL CARGUE DE LA PIEZA MENCIONADA, NO SE DIO EN VIGENCIA DE LA FIRMA TRUJILLO POLANIA, SIN EMBARGO SE SOLICITA ACCESO AL EXPEDIENTE PARA DAR CORRECCION A LO SOLICITADO. (SE CARGAN TODAS LAS PIEZAS REQUERIDAS) | AN95: ZULEIMA PARRA | AQ95: X | AR95: ZULEIMA BARROS
A96: TRUJILLO POLANIA Y ASOCIADOS | B96: ID_00528763 | C96: 2019_4041333 | D96: 1394631 | E96: 11001310500820180049700 | G96: ORDINARIO LABORAL DE PRIMERA INSTANCIA | H96: 19226323 | I96: ALVARO MONZON RODRIGUEZ | J96: Colpensiones | K96: BOGOTA | L96: SIN FALLO | N96: SIN FALLO | P96: SI | T96: NO | U96: Se cargó en la plataforma ekogui la pieza procesal DEMANDA-ORDINARIA, pero no corresponde al proceso actual. | AH96: ERROR | AI96: ////Se cargó en la plataforma ekogui la pieza procesal DEMANDA-ORDINARIA, pero no corresponde al proceso actual.//////////// | AJ96: NO PROCEDE ERROR | AK96: EL CARGUE DE LA PIEZA MENCIONADA, NO SE DIO EN VIGENCIA DE LA FIRMA TRUJILLO POLANIA, SIN EMBARGO SE SOLICITA ACCESO AL EXPEDIENTE PARA DAR CORRECCION A LO SOLICITADO. (SE CARGAN TODAS LAS PIEZAS REQUERIDAS) | AN96: ZULEIMA PARRA | AQ96: X | AR96: ZULEIMA BARROS
A97: TABOR ASESORES LEGALES SAS | B97: ID_007737448 | C97: 2024_22772811 | D97: 2594301 | E97: 11001310503820240020900 | G97: ORDINARIO LABORAL DE PRIMERA INSTANCIA | H97: 79524086 | I97: FLABIO FONSECA VARGAS | J97: Colpensiones | K97: BOGOTA | L97: DESFAVORABLE | M97: 19/08/2025 | N97: SIN FALLO | P97: NO | Q97: Se cargó en la plataforma ekogui la pieza procesal ACTA DE AUDIENCIA, pero no corresponde al proceso actual. | T97: SI | AH97: ERROR | AI97: Se cargó en la plataforma ekogui la pieza procesal ACTA DE AUDIENCIA, pero no corresponde al proceso actual.//////////////// | AJ97: NO PROCEDE ERROR | AK97: EL ACTA DE AUDIENCIA SI CORRESPONDE AL PROCESO POR CUANTO EL DEMANDANTE EN EL ARCHIVO CARGADO ES FLABIO FONSECA VARGAS | AN97: ZULEIMA PARRA | AQ97: X | AR97: ZULEIMA BARROS
A98: TRUJILLO POLANIA Y ASOCIADOS | B98: ID_00550144 | C98: 2019_7684098 | D98: 2033603 | E98: 11001310500920190012500 | G98: ORDINARIO LABORAL DE PRIMERA INSTANCIA | H98: 41439427 | I98: MARIA CONCEPCION BELLO GONZALEZ | J98: Colpensiones | K98: BOGOTA | L98: SIN FALLO | N98: SIN FALLO | P98: SI | T98: NO | U98: No se cargó en la plataforma ekogui la pieza procesal CONTESTACION DE LA DEMANDA. | AH98: ERROR | AI98: ////No se cargó en la plataforma ekogui la pieza procesal CONTESTACION DE LA DEMANDA.//////////// | AJ98: NO PROCEDE ERROR | AK98: EL CARGUE DE LA PIEZA MENCIONADA, NO SE DIO EN VIGENCIA DE LA FIRMA TRUJILLO POLANIA, SIN EMBARGO SE SOLICITA ACCESO AL EXPEDIENTE PARA DAR CORRECCION A LO SOLICITADO. (SE CARGAN TODAS LAS PIEZAS REQUERIDAS) | AN98: ZULEIMA PARRA | AQ98: X | AR98: ZULEIMA BARROS
A99: TRUJILLO POLANIA Y ASOCIADOS | B99: ID_00565004 | C99: 2019_10089371 | D99: 2044864 | E99: 11001310501420170060000 | G99: ORDINARIO LABORAL DE PRIMERA INSTANCIA | H99: 35521972 | I99: CLARA INES ESTRADA GARZON | J99: Colpensiones | K99: BOGOTA | L99: SIN FALLO | N99: SIN FALLO | P99: SI | T99: NO | U99: Se cargó en la plataforma ekogui la pieza procesal CONTESTACION DE LA DEMANDA, pero en formato Word, sin firmas y sello. | AH99: ERROR | AI99: ////Se cargó en la plataforma ekogui la pieza procesal CONTESTACION DE LA DEMANDA, pero en formato Word, sin firmas y sello.//////////// | AJ99: NO PROCEDE ERROR | AK99: EL CARGUE DE LA PIEZA MENCIONADA, NO SE DIO EN VIGENCIA DE LA FIRMA TRUJILLO POLANIA, SIN EMBARGO SE SOLICITA ACCESO AL EXPEDIENTE PARA DAR CORRECCION A LO SOLICITADO. (SE CARGAN TODAS LAS PIEZAS REQUERIDAS) | AN99: ZULEIMA PARRA | AQ99: X | AR99: ZULEIMA BARROS
A100: TRUJILLO POLANIA Y ASOCIADOS | B100: ID_00567576 | C100: 2019_10573020 | D100: 2049221 | E100: 11001310501020190022600 | G100: ORDINARIO LABORAL DE PRIMERA INSTANCIA | H100: 79423162 | I100: MARCO TULIO MARTINEZ SAENZ | J100: Colpensiones | K100: BOGOTA | L100: DESFAVORABLE | M100: 27/08/2024 | N100: SIN FALLO | P100: SI | T100: NO | U100: Se cargó en la plataforma ekogui la pieza procesal CONTESTACION DE LA DEMANDA, pero en formato Word, sin firmas y sello. | AH100: ERROR | AI100: ////Se cargó en la plataforma ekogui la pieza procesal CONTESTACION DE LA DEMANDA, pero en formato Word, sin firmas y sello.//////////// | AJ100: NO PROCEDE ERROR | AK100: EL CARGUE DE LA PIEZA MENCIONADA, NO SE DIO EN VIGENCIA DE LA FIRMA TRUJILLO POLANIA, SIN EMBARGO SE SOLICITA ACCESO AL EXPEDIENTE PARA DAR CORRECCION A LO SOLICITADO. (SE CARGAN TODAS LAS PIEZAS REQUERIDAS) | AN100: ZULEIMA PARRA | AQ100: X | AR100: ZULEIMA BARROS
...

Sheet Hoja2
A1: FIRMA | B1: ID_PROCESOS | C1: NO_BIZAGI | D1: ID_EKOGUI | E1: DIGITOS_23 | F1: 21 DIG | G1: TIPO_PROCESO | H1: IDENTIFICACION_DEMANDANTE | I1: NOMBRE_DEMANDANTE | J1: DEMANDADO | K1: REGIONAL | L1: SENTIDO_FALLO_1INSTANCIA | M1: FECHA_FALLO_1INSTANCIA | N1: SENTIDO_FALLO_2INSTANCIA | O1: FECHA_FALLO_2INSTANCIA | P1: DEMANDA | Q1: OBSERVACIÓN DEMANDA | R1: ACTA_DE_AUDIENCIA | S1: OBSERVACIÓN ACTA_DE_AUDIENCIA | T1: CONTESTACION_DE_DEMANDA | U1: OBSERVACIÓN CONTESTACION_DE_DEMANDA | V1: SENTENCIA_PRIMERA_INSTANCIA | W1: OBSERVACIÓN SENTENCIA_PRIMERA_INSTANCIA | X1: SENTENCIA_SEGUNDA_INSTANCIA | Y1: OBSERVACIÓN SENTENCIA_SEGUNDA_INSTANCIA | Z1: DEMANDA | AA1: OBSERVACIÓN DEMANDA | AB1: MANDAMIENTO_DE_PAGO | AC1: OBSERVACIÓN MANDAMIENTO_DE_PAGO | AD1: EXCEPCIONES_CONTESTACION | AE1: OBSERVACIÓN EXCEPCIONES_CONTESTACION | AF1: AUTO_QUE_ORDENA_CONTINUAR/NO_CONTINUAR_CON _LA_EJECUCION | AG1: OBSERVACIÓN AUTO_QUE_ORDENA_CONTINUAR/NO_CONTINUAR_CON _LA_EJECUCION | AH1: VALIDACIÓN | AI1: OBSERVACIÓN ERROR | AJ1: PROCEDE / NO PROCEDE ERROR | AK1: RAZÓN POR LA CUAL NO PROCEDE | AL1: OBSERVACIÓN REGIONAL | AM1: CONCLUSIÓN | AN1: ENCARGADO | AO1: ACTUALIZACION
A2: UNION TEMPORAL SUPRA LEGAL | B2: ID_007564982 | C2: 2024_2796587 | D2: 2515790 | E2: 05001310501920240001100 | G2: ORDINARIO LABORAL DE PRIMERA INSTANCIA | H2: 3228672 | I2: GUSTAVO ALONSO RESTREPO MOLINA | J2: Colpensiones | K2: ANTIOQUIA | L2: FAVORABLE | M2: 30/07/2024 | N2: FAVORABLE | O2: 22/04/2025 | AP2: DANIELA | AQ2: OK
A3: UNION TEMPORAL VILLEGAS CONSULTORES JURIDICOS | B3: ID_007806569 | C3: 2025_3193558 | D3: 2624776 | E3: 05001410501020240054800 | G3: ORDINARIO LABORAL DE UNICA INSTANCIA | H3: 70085715 | I3: TEOBALDO ENRIQUE CABRERA LUNA | J3: Colpensiones | K3: ANTIOQUIA | L3: SIN FALLO | N3: SIN FALLO | AP3: DANIELA | AQ3: OK
A4: UNION TEMPORAL SUPRA LEGAL | B4: ID_00329325 | C4: 2017_5172484 | D4: 1165730 | E4: 05001310500420160026700 | G4: EJECUTIVO LABORAL | H4: 3515767 | I4: FRANCISCO HERNANDO LOPEZ RAMIREZ | J4: COLPENSIONES | K4: ANTIOQUIA | L4: SIN FALLO | N4: SIN FALLO | AP4: DANIELA | AQ4: OK
A5: UNION TEMPORAL SUPRA LEGAL | B5: ID_00561372 | C5: 2019_9469591 | D5: 2037429 | E5: 05001310500420190024100 | G5: ORDINARIO LABORAL DE PRIMERA INSTANCIA | H5: 21437751 | I5: MIRYAM DEL SOCORRO MEDINA HENAO | J5: Colpensiones | K5: ANTIOQUIA | L5: DESFAVORABLE | M5: 18/09/2024 | N5: SIN FALLO | AP5: DANIELA | AQ5: OK
A6: SOLUCIONES JURIDICAS Y EMPRESARIAL SJC SAS | B6: ID_00566946 | C6: 2019_10464478 | D6: 2046297 | E6: 05001310501620190038800 | G6: ORDINARIO LABORAL DE PRIMERA INSTANCIA | H6: 43060557 | I6: BLANCA HELY RAMIREZ CORRALES | J6: Colpensiones | K6: ANTIOQUIA | L6: FAVORABLE | M6: 25/03/2021 | N6: FAVORABLE | O6: 17/02/2022 | AP6: DANIELA | AQ6: OK
A7: SOLUCIONES JURIDICAS Y EMPRESARIAL SJC SAS | B7: ID_007424507 | C7: 2023_9051099 | D7: 2439196 | E7: 05001310501120230003400 | G7: ORDINARIO LABORAL DE PRIMERA INSTANCIA | H7: 70553127 | I7: CESAR AUGUSTO ACOSTA TORRES | J7: Colpensiones | K7: ANTIOQUIA | L7: DESFAVORABLE | M7: 10/04/2024 | N7: DESFAVORABLE | O7: 26/07/2024 | AP7: DANIELA | AQ7: OK
A8: UNION TEMPORAL VILLEGAS CONSULTORES JURIDICOS | B8: ID_007378058 | C8: 2023_4113846 | D8: 2409982 | E8: 05001310502220220017000 | G8: ORDINARIO LABORAL DE PRIMERA INSTANCIA | H8: 70061924 | I8: NORMAN RAMIRO CANO MAYA | J8: Colpensiones | K8: ANTIOQUIA | L8: DESFAVORABLE | M8: 2/04/2025 | N8: SIN FALLO | AP8: DANIELA | AQ8: OK
A9: UNION TEMPORAL VILLEGAS CONSULTORES JURIDICOS | B9: ID_007756436 | C9: 2024_24824951 | D9: 2602917 | E9: 05360310500120240032600 | G9: EJECUTIVO LABORAL | H9: 70120321 | I9: FRANCISCO FOCION MONSALVE SANCHEZ | J9: Colpensiones | K9: ANTIOQUIA | L9: CONTINUA CON LA EJECUCION | M9: 6/03/2025 | N9: SIN FALLO | AP9: DANIELA | AQ9: OK
A10: WISS CONSULTORIA JURIDICA SAS | B10: ID_007822180 | C10: 2025_5661285 | D10: 2632000 | E10: 05001410501220240028100 | G10: ORDINARIO LABORAL DE UNICA INSTANCIA | H10: 14248525 | I10: JAIME DANILO VALENCIA CARDONA | J10: Colpensiones | K10: ANTIOQUIA | L10: SIN FALLO | N10: SIN FALLO | AP10: DANIELA | AQ10: OK
A11: UNION TEMPORAL SUPRA LEGAL | B11: ID_00306769 | C11: 2017_1149307 | D11: 981238 | E11: 05001310500420150040100 | G11: EJECUTIVO LABORAL | H11: 32429719 | I11: ANGELA ALICIA ROJAS ROJAS | J11: COLPENSIONES | K11: ANTIOQUIA | L11: CONTINUA CON LA EJECUCION | M11: 21/03/2017 | N11: SIN FALLO | AP11: DANIELA | AQ11: OK
A12: UNION TEMPORAL SUPRA LEGAL | B12: ID_007064460 | C12: 2021_9815582 | D12: 2230207 | E12: 05001310502420210020300 | G12: ORDINARIO LABORAL DE PRIMERA INSTANCIA | H12: 32345404 | I12: LUZ AZUCENA MUNERA SANTA | J12: Colpensiones | K12: ANTIOQUIA | L12: SIN FALLO | N12: SIN FALLO | AP12: DANIELA | AQ12: OK
A13: SOLUCIONES JURIDICAS Y EMPRESARIAL SJC SAS | B13: ID_007738587 | C13: 2024_22895026 | D13: 2593362 | E13: 05001310502220240011400 | G13: ORDINARIO LABORAL DE PRIMERA INSTANCIA | H13: 70054604 | I13: OMAR DE JESUS VANEGAS RIOS | J13: Colpensiones | K13: ANTIOQUIA | L13: SIN FALLO | N13: SIN FALLO | AP13: DANIELA | AQ13: OK
A14: SOLUCIONES JURIDICAS Y EMPRESARIAL SJC SAS | B14: ID_007759012 | C14: 2024_25096128 | D14: 2604700 | E14: 05001310500320240004500 | G14: ORDINARIO LABORAL DE PRIMERA INSTANCIA | H14: 70564222 | I14: JUAN GUILLERMO BUSTAMANTE CARDONA | J14: Colpensiones | K14: ANTIOQUIA | L14: SIN FALLO | N14: SIN FALLO | AP14: DANIELA | AQ14: OK
A15: UNION TEMPORAL SUPRA LEGAL | B15: ID_00282963 | C15: 2016_12441396 | D15: 1189749 | E15: 05001310500420160041200 | G15: EJECUTIVO LABORAL | H15: 8354806 | I15: CARLOS IGNACIO HENAO MEJIA | J15: COLPENSIONES | K15: ANTIOQUIA | L15: CONTINUA CON LA EJECUCION | M15: 24/05/2018 | N15: SIN FALLO | AP15: DANIELA | AQ15: OK
A16: WISS CONSULTORIA JURIDICA SAS | B16: ID_00576126 | C16: 2019_11845871 | D16: 2069339 | E16: 05001410500420190009700 | G16: EJECUTIVO LABORAL | H16: 70113412 | I16: CARLOS ALBERTO MOLINA SEGURA | J16: Colpensiones | K16: ANTIOQUIA | L16: CONTINUA CON LA EJECUCION | M16: 6/12/2019 | N16: SIN FALLO | AP16: DANIELA | AQ16: OK
A17: SOLUCIONES JURIDICAS Y EMPRESARIAL SJC SAS | B17: ID_007338795 | C17: 2022_18722231 | D17: 2385745 | E17: 05615310500120220042600 | G17: ORDINARIO LABORAL DE UNICA INSTANCIA | H17: 21873357 | I17: MARIA OMAIRA GOMEZ ARCILA | J17: Colpensiones | K17: ANTIOQUIA | L17: SIN FALLO | N17: SIN FALLO | AP17: DANIELA | AQ17: OK
A18: SOLUCIONES JURIDICAS Y EMPRESARIAL SJC SAS | B18: ID_007583300 | C18: 2024_4670125 | D18: 2523818 | E18: 05001310502020240003300 | G18: ORDINARIO LABORAL DE PRIMERA INSTANCIA | H18: 8226272 | I18: JESUS ANGEL CORRALES COSSIO | J18: Colpensiones | K18: ANTIOQUIA | L18: SIN FALLO | N18: SIN FALLO | AP18: DANIELA | AQ18: OK
A19: UNION TEMPORAL SUPRA LEGAL | B19: ID_007053564 | C19: 2021_9068082 | D19: 2225276 | E19: 05001310502420210015300 | G19: ORDINARIO LABORAL DE PRIMERA INSTANCIA | H19: 15350140 | I19: JOSE HUBERTO TORO MORALES | J19: Colpensiones | K19: ANTIOQUIA | L19: SIN FALLO | N19: SIN FALLO | AP19: DANIELA | AQ19: OK
A20: SOLUCIONES JURIDICAS Y EMPRESARIAL SJC SAS | B20: ID_007625594 | C20: 2024_9676910 | D20: 2540915 | E20: 05001310501620230028600 | G20: ORDINARIO LABORAL DE PRIMERA INSTANCIA | H20: 39747890 | I20: NIDIA RAMIREZ CASTRO | J20: Colpensiones | K20: ANTIOQUIA | L20: SIN FALLO | N20: SIN FALLO | AP20: DANIELA | AQ20: OK
A21: UNION TEMPORAL VILLEGAS CONSULTORES JURIDICOS | B21: ID_00275728 | C21: 2016_10698747 | D21: 1036249 | E21: 05045310500120160127300 | G21: ORDINARIO LABORAL DE PRIMERA INSTANCIA | H21: 39317991 | I21: MARIA EUGENIA FAJARDO GOMEZ | J21: COLPENSIONES | K21: ANTIOQUIA | L21: SIN FALLO | N21: SIN FALLO | AP21: DANIELA | AQ21: OK
A22: UNION TEMPORAL SUPRA LEGAL | B22: ID_00394325 | C22: 2018_524561 | D22: 1138266 | E22: 05001310500420170079500 | G22: EJECUTIVO LABORAL | H22: 3336421 | I22: JAIME JARAMILLO PANESO | J22: Colpensiones | K22: ANTIOQUIA | L22: CONTINUA CON LA EJECUCION | M22: 7/05/2019 | N22: SIN FALLO | AP22: DANIELA | AQ22: OK
A23: WISS CONSULTORIA JURIDICA SAS | B23: ID_00296660 | C23: 2013_4657830 | D23: 536851 | E23: 05001410500520130029800 | G23: EJECUTIVO LABORAL | H23: 32077697 | I23: MARIA UBALDINA BEDOYA ALVAREZ | J23: COLPENSIONES | K23: ANTIOQUIA | L23: CONTINUA CON LA EJECUCION | M23: 6/09/2013 | N23: SIN FALLO | AP23: DANIELA | AQ23: OK
A24: UNION TEMPORAL VILLEGAS CONSULTORES JURIDICOS | B24: ID_007216490 | C24: 2022_7086031 | D24: 2304431 | E24: 05001310501320220015400 | G24: ORDINARIO LABORAL DE PRIMERA INSTANCIA | H24: 21851570 | I24: LUZ MARINA GAVIRIA ACOSTA | J24: Colpensiones | K24: ANTIOQUIA | L24: DESFAVORABLE | M24: 28/02/2023 | N24: SIN FALLO | AP24: DANIELA | AQ24: OK
A25: UNION TEMPORAL VILLEGAS CONSULTORES JURIDICOS | B25: ID_007626617 | C25: 2024_9783363 | D25: 2540198 | E25: 05001310501820240006500 | G25: ORDINARIO LABORAL DE PRIMERA INSTANCIA | H25: 42892748 | I25: CLAUDIA CECILIA ARANGO SALAZAR | J25: Colpensiones | K25: ANTIOQUIA | L25: DESFAVORABLE | M25: 6/12/2024 | N25: SIN FALLO | AP25: DANIELA | AQ25: OK
A26: SOLUCIONES JURIDICAS Y EMPRESARIAL SJC SAS | B26: ID_007530947 | C26: 2023_19468439 | D26: 2500673 | E26: 05001310502720230033000 | G26: ORDINARIO LABORAL DE PRIMERA INSTANCIA | H26: 18005117 | I26: ANDRES EMILIO ARCHBOLD BRYAN | J26: Colpensiones | K26: ANTIOQUIA | L26: DESFAVORABLE | M26: 19/02/2024 | N26: SIN FALLO | AP26: DANIELA | AQ26: OK
A27: SOLUCIONES JURIDICAS Y EMPRESARIAL SJC SAS | B27: ID_007210966 | C27: 2022_6657368 | D27: 2300768 | E27: 05001310500620220003200 | G27: ORDINARIO LABORAL DE PRIMERA INSTANCIA | H27: 51852650 | I27: SILIA JAQUELINE CAICEDO | J27: Colpensiones | K27: ANTIOQUIA | L27: SIN FALLO | N27: SIN FALLO | P27: SI | T27: SI | V27: NO APLICA | X27: NO APLICA | AP27: MANUEL | AQ27: OK
A28: SOLUCIONES JURIDICAS Y EMPRESARIAL SJC SAS | B28: ID_007411772 | C28: 2023_7511587 | D28: 2431300 | E28: 05088310500220220008800 | G28: ORDINARIO LABORAL DE PRIMERA INSTANCIA | H28: 79590025 | I28: LUIS FERNANDO CELY ROMERO | J28: Colpensiones | K28: ANTIOQUIA | L28: FAVORABLE | M28: 30/01/2024 | N28: SIN FALLO | P28: SI | T28: SI | V28: SI | X28: NO APLICA | AP28: MANUEL | AQ28: OK
A29: UNION TEMPORAL VILLEGAS CONSULTORES JURIDICOS | B29: ID_007750470 | C29: 2024_24144753 | D29: 2600578 | E29: 05001310500820240016800 | G29: ORDINARIO LABORAL DE PRIMERA INSTANCIA | H29: 32443110 | I29: MARIA DORA OROZCO CORTES | J29: Colpensiones | K29: ANTIOQUIA | L29: SIN FALLO | N29: SIN FALLO | P29: SI | T29: SI | V29: NO APLICA | X29: NO APLICA | AP29: MANUEL | AQ29: OK
A30: SOLUCIONES JURIDICAS Y EMPRESARIAL SJC SAS | B30: ID_007228829 | C30: 2022_8404763 | D30: 2313417 | E30: 05001310501120220006500 | G30: ORDINARIO LABORAL DE PRIMERA INSTANCIA | H30: 73112048 | I30: RUBEN NICOLAS POLO ARRAZOLA | J30: Colpensiones | K30: ANTIOQUIA | L30: DESFAVORABLE | M30: 5/12/2023 | N30: DESFAVORABLE | O30: 30/08/2024 | P30: SI | T30: SI | V30: SI | X30: SI | AP30: MANUEL | AQ30: OK
A31: UNION TEMPORAL VILLEGAS CONSULTORES JURIDICOS | B31: ID_007223060 | C31: 2022_7788903 | D31: 2311352 | E31: 05001310501020210039400 | G31: EJECUTIVO LABORAL | H31: 98714518 | I31: TERESA DE JESUS USUGA USUGA | J31: Colpensiones | K31: ANTIOQUIA | L31: CONTINUA CON LA EJECUCION | M31: 11/04/2023 | N31: SIN FALLO | Z31: SI | AB31: SI | AD31: SI | AF31: SI | AP31: MANUEL | AQ31: OK
A32: SOLUCIONES JURIDICAS Y EMPRESARIAL SJC SAS | B32: ID_00557279 | C32: 2019_8843132 | D32: 2030574 | E32: 05001310501120180029100 | G32: ORDINARIO LABORAL DE PRIMERA INSTANCIA | H32: 618834 | I32: LUIS IVAN ALVAREZ MESA | J32: Colpensiones | K32: ANTIOQUIA | L32: DESFAVORABLE | M32: 21/08/2024 | N32: SIN FALLO | P32: SI | T32: SI | V32: SI | X32: NO APLICA | AP32: MANUEL | AQ32: OK
A33: UNION TEMPORAL VILLEGAS CONSULTORES JURIDICOS | B33: ID_007365159 | C33: 2023_2967149 | D33: 2401828 | E33: 05001310502120230004200 | G33: ORDINARIO LABORAL DE PRIMERA INSTANCIA | H33: 16703374 | I33: RICARDO ANDRES PARDO DIAZ | J33: Colpensiones | K33: ANTIOQUIA | L33: DESFAVORABLE | M33: 25/07/2024 | N33: DESFAVORABLE | O33: 6/12/2024 | P33: SI | T33: SI | V33: SI | X33: SI | AP33: MANUEL | AQ33: OK
A34: SOLUCIONES JURIDICAS Y EMPRESARIAL SJC SAS | B34: ID_00390590 | C34: 2017_13152049 | D34: 1117349 | E34: 05001310502220170073300 | G34: ORDINARIO LABORAL DE PRIMERA INSTANCIA | H34: 22023192 | I34: LEONILDA DE JESUS CARDONA MENDOZA | J34: Colpensiones | K34: ANTIOQUIA | L34: FAVORABLE | M34: 18/10/2019 | N34: SIN FALLO | P34: SI | T34: SI | V34: SI | X34: NO APLICA | AP34: MANUEL | AQ34: OK
A35: UNION TEMPORAL SUPRA LEGAL | B35: ID_00450973 | C35: 2018_7542012 | D35: 1260234 | E35: 05001310500420140123300 | G35: EJECUTIVO LABORAL | H35: 21290134 | I35: ANA GUDIELA ALZATE GOMEZ | J35: Colpensiones | K35: ANTIOQUIA | L35: SIN FALLO | N35: SIN FALLO | Z35: SI | AB35: SI | AD35: SI | AF35: NO | AH35: ERROR | AP35: MANUEL | AQ35: OK
A36: UNION TEMPORAL SUPRA LEGAL | B36: ID_007470309 | C36: 2023_14267145 | D36: 2466722 | E36: 05001310500120230000100 | G36: ORDINARIO LABORAL DE PRIMERA INSTANCIA | H36: 70063494 | I36: FERNANDO DE JESUS RAVE RODAS | J36: Colpensiones | K36: ANTIOQUIA | L36: FAVORABLE | M36: 21/03/2025 | N36: SIN FALLO | P36: SI | T36: SI | V36: SI | X36: NO APLICA | AP36: MANUEL | AQ36: OK
A37: SOLUCIONES JURIDICAS Y EMPRESARIAL SJC SAS | B37: ID_007593070 | C37: 2024_5728767 | D37: 2528146 | E37: 05001310501520240000500 | G37: ORDINARIO LABORAL DE PRIMERA INSTANCIA | H37: 70552842 | I37: CARLOS ENRIQUE OROZCO ALVAREZ | J37: Colpensiones | K37: ANTIOQUIA | L37: FAVORABLE | M37: 23/01/2025 | N37: SIN FALLO | P37: SI | T37: SI | V37: SI | X37: NO APLICA | AP37: MANUEL | AQ37: OK
A38: WISS CONSULTORIA JURIDICA SAS | B38: ID_00456363 | C38: 2018_8387485 | D38: 1268180 | E38: 05001410500120170109400 | G38: ORDINARIO LABORAL DE UNICA INSTANCIA | H38: 70075902 | I38: HUMBERTO DE JESUS PASOS RESTREPO | J38: Colpensiones | K38: ANTIOQUIA | L38: FAVORABLE | M38: 15/03/2021 | N38: SIN FALLO | P38: SI | R38: SI | AP38: MANUEL | AQ38: OK
A39: UNION TEMPORAL SUPRA LEGAL | B39: ID_007747422 | C39: 2024_23927427 | D39: 2601282 | E39: 05001410500720241041400 | G39: EJECUTIVO LABORAL | H39: 43093205 | I39: MARIA DEL CARMEN OCHOA DUARTE | J39: Colpensiones | K39: ANTIOQUIA | L39: SIN FALLO | N39: SIN FALLO | Z39: SI | AB39: SI | AD39: SI | AF39: SI | AP39: MANUEL | AQ39: OK
A40: UNION TEMPORAL SUPRA LEGAL | B40: ID_007605080 | C40: 2024_7189386 | D40: 2532094 | E40: 05001310502420230037400 | G40: ORDINARIO LABORAL DE PRIMERA INSTANCIA | H40: 43528147 | I40: MADELEN MARIN FERNANDEZ | J40: Colpensiones | K40: ANTIOQUIA | L40: SIN FALLO | N40: SIN FALLO | P40: SI | T40: SI | V40: NO APLICA | X40: NO APLICA | AP40: MANUEL | AQ40: OK
A41: UNION TEMPORAL VILLEGAS CONSULTORES JURIDICOS | B41: ID_007639607 | C41: 2024_10956184 | D41: 2545799 | E41: 05045310500120240019300 | G41: ORDINARIO LABORAL DE PRIMERA INSTANCIA | H41: 15350450 | I41: EFRAIN RIOS ARIAS | J41: Colpensiones | K41: ANTIOQUIA | L41: SIN FALLO | N41: SIN FALLO | P41: SI | T41: SI | V41: NO APLICA | X41: NO APLICA | AP41: MANUEL | AQ41: OK
A42: WISS CONSULTORIA JURIDICA SAS | B42: ID_007830069 | C42: 2025_7107836 | D42: 2635239 | E42: 05001410500120240051300 | G42: ORDINARIO LABORAL DE UNICA INSTANCIA | H42: 42004942 | I42: INES HERCILIA CORRALES LEIVA | J42: Colpensiones | K42: ANTIOQUIA | L42: SIN FALLO | N42: SIN FALLO | P42: SI | R42: NO APLICA | AP42: MANUEL | AQ42: OK
A43: SOLUCIONES JURIDICAS Y EMPRESARIAL SJC SAS | B43: ID_007431703 | C43: 2023_9917932 | D43: 2442934 | E43: 05001310500420230015400 | G43: ORDINARIO LABORAL DE PRIMERA INSTANCIA | H43: 3229707 | I43: EDGAR FERNANDO BARREIRO LOPEZ | J43: Colpensiones | K43: ANTIOQUIA | L43: SIN FALLO | N43: SIN FALLO | P43: SI | T43: SI | V43: NO APLICA | X43: NO APLICA | AP43: MANUEL | AQ43: OK
A44: UNION TEMPORAL VILLEGAS CONSULTORES JURIDICOS | B44: ID_00324352 | C44: 2017_4082168 | D44: 1138431 | E44: 05001310501220160024400 | G44: ORDINARIO LABORAL DE PRIMERA INSTANCIA | H44: 43036698 | I44: LYDA DE JESUS ZAPATA ZAPATA | J44: COLPENSIONES | K44: ANTIOQUIA | L44: FAVORABLE | M44: 19/09/2022 | N44: FAVORABLE | O44: 21/03/2025 | P44: SI | T44: SI | V44: SI | X44: SI | AP44: MANUEL | AQ44: OK
A45: UNION TEMPORAL VILLEGAS CONSULTORES JURIDICOS | B45: ID_007795508 | C45: 2025_1955857 | D45: 2619897 | E45: 05001310500820240017700 | G45: ORDINARIO LABORAL DE PRIMERA INSTANCIA | H45: 32483987 | I45: YOLANDA DE JESUS USUGA DAVID | J45: Colpensiones | K45: ANTIOQUIA | L45: SIN FALLO | N45: SIN FALLO | P45: SI | T45: SI | V45: NO APLICA | X45: NO APLICA | AP45: MANUEL | AQ45: OK
A46: SOLUCIONES JURIDICAS Y EMPRESARIAL SJC SAS | B46: ID_007491123 | C46: 2023_16293865 | D46: 2447959 | E46: 05001310502020220043700 | G46: ORDINARIO LABORAL DE PRIMERA INSTANCIA | H46: 63394533 | I46: YAMILE RINCON CASTELLANOS | J46: Colpensiones | K46: ANTIOQUIA | L46: SIN FALLO | N46: SIN FALLO | P46: SI | T46: SI | V46: NO APLICA | X46: NO APLICA | AP46: MANUEL | AQ46: OK
A47: SOLUCIONES JURIDICAS Y EMPRESARIAL SJC SAS | B47: ID_00596265 | C47: 2019_15421369 | D47: 2098167 | E47: 05001310500620190053300 | G47: ORDINARIO LABORAL DE PRIMERA INSTANCIA | H47: 30274761 | I47: LUZ ZORAIDA ALBARRACIN GUZMAN | J47: Colpensiones | K47: ANTIOQUIA | L47: FAVORABLE | M47: 9/05/2024 | N47: DESFAVORABLE | O47: 19/07/2024 | P47: SI | T47: SI | V47: NO | X47: NO | AH47: ERROR | AP47: MANUEL | AQ47: OK
A48: SOLUCIONES JURIDICAS Y EMPRESARIAL SJC SAS | B48: ID_007849448 | C48: 2025_9410420 | E48: 05088310500220250016000 | G48: ORDINARIO LABORAL DE UNICA INSTANCIA | H48: 71585010 | I48: LUIS FERNANDO VELASQUEZ MORALES | J48: Colpensiones | K48: ANTIOQUIA | P48: SI | R48: NO APLICA | AP48: MANUEL | AQ48: OK
A49: UNION TEMPORAL VILLEGAS CONSULTORES JURIDICOS | B49: ID_00366795 | C49: 2017_10472976 | D49: 1191146 | E49: 05001310500220170028300 | G49: ORDINARIO LABORAL DE PRIMERA INSTANCIA | H49: 21334585 | I49: MARIA JUDIT SALDARRIAGA DE RIVERA | J49: Colpensiones | K49: ANTIOQUIA | L49: FAVORABLE | M49: 13/03/2019 | N49: SIN FALLO | P49: SI | T49: SI | V49: SI | X49: NO APLICA | AP49: MANUEL | AQ49: OK
A50: UNION TEMPORAL VILLEGAS CONSULTORES JURIDICOS | B50: ID_007615877 | C50: 2024_8431061 | D50: 2537276 | E50: 05001310502520240002800 | G50: ORDINARIO LABORAL DE PRIMERA INSTANCIA | H50: 42866853 | I50: PATRICIA SUESCUM MONTOYA | J50: Colpensiones | K50: ANTIOQUIA | L50: SIN FALLO | N50: SIN FALLO | P50: SI | T50: SI | V50: NO APLICA | X50: NO APLICA | AP50: MANUEL | AQ50: OK
A51: SOLUCIONES JURIDICAS Y EMPRESARIAL SJC SAS | B51: ID_00688655 | C51: 2020_11181548 | D51: 2158782 | E51: 05001310502220200013200 | G51: ORDINARIO LABORAL DE PRIMERA INSTANCIA | H51: 15503357 | I51: GUILLERMO LEON AMAYA RESTREPO | J51: Colpensiones | K51: ANTIOQUIA | L51: SIN FALLO | N51: SIN FALLO | P51: SI | T51: SI | V51: NO APLICA | X51: NO APLICA | AP51: MANUEL | AQ51: OK
A52: WISS CONSULTORIA JURIDICA SAS | B52: ID_007848749 | C52: 2025_9318936 | E52: 05001410501220250000800 | G52: ORDINARIO LABORAL DE UNICA INSTANCIA | H52: 39405768 | I52: MARTHA CECILIA HARNISH MARIN | J52: Colpensiones | K52: ANTIOQUIA | P52: SI | R52: NO APLICA | AP52: MANUEL | AQ52: OK
A53: WISS CONSULTORIA JURIDICA SAS | B53: ID_007814008 | C53: 2025_4273499 | D53: 2628111 | E53: 05001410500120250001500 | G53: ORDINARIO LABORAL DE UNICA INSTANCIA | H53: 3625807 | I53: JOSE MIGUEL CANO RESTREPO | J53: Colpensiones | K53: ANTIOQUIA | L53: SIN FALLO | N53: SIN FALLO | P53: SI | R53: SI | AP53: MANUEL | AQ53: OK
A54: UNION TEMPORAL SUPRA LEGAL | B54: ID_00044079 | C54: ISS_INAC_005116 | D54: 48775 | E54: 05001310500420100092300 | G54: EJECUTIVO LABORAL | H54: 3591787 | I54: JUAN DE DIOS GOMEZ GARCIA | J54: ISS | K54: ANTIOQUIA | L54: CONTINUA CON LA EJECUCION | M54: 28/03/2011 | N54: SIN FALLO | AP54: ADDY | AQ54: OK
A55: UNION TEMPORAL SUPRA LEGAL | B55: ID_00049614 | C55: ISS_INAC_010651 | D55: 47758 | E55: 05001310500420080092700 | G55: EJECUTIVO LABORAL | H55: 43426460 | I55: GLORIA ESTELA QUIROZ MADRIGAL | J55: ISS | K55: ANTIOQUIA | L55: CONTINUA CON LA EJECUCION | M55: 14/04/2011 | N55: SIN FALLO | AP55: ADDY | AQ55: OK
A56: UNION TEMPORAL SUPRA LEGAL | B56: ID_00050724 | C56: ISS_INAC_011761 | D56: 47370 | E56: 05001310500420070071900 | G56: EJECUTIVO LABORAL | H56: 607976 | I56: ROBERTO RUA COLORADO | J56: ISS | K56: ANTIOQUIA | L56: CONTINUA CON LA EJECUCION | M56: 6/05/2009 | N56: SIN FALLO | AP56: ADDY | AQ56: OK
A57: SOLUCIONES JURIDICAS Y EMPRESARIAL SJC SAS | B57: ID_00277561 | C57: 2016_11152150 | D57: 891928 | E57: 05001310501120150002700 | G57: EJECUTIVO LABORAL | H57: 20034829 | I57: MARIA CELINA MESA DE VELASQUEZ | J57: COLPENSIONES | K57: ANTIOQUIA | L57: CONTINUA CON LA EJECUCION | M57: 30/08/2024 | N57: SIN FALLO | AP57: ADDY | AQ57: OK
A58: SOLUCIONES JURIDICAS Y EMPRESARIAL SJC SAS | B58: ID_00285543 | C58: 2016_12856272 | D58: 934392 | E58: 05001310501520160019300 | G58: EJECUTIVO LABORAL | H58: 731838 | I58: GABRIEL DE JESUS ORTIZ | J58: COLPENSIONES | K58: ANTIOQUIA | L58: CONTINUA CON LA EJECUCION | M58: 2/05/2018 | N58: SIN FALLO | AP58: ADDY | AQ58: OK
A59: SOLUCIONES JURIDICAS Y EMPRESARIAL SJC SAS | B59: ID_00337947 | C59: 2017_7094522 | D59: 1144813 | E59: 05001310500320160122100 | G59: EJECUTIVO LABORAL | H59: 32538985 | I59: MARINA DEL SOCORRO MESA SANTAMARIA | J59: Colpensiones | K59: ANTIOQUIA | L59: CONTINUA CON LA EJECUCION | M59: 29/11/2018 | N59: SIN FALLO | AP59: ADDY | AQ59: OK
A60: SOLUCIONES JURIDICAS Y EMPRESARIAL SJC SAS | B60: ID_00340715 | C60: 2017_7387023 | D60: 1164462 | E60: 05001310501520170022800 | G60: EJECUTIVO LABORAL | H60: 43025301 | I60: MARLENY DEL SOCORRO HENAO GARCIA | J60: Colpensiones | K60: ANTIOQUIA | L60: CONTINUA CON LA EJECUCION | M60: 9/05/2018 | N60: SIN FALLO | AP60: ADDY | AQ60: OK
A61: UNION TEMPORAL SUPRA LEGAL | B61: ID_00341171 | C61: 2017_7450009 | D61: 1179784 | E61: 05001310500420150087100 | G61: EJECUTIVO LABORAL | H61: 8289843 | I61: JORGE EDUARDO CARMONA LONGAS | J61: Colpensiones | K61: ANTIOQUIA | L61: CONTINUA CON LA EJECUCION | M61: 14/09/2022 | N61: SIN FALLO | AP61: ADDY | AQ61: OK
A62: UNION TEMPORAL VILLEGAS CONSULTORES JURIDICOS | B62: ID_00384529 | C62: 2017_12441813 | D62: 1165818 | E62: 05001310501220170084200 | G62: EJECUTIVO LABORAL | H62: 21779832 | I62: MARIA DEL CARMEN JIMENEZ GARCIA | J62: Colpensiones | K62: ANTIOQUIA | L62: CONTINUA CON LA EJECUCION | M62: 3/05/2019 | N62: SIN FALLO | AP62: ADDY | AQ62: OK
A63: UNION TEMPORAL VILLEGAS CONSULTORES JURIDICOS | B63: ID_00432738 | C63: 2018_5232743 | D63: 1222352 | E63: 05001310501220170012100 | G63: EJECUTIVO LABORAL | H63: 15455055 | I63: LUIS GONZALO SALDARRIAGA MEJIA | J63: Colpensiones | K63: ANTIOQUIA | L63: CONTINUA CON LA EJECUCION | M63: 26/10/2018 | N63: SIN FALLO | AP63: ADDY | AQ63: OK
A64: UNION TEMPORAL SUPRA LEGAL | B64: ID_00496222 | C64: 2018_14885945 | D64: 1346229 | E64: 05001310500720180070000 | G64: EJECUTIVO LABORAL | H64: 21459169 | I64: MARGARITA AGUDELO AGUDELO | J64: Colpensiones | K64: ANTIOQUIA | L64: CONTINUA CON LA EJECUCION | M64: 15/02/2019 | N64: SIN FALLO | AP64: ADDY | AQ64: OK
A65: WISS CONSULTORIA JURIDICA SAS | B65: ID_00510429 | C65: 2019_1325869 | D65: 1375744 | E65: 05001410500420180042700 | G65: EJECUTIVO LABORAL | H65: 8420366 | I65: HUMBERTO PALACIO CAICEDO | J65: Colpensiones | K65: ANTIOQUIA | L65: CONTINUA CON LA EJECUCION | M65: 10/05/2019 | N65: SIN FALLO | AP65: ADDY | AQ65: OK
... A69: UNION TEMPORAL SUPRA LEGAL | B69: ID_00590089 | C69: 2019_14310875 | D69: 2087538 | E69: 05001410500520160097600 | G69: EJECUTIVO LABORAL | H69: 654163 | I69: JESUS EMILIO MONSALVE ISAZA | J69: Colpensiones | K69: ANTIOQUIA | L69: CONTINUA CON LA EJECUCION | M69: 17/02/2020 | N69: SIN FALLO | AP69: ADDY | AQ69: OK
A70: SOLUCIONES JURIDICAS Y EMPRESARIAL SJC SAS | B70: ID_007022490 | C70: 2021_6924225 | D70: 2209214 | E70: 05001410500620200045000 | G70: ORDINARIO LABORAL DE UNICA INSTANCIA | H70: 22210268 | I70: GILMA ROSA CASTAÑO PATIÑO | J70: Colpensiones | K70: ANTIOQUIA | L70: FAVORABLE | M70: 11/08/2021 | N70: FAVORABLE | O70: 31/01/2023 | AP70: ADDY | AQ70: OK
A71: SOLUCIONES JURIDICAS Y EMPRESARIAL SJC SAS | B71: ID_00290467 | C71: 2016_13950667 | D71: 1145322 | E71: 05001310500320150121100 | G71: EJECUTIVO LABORAL | H71: 8292785 | I71: ANIBAL DE JESUS RIOS LOPEZ | J71: COLPENSIONES | K71: ANTIOQUIA | L71: CONTINUA CON LA EJECUCION | M71: 16/06/2017 | N71: SIN FALLO | AP71: MARY | AQ71: OK
A72: UNION TEMPORAL VILLEGAS CONSULTORES JURIDICOS | B72: ID_007298815 | C72: 2022_14976650 | D72: 2360292 | E72: 05001310502520220029100 | G72: ORDINARIO LABORAL DE PRIMERA INSTANCIA | H72: 2774356 | I72: JESUS SALVADOR PIEDRAHITA GRISALES | J72: Colpensiones | K72: ANTIOQUIA | L72: DESFAVORABLE | M72: 29/11/2024 | N72: SIN FALLO | AP72: MARY | AQ72: OK
A73: UNION TEMPORAL SUPRA LEGAL | B73: ID_00423061 | C73: 2018_4098278 | D73: 1214221 | E73: 05001310500420180023700 | G73: ORDINARIO LABORAL DE PRIMERA INSTANCIA | H73: 43474885 | I73: YOLANDA FORERO OSORIO | J73: Colpensiones | K73: ANTIOQUIA | L73: SIN FALLO | N73: SIN FALLO | AP73: MARY | AQ73: OK
A74: UNION TEMPORAL SUPRA LEGAL | B74: ID_00355744 | C74: 2017_9230528 | D74: 1177757 | E74: 05001310500420170064400 | G74: EJECUTIVO LABORAL | H74: 8275138 | I74: CASTOR MARIA SANCHEZ SIERRA | J74: Colpensiones | K74: ANTIOQUIA | L74: CONTINUA CON LA EJECUCION | M74: 12/10/2022 | N74: SIN FALLO | AP74: MARY | AQ74: OK
A75: SOLUCIONES JURIDICAS Y EMPRESARIAL SJC SAS | B75: ID_00459144 | C75: 2018_8672972 | D75: 1275016 | E75: 05001310502020180033900 | G75: ORDINARIO LABORAL DE PRIMERA INSTANCIA | H75: 29088321 | I75: MARIELA DUQUE DE GIRALDO | J75: Colpensiones | K75: ANTIOQUIA | L75: FAVORABLE | M75: 21/11/2022 | N75: FAVORABLE | O75: 28/02/2023 | AP75: MARY | AQ75: OK
A76: SOLUCIONES JURIDICAS Y EMPRESARIAL SJC SAS | B76: ID_007567800 | C76: 2024_3163918 | D76: 2516913 | E76: 05001310502020231001700 | G76: EJECUTIVO LABORAL | H76: 21374842 | I76: MARIA GLORIA MADRID PASOS | J76: Colpensiones | K76: ANTIOQUIA | L76: CONTINUA CON LA EJECUCION | M76: 2/04/2024 | N76: SIN FALLO | AP76: MARY | AQ76: OK
A77: UNION TEMPORAL SUPRA LEGAL | B77: ID_007661716 | C77: 2024_13473288 | D77: 2555995 | E77: 05001310500420240000300 | G77: ORDINARIO LABORAL DE PRIMERA INSTANCIA | H77: 1128053962 | I77: DIANA PATRICIA GALVIS GARCIA | J77: Colpensiones | K77: ANTIOQUIA | L77: SIN FALLO | N77: SIN FALLO | AP77: MARY | AQ77: OK
A78: UNION TEMPORAL VILLEGAS CONSULTORES JURIDICOS | B78: ID_007151298 | C78: 2022_1753976 | D78: 2265728 | E78: 05001310501220210053400 | G78: ORDINARIO LABORAL DE PRIMERA INSTANCIA | H78: 43436727 | I78: BLANCA GUDIELA JARAMILLO TAMAYO | J78: Colpensiones | K78: ANTIOQUIA | L78: SIN FALLO | N78: SIN FALLO | AP78: MARY | AQ78: OK
A79: SOLUCIONES JURIDICAS Y EMPRESARIAL SJC SAS | B79: ID_007829737 | C79: 2025_7095375 | D79: 2638309 | E79: 05001410500220250009900 | G79: ORDINARIO LABORAL DE UNICA INSTANCIA | H79: 43088333 | I79: BEATRIZ ELENA DURANGO URIBE | J79: Colpensiones | K79: ANTIOQUIA | L79: SIN FALLO | N79: SIN FALLO | AP79: MARY | AQ79: OK
A80: SOLUCIONES JURIDICAS Y EMPRESARIAL SJC SAS | B80: ID_007406326 | C80: 2023_6913733 | D80: 2428946 | E80: 05001310502320230000100 | G80: ORDINARIO LABORAL DE PRIMERA INSTANCIA | H80: 42756825 | I80: MARGARITA MARIA SALDARRIAGA VILLADA | J80: Colpensiones | K80: ANTIOQUIA | L80: DESFAVORABLE | M80: 8/07/2024 | N80: DESFAVORABLE | O80: 6/03/2025 | AP80: MARY | AQ80: OK
A81: SOLUCIONES JURIDICAS Y EMPRESARIAL SJC SAS | B81: ID_007113512 | C81: 2021_13728153 | D81: 2248292 | E81: 05615310500120210034000 | G81: ORDINARIO LABORAL DE PRIMERA INSTANCIA | H81: 15445815 | I81: MILTON YAIR VILLADA ARIAS | J81: Colpensiones | K81: ANTIOQUIA | L81: SIN FALLO | N81: SIN FALLO | AP81: MARY | AQ81: OK
A82: SOLUCIONES JURIDICAS Y EMPRESARIAL SJC SAS | B82: ID_007637443 | C82: 2024_10768268 | D82: 2545991 | E82: 05001310500320240008300 | G82: ORDINARIO LABORAL DE PRIMERA INSTANCIA | H82: 17323920 | I82: HENRY FERNANDO LUNA MONROY | J82: Colpensiones | K82: ANTIOQUIA | L82: SIN FALLO | N82: SIN FALLO | AP82: MARY | AQ82: OK
A83: UNION TEMPORAL VILLEGAS CONSULTORES JURIDICOS | B83: ID_007483419 | C83: 2023_15331449 | D83: 2472435 | E83: 05001310502120230029400 | G83: ORDINARIO LABORAL DE PRIMERA INSTANCIA | H83: 6788335 | I83: HERIBERTO DE JESUS CASTAÑO BURITICA | J83: Colpensiones | K83: ANTIOQUIA | L83: DESFAVORABLE | M83: 18/07/2024 | N83: DESFAVORABLE | O83: 7/04/2025 | AP83: MARY | AQ83: OK
A84: UNION TEMPORAL SUPRA LEGAL | B84: ID_007525103 | C84: 2023_19074610 | D84: 2497173 | E84: 05001310500420170036600 | G84: EJECUTIVO LABORAL | H84: 10061045 | I84: LUIS EDUARDO BARRERO | J84: Colpensiones | K84: ANTIOQUIA | L84: SIN FALLO | N84: SIN FALLO | AP84: MARY | AQ84: OK
A85: UNION TEMPORAL SUPRA LEGAL | B85: ID_00433062 | C85: 2018_5310438 | D85: 1231480 | E85: 05001310500420170013000 | G85: EJECUTIVO LABORAL | H85: 3559469 | I85: JOSE FERNANDO SANCHEZ LEMA | J85: Colpensiones | K85: ANTIOQUIA | L85: CONTINUA CON LA EJECUCION | M85: 3/09/2021 | N85: SIN FALLO | AP85: MARY | AQ85: OK
A86: SOLUCIONES JURIDICAS Y EMPRESARIAL SJC SAS | B86: ID_00613596 | C86: 2020_1875233 | D86: 2117536 | E86: 05001310502220190064900 | G86: ORDINARIO LABORAL DE PRIMERA INSTANCIA | H86: 71602077 | I86: JORGE DE LA EUCARISTIA ZULUAGA RUIZ | J86: Colpensiones | K86: ANTIOQUIA | L86: FAVORABLE | M86: 3/04/2024 | N86: DESFAVORABLE | O86: 30/08/2024 | AP86: MARY | AQ86: OK
A87: UNION TEMPORAL VILLEGAS CONSULTORES JURIDICOS | B87: ID_007416873 | C87: 2023_8029909 | D87: 2431896 | E87: 05579310500120220032700 | G87: ORDINARIO LABORAL DE PRIMERA INSTANCIA | H87: 1039698674 | I87: ELISABETH ZAPATA SANCHEZ | J87: Colpensiones | K87: ANTIOQUIA | L87: SIN FALLO | N87: SIN FALLO | AP87: MARY | AQ87: OK
A88: UNION TEMPORAL VILLEGAS CONSULTORES JURIDICOS | B88: ID_007710233 | C88: 2024_18856812 | D88: 2578214 | E88: 05209318900120240002800 | G88: ORDINARIO LABORAL DE PRIMERA INSTANCIA | H88: 3538164 | I88: REINALDO ANTONIO GIRALDO HERNANDEZ | J88: Colpensiones | K88: ANTIOQUIA | L88: SIN FALLO | N88: SIN FALLO | AP88: MARY | AQ88: OK
A89: UNION TEMPORAL VILLEGAS CONSULTORES JURIDICOS | B89: ID_007112703 | C89: 2021_13651314 | D89: 2248754 | E89: 05001310501420210042200 | G89: ORDINARIO LABORAL DE PRIMERA INSTANCIA | H89: 8286127 | I89: JESUS MARIA PEREZ TORRES | J89: Colpensiones | K89: ANTIOQUIA | L89: FAVORABLE | M89: 27/02/2024 | N89: FAVORABLE | O89: 7/05/2024 | AP89: MARY | AQ89: OK
A90: UNION TEMPORAL VILLEGAS CONSULTORES JURIDICOS | B90: ID_006937729 | C90: 2021_632193 | D90: 2173133 | E90: 05001310501420200034300 | G90: ORDINARIO LABORAL DE PRIMERA INSTANCIA | H90: 70116674 | I90: VICTOR DE JESUS OSPINA CARO | J90: Colpensiones | K90: ANTIOQUIA | L90: SIN FALLO | N90: SIN FALLO | AP90: MARY | AQ90: OK
A91: UNION TEMPORAL VILLEGAS CONSULTORES JURIDICOS | B91: ID_007650167 | C91: 2024_12113404 | D91: 2549583 | E91: 05001310502520240003600 | G91: ORDINARIO LABORAL DE PRIMERA INSTANCIA | H91: 42938606 | I91: SIRLEY DEL SOCORRO OCHOA QUINTANA | J91: Colpensiones | K91: ANTIOQUIA | L91: SIN FALLO | N91: SIN FALLO | AP91: MARY | AQ91: OK
A92: UNION TEMPORAL SUPRA LEGAL | B92: ID_00256805 | C92: 2016_5046876 | D92: 915712 | E92: 05001310500420150151800 | G92: ORDINARIO LABORAL DE PRIMERA INSTANCIA | H92: 32308705 | I92: NORA DEL SOCORRO PEREZ DE CARMONA | J92: COLPENSIONES | K92: ANTIOQUIA | L92: DESFAVORABLE | M92: 23/01/2019 | N92: SIN FALLO | AP92: MARY | AQ92: OK
A93: UNION TEMPORAL SUPRA LEGAL | B93: ID_007817877 | C93: 2025_4986182 | D93: 2629963 | E93: 05001410500720250005300 | G93: ORDINARIO LABORAL DE UNICA INSTANCIA | H93: 32555224 | I93: LILIANA MARIA JARAMILLO MUÑOZ | J93: Colpensiones | K93: ANTIOQUIA | L93: SIN FALLO | N93: SIN FALLO | AP93: MARY | AQ93: OK
A94: UNION TEMPORAL SUPRA LEGAL | B94: ID_007631911 | C94: 2024_10208564 | D94: 2543771 | E94: 05001310500720240007200 | G94: ORDINARIO LABORAL DE PRIMERA INSTANCIA | H94: 98489255 | I94: OSCAR DARIO SOSSA BETANCUR | J94: Colpensiones | K94: ANTIOQUIA | L94: DESFAVORABLE | M94: 6/12/2024 | N94: SIN FALLO | AP94: MARY | AQ94: OK
A95: UNION TEMPORAL VILLEGAS CONSULTORES JURIDICOS | B95: ID_00548651 | C95: 2019_7356522 | D95: 2018014 | E95: 05001310501220180018300 | G95: EJECUTIVO LABORAL | H95: 3399136 | I95: LUIS FERNANDO BELTRAN LEON | J95: Colpensiones | K95: ANTIOQUIA | L95: CONTINUA CON LA EJECUCION | M95: 16/08/2019 | N95: SIN FALLO | AP95: MARY | AQ95: OK
A96: UNION TEMPORAL VILLEGAS CONSULTORES JURIDICOS | B96: ID_007330912 | C96: 2022_18061150 | D96: 2380042 | E96: 05001310501420220045200 | G96: ORDINARIO LABORAL DE PRIMERA INSTANCIA | H96: 71591495 | I96: JORGE ALBERTO CAMPILLO VELEZ | J96: Colpensiones | K96: ANTIOQUIA | L96: DESFAVORABLE | M96: 4/02/2025 | N96: DESFAVORABLE | O96: 7/03/2025 | AP96: MARY | AQ96: OK
A97: UNION TEMPORAL SUPRA LEGAL | B97: ID_007421293 | C97: 2023_8612451 | D97: 2437608 | E97: 05001310502420230011700 | G97: ORDINARIO LABORAL DE PRIMERA INSTANCIA | H97: 10246937 | I97: ALVARO LOPEZ ARANGO | J97: Colpensiones | K97: ANTIOQUIA | L97: SIN FALLO | N97: SIN FALLO | AP97: MARY | AQ97: OK
A98: UNION TEMPORAL SUPRA LEGAL | B98: ID_007572655 | C98: 2024_3637650 | D98: 2521719 | E98: 05001310502420240001600 | G98: ORDINARIO LABORAL DE PRIMERA INSTANCIA | H98: 8308251 | I98: GUSTAVO ADOLFO RENDON CORREA | J98: Colpensiones | K98: ANTIOQUIA | L98: SIN FALLO | N98: SIN FALLO | AP98: MARY | AQ98: OK
A99: SOLUCIONES JURIDICAS Y EMPRESARIAL SJC SAS | B99: ID_00052733 | C99: ISS_INAC_013770 | D99: 241892 | E99: 05001310500320100118300 | G99: EJECUTIVO LABORAL | H99: 22036368 | I99: PASTORA VELEZ DE CAÑAVERAL | J99: ISS | K99: ANTIOQUIA | L99: CONTINUA CON LA EJECUCION | M99: 26/09/2012 | N99: SIN FALLO | AP99: MARY | AQ99: OK
A100: UNION TEMPORAL VILLEGAS CONSULTORES JURIDICOS | B100: ID_007451576 | C100: 2023_12321717 | D100: 2454809 | E100: 05001310501820230029500 | G100: ORDINARIO LABORAL DE PRIMERA INSTANCIA | H100: 70516233 | I100: LUIS ANGEL GALEANO RESTREPO | J100: Colpensiones | K100: ANTIOQUIA | L100: DESFAVORABLE | M100: 30/09/2024 | N100: SIN FALLO | AP100: MARY | AQ100: OK
A101: SOLUCIONES JURIDICAS Y EMPRESARIAL SJC SAS | B101: ID_00469605 | C101: 2018_10484735 | D101: 1294721 | E101: 05001310500320160102700 | G101: EJECUTIVO LABORAL | H101: 42767379 | I101: MIBIA HERRERA GARCIA | J101: Colpensiones | K101: ANTIOQUIA | L101: CONTINUA CON LA EJECUCION | M101: 4/09/2019 | N101: SIN FALLO | AP101: MARY | AQ101: OK
A102: UNION TEMPORAL SUPRA LEGAL | B102: ID_007412364 | C102: 2023_7565090 | D102: 2435048 | E102: 05001310500420210046600 | G102: ORDINARIO LABORAL DE PRIMERA INSTANCIA | H102: 20939721 | I102: LUZ MARINA GOMEZ VASQUEZ | J102: Colpensiones | K102: ANTIOQUIA | L102: SIN FALLO | N102: SIN FALLO | AP102: MARY | AQ102: OK
A103: UNION TEMPORAL VILLEGAS CONSULTORES JURIDICOS | B103: ID_007430708 | C103: 2023_9731198 | D103: 2444534 | E103: 05001310501820230010800 | G103: ORDINARIO LABORAL DE PRIMERA INSTANCIA | H103: 70557242 | I103: GUILLERMO LEON COLORADO FLOREZ | J103: Colpensiones | K103: ANTIOQUIA | L103: DESFAVORABLE | M103: 17/02/2025 | N103: SIN FALLO | AP103: MARY | AQ103: OK
...

Sheet Hoja1
A1: FIRMA | B1: ID_PROCESOS | C1: NO_BIZAGI | D1: ID_EKOGUI | E1: DIGITOS_23 | F1: 21 DIG | G1: TIPO_PROCESO | H1: IDENTIFICACION_DEMANDANTE | I1: NOMBRE_DEMANDANTE | J1: DEMANDADO | K1: REGIONAL | L1: SENTIDO_FALLO_1INSTANCIA | M1: FECHA_FALLO_1INSTANCIA | N1: SENTIDO_FALLO_2INSTANCIA | O1: FECHA_FALLO_2INSTANCIA | P1: DEMANDA | Q1: OBSERVACIÓN DEMANDA | R1: ACTA_DE_AUDIENCIA | S1: OBSERVACIÓN ACTA_DE_AUDIENCIA | T1: CONTESTACION_DE_DEMANDA | U1: OBSERVACIÓN CONTESTACION_DE_DEMANDA | V1: SENTENCIA_PRIMERA_INSTANCIA | W1: OBSERVACIÓN SENTENCIA_PRIMERA_INSTANCIA | X1: SENTENCIA_SEGUNDA_INSTANCIA | Y1: OBSERVACIÓN SENTENCIA_SEGUNDA_INSTANCIA | Z1: DEMANDA | AA1: OBSERVACIÓN DEMANDA | AB1: MANDAMIENTO_DE_PAGO | AC1: OBSERVACIÓN MANDAMIENTO_DE_PAGO | AD1: EXCEPCIONES_CONTESTACION | AE1: OBSERVACIÓN EXCEPCIONES_CONTESTACION | AF1: AUTO_QUE_ORDENA_CONTINUAR/NO_CONTINUAR_CON _LA_EJECUCION | AG1: OBSERVACIÓN AUTO_QUE_ORDENA_CONTINUAR/NO_CONTINUAR_CON _LA_EJECUCION | AH1: VALIDACIÓN | AI1: OBSERVACIÓN ERROR | AJ1: PROCEDE / NO PROCEDE ERROR | AK1: RAZÓN POR LA CUAL NO PROCEDE | AL1: OBSERVACIÓN REGIONAL | AM1: CONCLUSIÓN | AN1: ENCARGADO | AO1: ACTUALIZACION
A2: WISS CONSULTORIA JURIDICA SAS | B2: ID_00013353 | C2: 2013_2029083 | D2: 543906 | E2: 05001310500920130011400 | F2: 050013105009201300114 | G2: EJECUTIVO LABORAL | H2: 3390088 | I2: GABRIEL ENRIQUE HERNANDEZ LOPEZ | J2: COLPENSIONES | K2: ANTIOQUIA | L2: CONTINUA CON LA EJECUCION | M2: 21/10/2014 | N2: SIN FALLO | Z2: SI | AB2: SI | AD2: SI | AF2: SI | AN2: Leonardo | AO2: ID_00013353
A3: UNION TEMPORAL VILLEGAS CONSULTORES JURIDICOS | B3: ID_00017562 | C3: 2013_2880644 | D3: 1165031 | E3: 05001310502120120127300 | F3: 050013105021201201273 | G3: EJECUTIVO LABORAL | H3: 43062151 | I3: LUZ MARLENY TAMAYO | J3: COLPENSIONES | K3: ANTIOQUIA | L3: CONTINUA CON LA EJECUCION | M3: 1/08/2013 | N3: SIN FALLO | Z3: SI | AB3: SI | AD3: NO | AE3: No se cargó en la plataforma ekogui la pieza procesal MANDAMIENTO DE PAGO. | AF3: SI | AH3: ERROR | AN3: Leonardo | AO3: ID_00017562
A4: UNION TEMPORAL VILLEGAS CONSULTORES JURIDICOS | B4: ID_00024544 | C4: ISS_08456 | D4: 53654 | E4: 05001310500820090049900 | F4: 050013105008200900499 | G4: EJECUTIVO LABORAL | H4: 573575 | I4: CARLOS ENRIQUE GUTIERREZ QUINTERO | J4: ISS | K4: ANTIOQUIA | L4: CONTINUA CON LA EJECUCION | M4: 27/09/2010 | N4: SIN FALLO | Z4: SI | AB4: SI | AD4: SI | AF4: SI | AN4: Mary | AO4: ID_00024544
A5: UNION TEMPORAL VILLEGAS CONSULTORES JURIDICOS | B5: ID_00024560 | C5: ISS_04280 | D5: 53808 | E5: 05001310500820090087700 | F5: 050013105008200900877 | G5: EJECUTIVO LABORAL | H5: 590850 | I5: LUIS HORACIO CASTRO ALZATE | J5: ISS | K5: ANTIOQUIA | L5: CONTINUA CON LA EJECUCION | M5: 22/03/2011 | N5: CONTINUA CON LA EJECUCION | O5: 28/09/2012 | Z5: NO | AA5: No se cargó en la plataforma ekogui la pieza procesal DEMANDA QUE DA ORIGEN AL MANDAMIENTO DE PAGO. | AB5: SI | AD5: SI | AF5: SI | AH5: ERROR | AN5: Manuel | AO5: ID_00024560
A6: UNION TEMPORAL VILLEGAS CONSULTORES JURIDICOS | B6: ID_00024704 | C6: ISS_14399 | D6: 242307 | E6: 05001310500820100064500 | F6: 050013105008201000645 | G6: EJECUTIVO LABORAL | H6: 763300 | I6: PABLO EMILIO PANIAGUA GUTIERREZ | J6: ISS | K6: ANTIOQUIA | L6: CONTINUA CON LA EJECUCION | M6: 16/11/2011 | N6: SIN FALLO | Z6: SI | AB6: SI | AD6: SI | AF6: SI | AN6: Addy | AO6: ID_00024704
A7: UNION TEMPORAL VILLEGAS CONSULTORES JURIDICOS | B7: ID_00025089 | C7: ISS_11384 | D7: 1191645 | E7: 05001310500820110042900 | F7: 050013105008201100429 | G7: EJECUTIVO LABORAL | H7: 2463077 | I7: BERNARDO MEDINA MORALES | J7: ISS | K7: ANTIOQUIA | L7: CONTINUA CON LA EJECUCION | M7: 5/11/2014 | N7: SIN FALLO | Z7: NO | AA7: No se cargó en la plataforma ekogui la pieza procesal DEMANDA QUE DA ORIGEN AL MANDAMIENTO DE PAGO. | AB7: SI | AD7: SI | AF7: SI | AH7: ERROR | AN7: Leonardo | AO7: ID_00025089
A8: UNION TEMPORAL VILLEGAS CONSULTORES JURIDICOS | B8: ID_00025230 | C8: ISS_15003 | D8: 1178818 | E8: 05001310500520120020300 | F8: 050013105005201200203 | G8: ORDINARIO LABORAL DE PRIMERA INSTANCIA | H8: 2706192 | I8: MANUEL SALVADOR PIEDRAHITA | J8: ISS | K8: ANTIOQUIA | L8: FAVORABLE | M8: 25/05/2012 | N8: FAVORABLE | O8: 13/07/2012 | P8: SI | T8: NO | U8: No se cargó en la plataforma ekogui la pieza procesal CONTESTACION DE LA DEMANDA. | V8: SI | X8: SI | AH8: ERROR | AN8: Mary | AO8: ID_00025230
A9: UNION TEMPORAL VILLEGAS CONSULTORES JURIDICOS | B9: ID_00025353 | C9: ISS_19859 | D9: 242332 | E9: 05001310500820100081300 | F9: 050013105008201000813 | G9: EJECUTIVO LABORAL | H9: 3304942 | I9: IVAN DE JESUS VASQUEZ LARA | J9: ISS | K9: ANTIOQUIA | L9: CONTINUA CON LA EJECUCION | M9: 28/11/2011 | N9: SIN FALLO | Z9: NO | AA9: No se cargó en la plataforma ekogui la pieza procesal DEMANDA QUE DA ORIGEN AL MANDAMIENTO DE PAGO. | AB9: NO | AC9: No se cargó en la plataforma ekogui la pieza procesal MANDAMIENTO DE PAGO. | AD9: SI | AF9: SI | AH9: ERROR | AN9: Manuel | AO9: ID_00025353
A10: UNION TEMPORAL VILLEGAS CONSULTORES JURIDICOS | B10: ID_00025396 | C10: ISS_01925 | D10: 1378748 | E10: 05001310500820080060700 | F10: 050013105008200800607 | G10: EJECUTIVO LABORAL | H10: 3320375 | I10: RAMIRO DE JESUS AVENDAÑO ZAPATA | J10: ISS | K10: ANTIOQUIA | L10: CONTINUA CON LA EJECUCION | M10: 31/07/2012 | N10: SIN FALLO | Z10: SI | AB10: SI | AD10: SI | AF10: NO APLICA | AN10: Addy | AO10: ID_00025396
A11: UNION TEMPORAL VILLEGAS CONSULTORES JURIDICOS | B11: ID_00025402 | C11: ISS_14657 | D11: 162893 | E11: 05001310500820100098200 | F11: 050013105008201000982 | G11: EJECUTIVO LABORAL | H11: 3322265 | I11: JORGE PELAEZ VARGAS | J11: ISS | K11: ANTIOQUIA | L11: CONTINUA CON LA EJECUCION | M11: 13/09/2011 | N11: SIN FALLO | Z11: NO | AA11: No se cargó en la plataforma ekogui la pieza procesal DEMANDA QUE DA ORIGEN AL MANDAMIENTO DE PAGO. | AB11: SI | AD11: NO | AE11: No se cargó en la plataforma ekogui la pieza procesal MANDAMIENTO DE PAGO. | AF11: SI | AH11: ERROR | AN11: Leonardo | AO11: ID_00025402
A12: UNION TEMPORAL VILLEGAS CONSULTORES JURIDICOS | B12: ID_00025554 | C12: ISS_18692 | D12: 53771 | E12: 05001310500820090080700 | F12: 050013105008200900807 | G12: EJECUTIVO LABORAL | H12: 3364996 | I12: GUILLERMO TIRADO | J12: ISS | K12: ANTIOQUIA | L12: CONTINUA CON LA EJECUCION | M12: 16/03/2011 | N12: SIN FALLO | Z12: NO | AA12: No se cargó en la plataforma ekogui la pieza procesal DEMANDA QUE DA ORIGEN AL MANDAMIENTO DE PAGO. | AB12: SI | AD12: SI | AF12: SI | AH12: ERROR | AN12: Mary | AO12: ID_00025554
A13: UNION TEMPORAL VILLEGAS CONSULTORES JURIDICOS | B13: ID_00025674 | C13: ISS_20040 | D13: 242335 | E13: 05001310500820100099300 | F13: 050013105008201000993 | G13: EJECUTIVO LABORAL | H13: 3407472 | I13: HERNANDO VELASQUEZ MONTOYA | J13: ISS | K13: ANTIOQUIA | L13: CONTINUA CON LA EJECUCION | M13: 28/11/2011 | N13: SIN FALLO | Z13: SI | AB13: NO | AC13: No se cargó en la plataforma ekogui la pieza procesal MANDAMIENTO DE PAGO. | AD13: SI | AF13: SI | AH13: ERROR | AN13: Manuel | AO13: ID_00025674
A14: UNION TEMPORAL VILLEGAS CONSULTORES JURIDICOS | B14: ID_00025696 | C14: ISS_05423 | D14: 1190769 | E14: 05001310500820110097100 | F14: 050013105008201100971 | G14: EJECUTIVO LABORAL | H14: 3416522 | I14: OCTAVIO DE JESUS DURANGO ACEVEDO | J14: ISS | K14: ANTIOQUIA | L14: CONTINUA CON LA EJECUCION | M14: 8/05/2012 | N14: SIN FALLO | Z14: SI | AB14: SI | AD14: SI | AF14: SI | AN14: Addy | AO14: ID_00025696
A15: UNION TEMPORAL VILLEGAS CONSULTORES JURIDICOS | B15: ID_00025901 | C15: ISS_08923 | D15: 1174831 | E15: 05001310500820110103800 | F15: 050013105008201101038 | G15: EJECUTIVO LABORAL | H15: 3487719 | I15: CARLOS ARTURO HERNANDEZ VELASQUEZ | J15: ISS | K15: ANTIOQUIA | L15: CONTINUA CON LA EJECUCION | M15: 20/04/2012 | N15: SIN FALLO | Z15: NO | AA15: No se cargó en la plataforma ekogui la pieza procesal DEMANDA QUE DA ORIGEN AL MANDAMIENTO DE PAGO. | AB15: SI | AD15: NO | AE15: No se cargó en la plataforma ekogui la pieza procesal MANDAMIENTO DE PAGO. | AF15: SI | AH15: ERROR | AN15: Leonardo | AO15: ID_00025901
A16: UNION TEMPORAL VILLEGAS CONSULTORES JURIDICOS | B16: ID_00026004 | C16: ISS_19377 | D16: 53446 | E16: 05001310500820090001900 | F16: 050013105008200900019 | G16: EJECUTIVO LABORAL | H16: 3515576 | I16: GUILLERMO ANTONIO VALENCIA GARCIA | J16: ISS | K16: ANTIOQUIA | L16: CONTINUA CON LA EJECUCION | M16: 2/06/2011 | N16: SIN FALLO | Z16: SI | AB16: SI | AD16: SI | AF16: SI | AN16: Mary | AO16: ID_00026004
A17: UNION TEMPORAL VILLEGAS CONSULTORES JURIDICOS | B17: ID_00026010 | C17: ISS_10301 | D17: 61520 | E17: 05001310501320100044700 | F17: 050013105013201000447 | G17: EJECUTIVO LABORAL | H17: 3515803 | I17: JOSE GUILLERMO LOPEZ ALZATE | J17: ISS | K17: ANTIOQUIA | L17: CONTINUA CON LA EJECUCION | M17: 17/05/2011 | N17: SIN FALLO | Z17: SI | AB17: NO | AC17: No se cargó en la plataforma ekogui la pieza procesal MANDAMIENTO DE PAGO. | AD17: SI | AF17: SI | AH17: ERROR | AN17: Manuel | AO17: ID_00026010
A18: WISS CONSULTORIA JURIDICA SAS | B18: ID_00026121 | C18: ISS_06217 | D18: 199463 | E18: 05001310500920100077300 | F18: 050013105009201000773 | G18: EJECUTIVO LABORAL | H18: 3562353 | I18: AMADOR DE JESUS FRANCO HENAO | J18: ISS | K18: ANTIOQUIA | L18: CONTINUA CON LA EJECUCION | M18: 16/09/2011 | N18: CONTINUA CON LA EJECUCION | O18: 12/04/2013 | Z18: SI | AB18: NO | AC18: No se cargó en la plataforma ekogui la pieza procesal MANDAMIENTO DE PAGO. | AD18: SI | AF18: SI | AH18: ERROR | AN18: Mary | AO18: ID_00026121
A19: WISS CONSULTORIA JURIDICA SAS | B19: ID_00026177 | C19: ISS_16097 | D19: 55011 | E19: 05001310500920090031200 | F19: 050013105009200900312 | G19: EJECUTIVO LABORAL | H19: 3596956 | I19: CARLOS ENRIQUE RESTREPO BALBIN | J19: ISS | K19: ANTIOQUIA | L19: CONTINUA CON LA EJECUCION | M19: 24/02/2011 | N19: SIN FALLO | Z19: NO | AA19: No se cargó en la plataforma ekogui la pieza procesal DEMANDA QUE DA ORIGEN AL MANDAMIENTO DE PAGO. | AB19: NO | AC19: No se cargó en la plataforma ekogui la pieza procesal MANDAMIENTO DE PAGO. | AD19: NO | AE19: No se cargó en la plataforma Ekogui la pieza procesal de contestación de demanda | AF19: SI | AH19: ERROR | AN19: Manuel | AO19: ID_00026177
A20: UNION TEMPORAL VILLEGAS CONSULTORES JURIDICOS | B20: ID_00026271 | C20: ISS_19481 | D20: 242330 | E20: 05001310500820100008800 | F20: 050013105008201000088 | G20: EJECUTIVO LABORAL | H20: 3658522 | I20: TOMAS ARTURO VALENCIA TORRES | J20: ISS | K20: ANTIOQUIA | L20: CONTINUA CON LA EJECUCION | M20: 28/11/2011 | N20: SIN FALLO | Z20: NO | AA20: No se cargó en la plataforma ekogui la pieza procesal DEMANDA-ORDINARIA. | AB20: SI | AD20: SI | AF20: SI | AH20: ERROR | AN20: Addy | AO20: ID_00026271
A21: UNION TEMPORAL VILLEGAS CONSULTORES JURIDICOS | B21: ID_00028271 | C21: ISS_05248 | D21: 53811 | E21: 05001310500820090088100 | F21: 050013105008200900881 | G21: EJECUTIVO LABORAL | H21: 8214151 | I21: JAIME RODRIGO DIAZ RESTREPO | J21: ISS | K21: ANTIOQUIA | L21: CONTINUA CON LA EJECUCION | M21: 11/10/2011 | N21: SIN FALLO | Z21: SI | AB21: SI | AD21: SI | AF21: SI | AN21: Leonardo | AO21: ID_00028271
A22: UNION TEMPORAL VILLEGAS CONSULTORES JURIDICOS | B22: ID_00028360 | C22: ISS_10921 | D22: 1173979 | E22: 05001310500220100047400 | F22: 050013105002201000474 | G22: EJECUTIVO LABORAL | H22: 8235195 | I22: JOSE ARNOLDO MARIN MARIN | J22: ISS | K22: ANTIOQUIA | L22: CONTINUA CON LA EJECUCION | M22: 18/09/2012 | N22: SIN FALLO | Z22: SI | AB22: SI | AD22: SI | AF22: SI | AN22: Mary | AO22: ID_00028360
A23: UNION TEMPORAL VILLEGAS CONSULTORES JURIDICOS | B23: ID_00028364 | C23: ISS_19995 | D23: 185367 | E23: 05001310500820100098600 | F23: 050013105008201000986 | G23: EJECUTIVO LABORAL | H23: 6235530 | I23: FRANCISCO JOSE VELASQUEZ GALLEGO | J23: ISS | K23: ANTIOQUIA | L23: CONTINUA CON LA EJECUCION | M23: 5/04/2011 | N23: SIN FALLO | Z23: NO | AA23: No se cargó en la plataforma ekogui la pieza procesal DEMANDA QUE DA ORIGEN AL MANDAMIENTO DE PAGO. | AB23: SI | AD23: NO | AE23: No se cargó en la plataforma Ekogui la pieza procesal de contestación de demanda | AF23: SI | AH23: ERROR | AN23: Manuel | AO23: ID_00028364
A24: WISS CONSULTORIA JURIDICA SAS | B24: ID_00028387 | C24: ISS_17803 | D24: 199459 | E24: 05001310500920100061800 | F24: 050013105009201000618 | G24: EJECUTIVO LABORAL | H24: 8238934 | I24: JOAQUIN EMILIO SANCHEZ LOPEZ | J24: ISS | K24: ANTIOQUIA | L24: CONTINUA CON LA EJECUCION | M24: 16/11/2011 | N24: SIN FALLO | Z24: SI | AB24: SI | AD24: NO | AE24: No se cargó en la plataforma ekogui la pieza procesal EXCEPCIONES | AF24: SI | AH24: ERROR | AN24: Addy | AO24: ID_00028387
A25: UNION TEMPORAL VILLEGAS CONSULTORES JURIDICOS | B25: ID_00028398 | C25: ISS_19901 | D25: 53162 | E25: 05001310500820080020900 | F25: 050013105008200800209 | G25: EJECUTIVO LABORAL | H25: 8240246 | I25: GUILLERMO DE JESUS VASQUEZ RAMOS | J25: ISS | K25: ANTIOQUIA | L25: SIN FALLO | N25: SIN FALLO | Z25: NO | AA25: No se cargó en la plataforma ekogui la pieza procesal DEMANDA-ORDINARIA. | AB25: NO | AC25: No se cargó en la plataforma ekogui la pieza procesal MANDAMIENTO DE PAGO. | AD25: SI | AF25: SI | AH25: ERROR | AN25: Addy | AO25: ID_00028398
A26: UNION TEMPORAL VILLEGAS CONSULTORES JURIDICOS | B26: ID_00028416 | C26: ISS_03507 | D26: 242265 | E26: 05001310500820100063900 | F26: 050013105008201000639 | G26: EJECUTIVO LABORAL | H26: 8242575 | I26: GUSTAVO ANTONIO CARDONA ARENAS | J26: ISS | K26: ANTIOQUIA | L26: CONTINUA CON LA EJECUCION | M26: 10/11/2011 | N26: SIN FALLO | Z26: SI | AB26: SI | AD26: SI | AF26: SI | AN26: Leonardo | AO26: ID_00028416
A27: UNION TEMPORAL VILLEGAS CONSULTORES JURIDICOS | B27: ID_00028433 | C27: ISS_08618 | D27: 242288 | E27: 05001310500820110012100 | F27: 050013105008201100121 | G27: EJECUTIVO LABORAL | H27: 8244736 | I27: LUIS ENRIQUE HENAO GIRALDO | J27: ISS | K27: ANTIOQUIA | L27: CONTINUA CON LA EJECUCION | M27: 28/11/2011 | N27: SIN FALLO | Z27: SI | AB27: SI | AD27: SI | AF27: SI | AN27: Mary | AO27: ID_00028433
A28: UNION TEMPORAL VILLEGAS CONSULTORES JURIDICOS | B28: ID_00028446 | C28: ISS_20381 | D28: 241767 | E28: 05001310500220110033900 | F28: 050013105002201100339 | G28: EJECUTIVO LABORAL | H28: 8245655 | I28: MANUEL SALVADOR VERGARA MONTOYA | J28: ISS | K28: ANTIOQUIA | L28: CONTINUA CON LA EJECUCION | M28: 13/08/2012 | N28: SIN FALLO | Z28: NO | AA28: No se cargó en la plataforma ekogui la pieza procesal DEMANDA QUE DA ORIGEN AL MANDAMIENTO DE PAGO. | AB28: SI | AD28: SI | AF28: SI | AH28: ERROR | AN28: Manuel | AO28: ID_00028446
A29: SOLUCIONES JURIDICAS Y EMPRESARIAL SJC SAS | B29: ID_00028663 | C29: ISS_01828 | D29: 241786 | E29: 05001310500320090136100 | F29: 050013105003200901361 | G29: EJECUTIVO LABORAL | H29: 8265607 | I29: LUIS ANGEL ARRUBLA DIOSA | J29: ISS | K29: ANTIOQUIA | L29: SIN FALLO | N29: SIN FALLO | Z29: SI | AB29: SI | AD29: NO APLICA | AF29: NO APLICA | AN29: Addy | AO29: ID_00028663
A30: UNION TEMPORAL VILLEGAS CONSULTORES JURIDICOS | B30: ID_00028681 | C30: ISS_02187 | D30: 242261 | E30: 05001310500820100020100 | F30: 050013105008201000201 | G30: EJECUTIVO LABORAL | H30: 8267158 | I30: JAVIER HINCAPIE BEDOYA | J30: ISS | K30: ANTIOQUIA | L30: CONTINUA CON LA EJECUCION | M30: 28/11/2011 | N30: SIN FALLO | Z30: NO | AA30: No se cargó en la plataforma ekogui la pieza procesal DEMANDA-ORDINARIA. | AB30: NO | AC30: No se cargó en la plataforma ekogui la pieza procesal MANDAMIENTO DE PAGO. | AD30: NO APLICA | AF30: NO APLICA | AH30: ERROR | AN30: Addy | AO30: ID_00028681
A31: UNION TEMPORAL VILLEGAS CONSULTORES JURIDICOS | B31: ID_00028764 | C31: ISS_03974 | D31: 1193234 | E31: 05001310500820110103400 | F31: 050013105008201101034 | G31: EJECUTIVO LABORAL | H31: 8272813 | I31: LUIS CARLOS CASTAÑEDA CARDONA | J31: ISS | K31: ANTIOQUIA | L31: CONTINUA CON LA EJECUCION | M31: 19/11/2012 | N31: SIN FALLO | Z31: SI | AB31: SI | AD31: NO | AE31: No se cargó en la plataforma ekogui la pieza procesal MANDAMIENTO DE PAGO. | AF31: SI | AH31: ERROR | AN31: Leonardo | AO31: ID_00028764
A32: UNION TEMPORAL SUPRA LEGAL | B32: ID_00031669 | C32: ISS_00629 | D32: 47548 | E32: 05001310500420080019100 | F32: 050013105004200800191 | G32: EJECUTIVO LABORAL | H32: 21376215 | I32: YOLANDA DE JESUS ALVAREZ GOMEZ | J32: ISS | K32: ANTIOQUIA | L32: CONTINUA CON LA EJECUCION | M32: 15/07/2010 | N32: SIN FALLO | Z32: NO | AA32: No se cargó en la plataforma ekogui la pieza procesal DEMANDA QUE DA ORIGEN AL MANDAMIENTO DE PAGO. | AB32: SI | AD32: SI | AF32: SI | AH32: ERROR | AN32: Mary | AO32: ID_00031669
A33: UNION TEMPORAL VILLEGAS CONSULTORES JURIDICOS | B33: ID_00031816 | C33: ISS_19606 | D33: 242912 | E33: 05001310501420110069900 | F33: 050013105014201100699 | G33: EJECUTIVO LABORAL | H33: 21458933 | I33: ARNOBIA DE JESUS VANEGAS MONTOYA | J33: ISS | K33: ANTIOQUIA | L33: CONTINUA CON LA EJECUCION | M33: 23/11/2011 | N33: SIN FALLO | Z33: NO | AA33: No se cargó en la plataforma ekogui la pieza procesal DEMANDA QUE DA ORIGEN AL MANDAMIENTO DE PAGO. | AB33: SI | AD33: NO | AE33: No se cargó en la plataforma ekogui la pieza procesal EXCEPCIONES | AF33: SI | AH33: ERROR | AN33: Mary | AO33: ID_00031816
A34: UNION TEMPORAL VILLEGAS CONSULTORES JURIDICOS | B34: ID_00033996 | C34: ISS_11955 | D34: 53695 | E34: 05001310500820090061100 | F34: 050013105008200900611 | G34: EJECUTIVO LABORAL | H34: 32431680 | I34: MARIA ADELAIDA MOLINA DE RAMIREZ | J34: ISS | K34: ANTIOQUIA | L34: CONTINUA CON LA EJECUCION | M34: 28/09/2010 | N34: SIN FALLO | Z34: SI | AB34: SI | AD34: SI | AF34: SI | AN34: Manuel | AO34: ID_00033996
A35: UNION TEMPORAL SUPRA LEGAL | B35: ID_00034062 | C35: ISS_07789 | D35: 1146878 | E35: 05001310500720080039500 | F35: 050013105007200800395 | G35: EJECUTIVO LABORAL | H35: 32444222 | I35: MARIA OTILIA GOMEZ DE SUAREZ | J35: ISS | K35: ANTIOQUIA | L35: CONTINUA CON LA EJECUCION | M35: 16/03/2012 | N35: SIN FALLO | Z35: SI | AB35: SI | AD35: SI | AF35: SI | AN35: Manuel | AO35: ID_00034062
A36: UNION TEMPORAL VILLEGAS CONSULTORES JURIDICOS | B36: ID_00034526 | C36: ISS_03686 | D36: 242266 | E36: 05001310500820110065300 | F36: 050013105008201100653 | G36: EJECUTIVO LABORAL | H36: 32508916 | I36: ROSALBA CARDONA ORTIZ | J36: ISS | K36: ANTIOQUIA | L36: CONTINUA CON LA EJECUCION | M36: 19/10/2011 | N36: SIN FALLO | Z36: NO | AA36: No se cargó en la plataforma ekogui la pieza procesal DEMANDA-ORDINARIA. | AB36: NO | AC36: No se cargó en la plataforma ekogui la pieza procesal DEMANDA-ORDINARIA. | AD36: SI | AF36: SI | AH36: ERROR | AN36: Addy | AO36: ID_00034526
A37: UNION TEMPORAL VILLEGAS CONSULTORES JURIDICOS | B37: ID_00036602 | C37: ISS_01719 | D37: 53448 | E37: 05001310500820090002201 | F37: 050013105008200900022 | G37: EJECUTIVO LABORAL | H37: 70160545 | I37: LUIS EDUARDO ARISTIZABAL QUINTERO | J37: ISS | K37: ANTIOQUIA | L37: CONTINUA CON LA EJECUCION | M37: 14/03/2012 | N37: SIN FALLO | Z37: SI | AB37: SI | AD37: SI | AF37: SI | AN37: Leonardo | AO37: ID_00036602
A38: UNION TEMPORAL VILLEGAS CONSULTORES JURIDICOS | B38: ID_00039097 | C38: ISS_INAC_000133 | D38: 241640 | E38: 05001310500220090085900 | F38: 050013105002200900859 | G38: EJECUTIVO LABORAL | H38: 3559595 | I38: JESUS ANTONIO AGUDELO AGUIRRE | J38: ISS | K38: ANTIOQUIA | L38: CONTINUA CON LA EJECUCION | M38: 15/11/2011 | N38: SIN FALLO | Z38: SI | AB38: SI | AD38: SI | AF38: SI | AN38: Mary | AO38: ID_00039097
A39: UNION TEMPORAL VILLEGAS CONSULTORES JURIDICOS | B39: ID_00039439 | C39: ISS_INAC_000475 | D39: 537319 | E39: 05001310500220070038200 | F39: 050013105002200700382 | G39: EJECUTIVO LABORAL | H39: 71330508 | I39: MARIO DE JESUS ALVAREZ MAYA | J39: ISS | K39: ANTIOQUIA | L39: CONTINUA CON LA EJECUCION | M39: 11/04/2014 | N39: SIN FALLO | Z39: SI | AB39: SI | AD39: SI | AF39: SI | AN39: Manuel | AO39: ID_00039439
A40: UNION TEMPORAL VILLEGAS CONSULTORES JURIDICOS | B40: ID_00039456 | C40: ISS_INAC_000492 | D40: 53225 | E40: 05001310500820080050700 | F40: 050013105008200800507 | G40: EJECUTIVO LABORAL | H40: 8226204 | I40: LEONEL DE JESUS ALVAREZ ORTIZ | J40: ISS | K40: ANTIOQUIA | L40: CONTINUA CON LA EJECUCION | M40: 12/03/2009 | N40: SIN FALLO | Z40: NO | AA40: No se cargó en la plataforma ekogui la pieza procesal DEMANDA-ORDINARIA. | AB40: SI | AD40: SI | AF40: SI | AH40: ERROR | AN40: Addy | AO40: ID_00039456
A41: UNION TEMPORAL VILLEGAS CONSULTORES JURIDICOS | B41: ID_00039622 | C41: ISS_INAC_000658 | D41: 58742 | E41: 05001310501220070013500 | F41: 050013105012200700135 | G41: EJECUTIVO LABORAL | H41: 3303804 | I41: LUIS ANIBAL AMAYA HERRERA | J41: ISS | K41: ANTIOQUIA | L41: CONTINUA CON LA EJECUCION | M41: 24/08/2009 | N41: SIN FALLO | Z41: NO | AA41: No se cargó en la plataforma ekogui la pieza procesal DEMANDA QUE DA ORIGEN AL MANDAMIENTO DE PAGO. | AB41: NO | AC41: No se cargó en la plataforma ekogui la pieza procesal MANDAMIENTO DE PAGO. | AD41: NO | AE41: No se cargó en la plataforma ekogui la pieza procesal MANDAMIENTO DE PAGO. | AF41: NO | AG41: No se cargó en la plataforma ekogui la pieza procesal AUTO QUE ORDENA/NO ORDENA CONTINUAR CON LA EJECUCION. | AH41: ERROR | AN41: Leonardo | AO41: ID_00039622
A42: UNION TEMPORAL VILLEGAS CONSULTORES JURIDICOS | B42: ID_00039984 | C42: ISS_INAC_001020 | D42: 53659 | E42: 05001310500820090050600 | F42: 050013105008200900506 | G42: EJECUTIVO LABORAL | H42: 603769 | I42: JOAQUIN GUILLERMO ARENAS CARVAJAL | J42: ISS | K42: ANTIOQUIA | L42: CONTINUA CON LA EJECUCION | M42: 12/02/2010 | N42: SIN FALLO | Z42: NO | AA42: No se cargó en la plataforma ekogui la pieza procesal DEMANDA QUE DA ORIGEN AL MANDAMIENTO DE PAGO. | AB42: SI | AD42: NO | AE42: No se cargó en la plataforma ekogui la pieza procesal EXCEPCIONES | AF42: SI | AH42: ERROR | AN42: Mary | AO42: ID_00039984
A43: WISS CONSULTORIA JURIDICA SAS | B43: ID_00039990 | C43: ISS_INAC_001026 | D43: 54495 | E43: 05001310500920070106700 | F43: 050013105009200701067 | G43: EJECUTIVO LABORAL | H43: 646791 | I43: GENARO ANTONIO ARENAS FERNANDEZ | J43: ISS | K43: ANTIOQUIA | L43: CONTINUA CON LA EJECUCION | M43: 25/02/2009 | N43: SIN FALLO | Z43: SI | AB43: SI | AD43: NO | AE43: No se cargó en la plataforma ekogui la pieza procesal MANDAMIENTO DE PAGO. | AF43: SI | AH43: ERROR | AN43: Leonardo | AO43: ID_00039990
A44: UNION TEMPORAL VILLEGAS CONSULTORES JURIDICOS | B44: ID_00040439 | C44: ISS_INAC_001475 | D44: 241987 | E44: 05001310500520110067000 | F44: 050013105005201100670 | G44: EJECUTIVO LABORAL | H44: 32435168 | I44: CONSUELO DEL CARMEN BEDOYA GUERRA | J44: ISS | K44: ANTIOQUIA | L44: CONTINUA CON LA EJECUCION | M44: 18/10/2011 | N44: FALLO NO APELADO | O44: 18/10/2011 | Z44: SI | AB44: SI | AD44: SI | AF44: SI | AN44: Manuel | AO44: ID_00040439
A45: WISS CONSULTORIA JURIDICA SAS | B45: ID_00040471 | C45: ISS_INAC_001507 | D45: 242363 | E45: 05001310500920090065500 | F45: 050013105009200900655 | G45: EJECUTIVO LABORAL | H45: 3303792 | I45: JAIME DE LA CRUZ BEDOYA PARRA | J45: ISS | K45: ANTIOQUIA | L45: CONTINUA CON LA EJECUCION | M45: 24/02/2012 | N45: SIN FALLO | Z45: SI | AB45: NO | AC45: No se cargó en la plataforma ekogui la pieza procesal MANDAMIENTO DE PAGO. | AD45: NO | AE45: No se cargó en la plataforma ekogui la pieza procesal EXCEPCIONES | AF45: SI | AH45: ERROR | AN45: Mary | AO45: ID_00040471
A46: UNION TEMPORAL VILLEGAS CONSULTORES JURIDICOS | B46: ID_00040526 | C46: ISS_INAC_001562 | D46: 184794 | E46: 05001310500220070034700 | F46: 050013105002200700347 | G46: EJECUTIVO LABORAL | H46: 8217197 | I46: IVAN DE JESUS BENITEZ CASTRO | J46: ISS | K46: ANTIOQUIA | L46: CONTINUA CON LA EJECUCION | M46: 8/05/2008 | N46: SIN FALLO | Z46: SI | AB46: SI | AD46: SI | AF46: SI | AN46: Addy | AO46: ID_00040526
A47: WISS CONSULTORIA JURIDICA SAS | B47: ID_00040713 | C47: ISS_INAC_001749 | D47: 54365 | E47: 05001310500920060078700 | F47: 050013105009200600787 | G47: EJECUTIVO LABORAL | H47: 3329412 | I47: JUSTO PASTOR OCAMPO BETANCUR | J47: ISS | K47: ANTIOQUIA | L47: CONTINUA CON LA EJECUCION | M47: 6/03/2007 | N47: SIN FALLO | Z47: NO | AA47: No se cargó en la plataforma ekogui la pieza procesal DEMANDA QUE DA ORIGEN AL MANDAMIENTO DE PAGO. | AB47: SI | AD47: NO | AE47: No se cargó en la plataforma Ekogui la pieza procesal de contestación de demanda | AF47: SI | AH47: ERROR | AN47: Manuel | AO47: ID_00040713
A48: UNION TEMPORAL VILLEGAS CONSULTORES JURIDICOS | B48: ID_00041021 | C48: ISS_INAC_002057 | D48: 1173812 | E48: 05001310500520110129700 | F48: 050013105005201101297 | G48: EJECUTIVO LABORAL | H48: 8253825 | I48: LUIS GUILLERMO CADAVID BERRIO | J48: ISS | K48: ANTIOQUIA | L48: CONTINUA CON LA EJECUCION | M48: 17/04/2012 | N48: SIN FALLO | Z48: SI | AB48: SI | AD48: NO | AE48: No se cargó en la plataforma ekogui la pieza procesal MANDAMIENTO DE PAGO. | AF48: NO | AG48: No se cargó en la plataforma ekogui la pieza procesal AUTO QUE ORDENA/NO ORDENA CONTINUAR CON LA EJECUCION. | AH48: ERROR | AN48: Leonardo | AO48: ID_00041021
A49: UNION TEMPORAL VILLEGAS CONSULTORES JURIDICOS | B49: ID_00041077 | C49: ISS_INAC_002113 | D49: 241991 | E49: 05001310500520080063600 | F49: 050013105005200800636 | G49: EJECUTIVO LABORAL | H49: 3322036 | I49: DARIO DE JESUS CALDERON LOPERA | J49: ISS | K49: ANTIOQUIA | L49: SIN FALLO | N49: SIN FALLO | Z49: NO | AA49: No se cargó en la plataforma ekogui la pieza procesal DEMANDA QUE DA ORIGEN AL MANDAMIENTO DE PAGO. | AB49: NO | AC49: No se cargó en la plataforma ekogui la pieza procesal MANDAMIENTO DE PAGO. | AD49: NO | AE49: No se cargó en la plataforma ekogui la pieza procesal EXCEPCIONES | AF49: NO | AG49: No se cargó en la plataforma ekogui la pieza procesal AUTO QUE ORDENA/NO ORDENA CONTINUAR CON LA EJECUCION. | AH49: ERROR | AN49: Mary | AO49: ID_00041077
A50: UNION TEMPORAL VILLEGAS CONSULTORES JURIDICOS | B50: ID_00041228 | C50: ISS_INAC_002264 | D50: 242262 | E50: 05001310500820090088700 | F50: 050013105008200900887 | G50: EJECUTIVO LABORAL | H50: 3307233 | I50: JESUS MARIA CANO MONSALVE | J50: ISS | K50: ANTIOQUIA | L50: CONTINUA CON LA EJECUCION | M50: 7/09/2012 | N50: SIN FALLO | Z50: SI | AB50: SI | AD50: SI | AF50: SI | AN50: Manuel | AO50: ID_00041228
A51: UNION TEMPORAL VILLEGAS CONSULTORES JURIDICOS | B51: ID_00041395 | C51: ISS_INAC_002431 | D51: 241665 | E51: 05001310500220110021100 | F51: 050013105002201100211 | G51: EJECUTIVO LABORAL | H51: 8260460 | I51: ISRAEL JOSE CARDONA CARMONA | J51: ISS | K51: ANTIOQUIA | L51: CONTINUA CON LA EJECUCION | M51: 23/05/2012 | N51: SIN FALLO | Z51: NO | AA51: No se cargó en la plataforma ekogui la pieza procesal DEMANDA-ORDINARIA. | AB51: SI | AD51: SI | AF51: SI | AH51: ERROR | AN51: Addy | AO51: ID_00041395
A52: UNION TEMPORAL VILLEGAS CONSULTORES JURIDICOS | B52: ID_00041738 | C52: ISS_INAC_002774 | D52: 242722 | E52: 05001310501220100013300 | F52: 050013105012201000133 | G52: EJECUTIVO LABORAL | H52: 3308017 | I52: RAMON ANTONIO CASTAÑO ARISTIZABAL | J52: ISS | K52: ANTIOQUIA | L52: CONTINUA CON LA EJECUCION | M52: 2/09/2011 | N52: SIN FALLO | Z52: SI | AB52: SI | AD52: SI | AF52: SI | AN52: Leonardo | AO52: ID_00041738
A53: UNION TEMPORAL VILLEGAS CONSULTORES JURIDICOS | B53: ID_00042038 | C53: ISS_INAC_003074 | D53: 349055 | E53: 05001310500820110084800 | F53: 050013105008201100848 | G53: EJECUTIVO LABORAL | H53: 526913 | I53: MIGUEL ANTONIO CHICA CANO | J53: ISS | K53: ANTIOQUIA | L53: CONTINUA CON LA EJECUCION | M53: 20/10/2011 | N53: SIN FALLO | Z53: NO | AA53: No se cargó en la plataforma ekogui la pieza procesal DEMANDA QUE DA ORIGEN AL MANDAMIENTO DE PAGO. | AB53: NO | AC53: No se cargó en la plataforma ekogui la pieza procesal MANDAMIENTO DE PAGO. | AD53: NO | AE53: No se cargó en la plataforma ekogui la pieza procesal EXCEPCIONES | AF53: SI | AH53: ERROR | AN53: Mary | AO53: ID_00042038
A54: WISS CONSULTORIA JURIDICA SAS | B54: ID_00042372 | C54: ISS_INAC_003408 | D54: 1189485 | E54: 05001310501720100112300 | F54: 050013105017201001123 | G54: EJECUTIVO LABORAL | H54: 8270104 | I54: CRUZ MUÑOZ SERGIO DE JESUS | J54: ISS | K54: ANTIOQUIA | L54: CONTINUA CON LA EJECUCION | M54: 17/03/2015 | N54: SIN FALLO | Z54: SI | AB54: SI | AD54: SI | AF54: SI | AN54: Addy | AO54: ID_00042372
A55: UNION TEMPORAL VILLEGAS CONSULTORES JURIDICOS | B55: ID_00042457 | C55: ISS_INAC_003493 | D55: 53441 | E55: 05001310500820090001100 | F55: 050013105008200900011 | G55: EJECUTIVO LABORAL | H55: 8239342 | I55: RAFAEL ANGEL DAZA GARCES | J55: ISS | K55: ANTIOQUIA | L55: CONTINUA CON LA EJECUCION | M55: 17/11/2010 | N55: SIN FALLO | Z55: SI | AB55: SI | AD55: SI | AF55: SI | AN55: Manuel | AO55: ID_00042457
A56: UNION TEMPORAL VILLEGAS CONSULTORES JURIDICOS | B56: ID_00042497 | C56: ISS_INAC_003533 | D56: 52930 | E56: 05001310500820060059300 | F56: 050013105008200600593 | G56: EJECUTIVO LABORAL | H56: 8253289 | I56: MANUEL FEDERICO DIAZ HERNANDEZ | J56: ISS | K56: ANTIOQUIA | L56: CONTINUA CON LA EJECUCION | M56: 20/06/2007 | N56: SIN FALLO | Z56: NO | AA56: No se cargó en la plataforma ekogui la pieza procesal DEMANDA-ORDINARIA. | AB56: NO | AC56: No se cargó en la plataforma ekogui la pieza procesal DEMANDA-ORDINARIA. | AD56: NO APLICA | AF56: NO APLICA | AH56: ERROR | AN56: Addy | AO56: ID_00042497
A57: UNION TEMPORAL SUPRA LEGAL | B57: ID_00042663 | C57: ISS_INAC_003699 | D57: 47536 | E57: 05001310500420080014200 | F57: 050013105004200800142 | G57: EJECUTIVO LABORAL | H57: 1591716 | I57: LUIS HERLINDO DURANGO VARGAS | J57: ISS | K57: ANTIOQUIA | L57: CONTINUA CON LA EJECUCION | M57: 14/02/2011 | N57: SIN FALLO | Z57: NO | AA57: No se cargó en la plataforma ekogui la pieza procesal DEMANDA QUE DA ORIGEN AL MANDAMIENTO DE PAGO. | AB57: SI | AD57: SI | AF57: SI | AH57: ERROR | AN57: Mary | AO57: ID_00042663
A58: SOLUCIONES JURIDICAS Y EMPRESARIAL SJC SAS | B58: ID_00042672 | C58: ISS_INAC_003708 | D58: 1149434 | E58: 05001310500320090085500 | F58: 050013105003200900855 | G58: EJECUTIVO LABORAL | H58: 71687892 | I58: JESUS HERNANDO ECHAVARRIA ARA | J58: ISS | K58: ANTIOQUIA | L58: CONTINUA CON LA EJECUCION | M58: 24/02/2016 | N58: SIN FALLO | Z58: NO | AA58: No se cargó en la plataforma ekogui la pieza procesal DEMANDA-ORDINARIA. | AB58: NO APLICA | AD58: NO APLICA | AF58: NO APLICA | AH58: ERROR | AN58: Addy | AO58: ID_00042672
A59: WISS CONSULTORIA JURIDICA SAS | B59: ID_00043100 | C59: ISS_INAC_004136 | D59: 242373 | E59: 05001310500920070098000 | F59: 050013105009200700980 | G59: EJECUTIVO LABORAL | H59: 22119824 | I59: CARMEN EMILIA FLOREZ DE QUICENO | J59: ISS | K59: ANTIOQUIA | L59: CONTINUA CON LA EJECUCION | M59: 30/11/2011 | N59: SIN FALLO | Z59: SI | AB59: SI | AD59: SI | AF59: SI | AN59: Leonardo | AO59: ID_00043100
A60: UNION TEMPORAL VILLEGAS CONSULTORES JURIDICOS | B60: ID_00043262 | C60: ISS_INAC_004298 | D60: 242279 | E60: 05001310500820110031200 | F60: 050013105008201100312 | G60: EJECUTIVO LABORAL | H60: 32454656 | I60: RUBIELA DEL SOCORRO GALINDO AGUDELO | J60: ISS | K60: ANTIOQUIA | L60: CONTINUA CON LA EJECUCION | M60: 3/08/2012 | N60: SIN FALLO | Z60: NO | AA60: No se cargó en la plataforma ekogui la pieza procesal DEMANDA QUE DA ORIGEN AL MANDAMIENTO DE PAGO. | AB60: SI | AD60: NO | AE60: No se cargó en la plataforma ekogui la pieza procesal MANDAMIENTO DE PAGO. | AF60: SI | AH60: ERROR | AN60: Leonardo | AO60: ID_00043262
A61: UNION TEMPORAL VILLEGAS CONSULTORES JURIDICOS | B61: ID_00043414 | C61: ISS_INAC_004450 | D61: 242881 | E61: 05001310501420110126400 | F61: 050013105014201101264 | G61: EJECUTIVO LABORAL | H61: 21728738 | I61: LUZ ELENA GARCES DE LONDOÑO | J61: ISS | K61: ANTIOQUIA | L61: SIN FALLO | N61: SIN FALLO | Z61: NO | AA61: No se cargó en la plataforma ekogui la pieza procesal DEMANDA QUE DA ORIGEN AL MANDAMIENTO DE PAGO. | AB61: NO | AC61: No se cargó en la plataforma ekogui la pieza procesal MANDAMIENTO DE PAGO. | AD61: NO | AE61: No se cargó en la plataforma ekogui la pieza procesal EXCEPCIONES | AF61: NO | AG61: No se cargó en la plataforma ekogui la pieza procesal AUTO QUE ORDENA/NO ORDENA CONTINUAR CON LA EJECUCION. | AH61: ERROR | AN61: Mary | AO61: ID_00043414
A62: UNION TEMPORAL VILLEGAS CONSULTORES JURIDICOS | B62: ID_00043496 | C62: ISS_INAC_004532 | D62: 59448 | E62: 05001310501220090000200 | F62: 050013105012200900002 | G62: EJECUTIVO LABORAL | H62: 32399993 | I62: FABIOLA GARCIA GUTIERREZ | J62: ISS | K62: ANTIOQUIA | L62: CONTINUA CON LA EJECUCION | M62: 14/08/2009 | N62: SIN FALLO | Z62: SI | AB62: SI | AD62: SI | AF62: SI | AN62: Manuel | AO62: ID_00043496
A63: UNION TEMPORAL VILLEGAS CONSULTORES JURIDICOS | B63: ID_00043695 | C63: ISS_INAC_004732 | D63: 44725 | E63: 05001310500220070094900 | F63: 050013105002200700949 | G63: EJECUTIVO LABORAL | H63: 3322804 | I63: MARIO DE JESUS GAVIRIA MAYA | J63: ISS | K63: ANTIOQUIA | L63: CONTINUA CON LA EJECUCION | M63: 4/07/2008 | N63: SIN FALLO | Z63: NO | AA63: No se cargó en la plataforma ekogui la pieza procesal DEMANDA-ORDINARIA. | AB63: NO | AC63: No se cargó en la plataforma ekogui la pieza procesal DEMANDA-ORDINARIA. | AD63: SI | AF63: SI | AH63: ERROR | AN63: Addy | AO63: ID_00043695
A64: UNION TEMPORAL VILLEGAS CONSULTORES JURIDICOS | B64: ID_00043721 | C64: ISS_INAC_004758 | D64: 1188085 | E64: 05001310502120110122400 | F64: 050013105021201101224 | G64: EJECUTIVO LABORAL | H64: 32460511 | I64: LUZ ARACELLY GAVIRIA VALENCIA | J64: ISS | K64: ANTIOQUIA | L64: SIN FALLO | N64: SIN FALLO | Z64: SI | AB64: SI | AD64: SI | AF64: NO | AG64: No se cargó en la plataforma ekogui la pieza procesal AUTO QUE ORDENA/NO ORDENA CONTINUAR CON LA EJECUCION. | AH64: ERROR | AN64: Leonardo | AO64: ID_00043721
A65: UNION TEMPORAL VILLEGAS CONSULTORES JURIDICOS | B65: ID_00043909 | C65: ISS_INAC_004946 | D65: 59162 | E65: 05001310501220080055000 | F65: 050013105012200800550 | G65: EJECUTIVO LABORAL | H65: 3561395 | I65: ROBERTO DE JESUS GIRALDO MONTOYA | J65: ISS | K65: ANTIOQUIA | L65: CONTINUA CON LA EJECUCION | M65: 24/04/2009 | N65: SIN FALLO | Z65: NO | AA65: No se cargó en la plataforma ekogui la pieza procesal DEMANDA QUE DA ORIGEN AL MANDAMIENTO DE PAGO. | AB65: NO | AC65: No se cargó en la plataforma ekogui la pieza procesal MANDAMIENTO DE PAGO. | AD65: NO | AE65: No se cargó en la plataforma ekogui la pieza procesal EXCEPCIONES | AF65: NO | AG65: No se cargó en la plataforma ekogui la pieza procesal AUTO QUE ORDENA/NO ORDENA CONTINUAR CON LA EJECUCION. | AH65: ERROR | AN65: Mary | AO65: ID_00043909
A66: UNION TEMPORAL VILLEGAS CONSULTORES JURIDICOS | B66: ID_00044216 | C66: ISS_INAC_005253 | D66: 53597 | E66: 05001310500820090034900 | F66: 050013105008200900349 | G66: EJECUTIVO LABORAL | H66: 42937377 | I66: BEATRIZ GOMEZ QUIROZ | J66: ISS | K66: ANTIOQUIA | L66: CONTINUA CON LA EJECUCION | M66: 20/04/2010 | N66: SIN FALLO | Z66: SI | AB66: SI | AD66: SI | AF66: SI | AN66: Manuel | AO66: ID_00044216
A67: UNION TEMPORAL VILLEGAS CONSULTORES JURIDICOS | B67: ID_00044780 | C67: ISS_INAC_005817 | D67: 53076 | E67: 05001310500820070101200 | F67: 050013105008200701012 | G67: EJECUTIVO LABORAL | H67: 3470779 | I67: PEDRO PABLO HENAO BETANCUR | J67: ISS | K67: ANTIOQUIA | L67: CONTINUA CON LA EJECUCION | M67: 6/03/2009 | N67: SIN FALLO | Z67: NO | AA67: No se cargó en la plataforma ekogui la pieza procesal DEMANDA-ORDINARIA. | AB67: SI | AD67: SI | AF67: SI | AH67: ERROR | AN67: Addy | AO67: ID_00044780
A68: WISS CONSULTORIA JURIDICA SAS | B68: ID_00044896 | C68: ISS_INAC_005933 | D68: 54395 | E68: 05001310500920070002200 | F68: 050013105009200700022 | G68: EJECUTIVO LABORAL | H68: 3470999 | I68: LUIS ALBERTO HERNANDEZ AGUDELO | J68: ISS | K68: ANTIOQUIA | L68: CONTINUA CON LA EJECUCION | M68: 13/05/2010 | N68: SIN FALLO | Z68: NO | AA68: No se cargó en la plataforma ekogui la pieza procesal DEMANDA QUE DA ORIGEN AL MANDAMIENTO DE PAGO. | AB68: SI | AD68: SI | AF68: SI | AH68: ERROR | AN68: Mary | AO68: ID_00044896
A69: UNION TEMPORAL SUPRA LEGAL | B69: ID_00044903 | C69: ISS_INAC_005940 | D69: 51574 | E69: 05001310500720070013100 | F69: 050013105007200700131 | G69: EJECUTIVO LABORAL | H69: 42970689 | I69: MARIA DOLORES HERNANDEZ ALVAREZ | J69: ISS | K69: ANTIOQUIA | L69: CONTINUA CON LA EJECUCION | M69: 19/05/2009 | N69: SIN FALLO | Z69: SI | AB69: SI | AD69: SI | AF69: SI | AN69: Mary | AO69: ID_00044903
A70: WISS CONSULTORIA JURIDICA SAS | B70: ID_00044920 | C70: ISS_INAC_005957 | D70: 242384 | E70: 05001310500920110076600 | F70: 050013105009201100766 | G70: EJECUTIVO LABORAL | H70: 6785325 | I70: HECTOR DE JESUS HERNANDEZ CARVAJAL | J70: ISS | K70: ANTIOQUIA | L70: CONTINUA CON LA EJECUCION | M70: 17/07/2012 | N70: SIN FALLO | Z70: NO | AA70: No se cargó en la plataforma ekogui la pieza procesal DEMANDA QUE DA ORIGEN AL MANDAMIENTO DE PAGO. | AB70: SI | AD70: NO | AE70: No se cargó en la plataforma Ekogui la pieza procesal de contestación de demanda | AF70: SI | AH70: ERROR | AN70: Manuel | AO70: ID_00044920
A71: UNION TEMPORAL VILLEGAS CONSULTORES JURIDICOS | B71: ID_00044997 | C71: ISS_INAC_006034 | D71: 242289 | E71: 05001310500820110041500 | F71: 050013105008201100415 | G71: EJECUTIVO LABORAL | H71: 770142 | I71: ROQUE DE JESUS HERNANDEZ QUIROZ | J71: ISS | K71: ANTIOQUIA | L71: CONTINUA CON LA EJECUCION | M71: 30/04/2012 | N71: SIN FALLO | Z71: NO | AA71: No se cargó en la plataforma ekogui la pieza procesal DEMANDA QUE DA ORIGEN AL MANDAMIENTO DE PAGO. | AB71: NO | AC71: No se cargó en la plataforma ekogui la pieza procesal MANDAMIENTO DE PAGO. | AD71: SI | AF71: SI | AH71: ERROR | AN71: Leonardo | AO71: ID_00044997
A72: UNION TEMPORAL VILLEGAS CONSULTORES JURIDICOS | B72: ID_00045063 | C72: ISS_INAC_006100 | D72: 1190655 | E72: 05001310500220080046000 | F72: 050013105002200800460 | G72: EJECUTIVO LABORAL | H72: 3333964 | I72: NOBARDO DE JESUS HERRERA GAVIRIA | J72: ISS | K72: ANTIOQUIA | L72: CONTINUA CON LA EJECUCION | M72: 3/07/2012 | N72: SIN FALLO | Z72: SI | AB72: SI | AD72: NO | AE72: No se cargó en la plataforma ekogui la pieza procesal EXCEPCIONES | AF72: SI | AH72: ERROR | AN72: Mary | AO72: ID_00045063
A73: SOLUCIONES JURIDICAS Y EMPRESARIAL SJC SAS | B73: ID_00045283 | C73: ISS_INAC_006320 | D73: 46471 | E73: 05001310500320090053400 | F73: 050013105003200900534 | G73: EJECUTIVO LABORAL | H73: 2897571 | I73: BELISARIO IBAÑEZ VARGAS | J73: ISS | K73: ANTIOQUIA | L73: CONTINUA CON LA EJECUCION | M73: 13/04/2016 | N73: SIN FALLO | Z73: SI | AB73: SI | AD73: SI | AF73: SI | AN73: Mary | AO73: ID_00045283
A74: WISS CONSULTORIA JURIDICA SAS | B74: ID_00045326 | C74: ISS_INAC_006363 | D74: 54733 | E74: 05001310500920080079800 | F74: 050013105009200800798 | G74: EJECUTIVO LABORAL | H74: 8239146 | I74: FERNANDO DEL SOCORRO ISAZA MORENO | J74: ISS | K74: ANTIOQUIA | L74: CONTINUA CON LA EJECUCION | M74: 4/11/2010 | N74: SIN FALLO | Z74: NO | AA74: No se cargó en la plataforma ekogui la pieza procesal DEMANDA-ORDINARIA. | AB74: NO | AC74: No se cargó en la plataforma ekogui la pieza procesal MANDAMIENTO DE PAGO. | AD74: NO | AE74: No se cargó en la plataforma ekogui la pieza procesal EXCEPCIONES | AF74: SI | AH74: ERROR | AN74: Addy | AO74: ID_00045326
A75: WISS CONSULTORIA JURIDICA SAS | B75: ID_00045811 | C75: ISS_INAC_006848 | D75: 242390 | E75: 05001310500920080109400 | F75: 050013105009200801094 | G75: EJECUTIVO LABORAL | H75: 3471747 | I75: JOSE LUIS LONDOÑO GRANADOS | J75: ISS | K75: ANTIOQUIA | L75: CONTINUA CON LA EJECUCION | M75: 30/09/2011 | N75: SIN FALLO | Z75: NO | AA75: No se cargó en la plataforma ekogui la pieza procesal DEMANDA QUE DA ORIGEN AL MANDAMIENTO DE PAGO. | AB75: NO | AC75: No se cargó en la plataforma ekogui la pieza procesal MANDAMIENTO DE PAGO. | AD75: NO | AE75: No se cargó en la plataforma ekogui la pieza procesal MANDAMIENTO DE PAGO. | AF75: NO | AG75: No se cargó en la plataforma ekogui la pieza procesal AUTO QUE ORDENA/NO ORDENA CONTINUAR CON LA EJECUCION. | AH75: ERROR | AN75: Leonardo | AO75: ID_00045811
A76: WISS CONSULTORIA JURIDICA SAS | B76: ID_00046477 | C76: ISS_INAC_007514 | D76: 55343 | E76: 05001310500920090115900 | F76: 050013105009200901159 | G76: EJECUTIVO LABORAL | H76: 22116115 | I76: MARTHA EUGENIA ZAPATA MANCO | J76: ISS | K76: ANTIOQUIA | L76: CONTINUA CON LA EJECUCION | M76: 25/06/2010 | N76: SIN FALLO | Z76: NO | AA76: No se cargó en la plataforma ekogui la pieza procesal DEMANDA QUE DA ORIGEN AL MANDAMIENTO DE PAGO. | AB76: SI | AD76: NO | AE76: No se cargó en la plataforma ekogui la pieza procesal EXCEPCIONES | AF76: SI | AH76: ERROR | AN76: Mary | AO76: ID_00046477
A77: WISS CONSULTORIA JURIDICA SAS | B77: ID_00046586 | C77: ISS_INAC_007623 | D77: 55116 | E77: 05001310500920090057700 | F77: 050013105009200900577 | G77: EJECUTIVO LABORAL | H77: 3322628 | I77: JOSE ROBERTO MARTINEZ SANCHEZ | J77: ISS | K77: ANTIOQUIA | L77: CONTINUA CON LA EJECUCION | M77: 10/02/2011 | N77: SIN FALLO | Z77: NO | AA77: No se cargó en la plataforma ekogui la pieza procesal DEMANDA QUE DA ORIGEN AL MANDAMIENTO DE PAGO. | AB77: NO | AC77: No se cargó en la plataforma ekogui la pieza procesal MANDAMIENTO DE PAGO. | AD77: NO | AE77: No se cargó en la plataforma Ekogui la pieza procesal de contestación de demanda | AF77: SI | AH77: ERROR | AN77: Manuel | AO77: ID_00046586
A78: WISS CONSULTORIA JURIDICA SAS | B78: ID_00046687 | C78: ISS_INAC_007724 | D78: 54657 | E78: 05001310500920080049500 | F78: 050013105009200800495 | G78: EJECUTIVO LABORAL | H78: 3358416 | I78: CARLOS EMILIO MAZO OSPINA | J78: ISS | K78: ANTIOQUIA | L78: CONTINUA CON LA EJECUCION | M78: 26/01/2009 | N78: SIN FALLO | Z78: NO | AA78: No se cargó en la plataforma ekogui la pieza procesal DEMANDA-ORDINARIA. | AB78: NO | AC78: No se cargó en la plataforma ekogui la pieza procesal MANDAMIENTO DE PAGO. | AD78: NO | AE78: No se cargó en la plataforma ekogui la pieza procesal EXCEPCIONES | AF78: NO APLICA | AH78: ERROR | AN78: Addy | AO78: ID_00046687
A79: UNION TEMPORAL VILLEGAS CONSULTORES JURIDICOS | B79: ID_00047022 | C79: ISS_INAC_008059 | D79: 2046258 | E79: 05001310500820110124300 | F79: 050013105008201101243 | G79: EJECUTIVO LABORAL | H79: 42968305 | I79: MARIA SOLEDAD MESA TORRES | J79: ISS | K79: ANTIOQUIA | L79: SIN FALLO | N79: SIN FALLO | Z79: SI | AB79: SI | AD79: SI | AF79: SI | AN79: Manuel | AO79: ID_00047022
A80: UNION TEMPORAL VILLEGAS CONSULTORES JURIDICOS | B80: ID_00047630 | C80: ISS_INAC_008667 | D80: 49258 | E80: 05001310500520080098100 | F80: 050013105005200800981 | G80: EJECUTIVO LABORAL | H80: 615751 | I80: PABLO EVELIO MORENO RODAS | J80: ISS | K80: ANTIOQUIA | L80: CONTINUA CON LA EJECUCION | M80: 28/06/2010 | N80: SIN FALLO | Z80: SI | AB80: SI | AD80: SI | AF80: SI | AN80: Addy | AO80: ID_00047630
A81: UNION TEMPORAL VILLEGAS CONSULTORES JURIDICOS | B81: ID_00048196 | C81: ISS_INAC_009233 | D81: 49649 | E81: 05001310500520090080800 | F81: 050013105005200900808 | G81: EJECUTIVO LABORAL | H81: 1249419 | I81: EGIDIO OROZCO GIRALDO | J81: ISS | K81: ANTIOQUIA | L81: CONTINUA CON LA EJECUCION | M81: 4/06/2010 | N81: SIN FALLO | Z81: SI | AB81: SI | AD81: SI | AF81: SI | AN81: Leonardo | AO81: ID_00048196
A82: WISS CONSULTORIA JURIDICA SAS | B82: ID_00048222 | C82: ISS_INAC_009259 | D82: 54346 | E82: 05001310500920060042300 | F82: 050013105009200600423 | G82: EJECUTIVO LABORAL | H82: 3404895 | I82: JOSE ADONAY OROZCO QUINTANA | J82: ISS | K82: ANTIOQUIA | L82: CONTINUA CON LA EJECUCION | M82: 16/05/2014 | N82: SIN FALLO | Z82: NO | AA82: No se cargó en la plataforma ekogui la pieza procesal DEMANDA QUE DA ORIGEN AL MANDAMIENTO DE PAGO. | AB82: NO | AC82: No se cargó en la plataforma ekogui la pieza procesal MANDAMIENTO DE PAGO. | AD82: NO | AE82: No se cargó en la plataforma ekogui la pieza procesal MANDAMIENTO DE PAGO. | AF82: SI | AH82: ERROR | AN82: Leonardo | AO82: ID_00048222
A83: WISS CONSULTORIA JURIDICA SAS | B83: ID_00048345 | C83: ISS_INAC_009382 | D83: 55352 | E83: 05001310500920100001200 | F83: 050013105009201000012 | G83: EJECUTIVO LABORAL | H83: 3435069 | I83: ORTIZ QUINTERO RAMON EMILIO | J83: ISS | K83: ANTIOQUIA | L83: CONTINUA CON LA EJECUCION | M83: 22/11/2010 | N83: SIN FALLO | Z83: SI | AB83: SI | AD83: SI | AF83: SI | AN83: Mary | AO83: ID_00048345
A84: UNION TEMPORAL VILLEGAS CONSULTORES JURIDICOS | B84: ID_00048502 | C84: ISS_INAC_009539 | D84: 2052746 | E84: 05001310500520120032600 | F84: 050013105005201200326 | G84: EJECUTIVO LABORAL | H84: 3465643 | I84: CARLOS ENRIQUE OSORNO HENAO | J84: ISS | K84: ANTIOQUIA | L84: CONTINUA CON LA EJECUCION | M84: 12/06/2012 | N84: SIN FALLO | Z84: SI | AB84: SI | AD84: SI | AF84: SI | AN84: Mary | AO84: ID_00048502
A85: WISS CONSULTORIA JURIDICA SAS | B85: ID_00048578 | C85: ISS_INAC_009615 | D85: 54389 | E85: 05001310500920060111400 | F85: 050013105009200601114 | G85: EJECUTIVO LABORAL | H85: 3309431 | I85: PEDRO JOSE OSPINA MARULANDA | J85: ISS | K85: ANTIOQUIA | L85: CONTINUA CON LA EJECUCION | M85: 9/05/2007 | N85: SIN FALLO | Z85: NO | AA85: No se cargó en la plataforma ekogui la pieza procesal DEMANDA QUE DA ORIGEN AL MANDAMIENTO DE PAGO. | AB85: SI | AD85: NO | AE85: No se cargó en la plataforma Ekogui la pieza procesal de contestación de demanda | AF85: SI | AH85: ERROR | AN85: Manuel | AO85: ID_00048578
A86: UNION TEMPORAL VILLEGAS CONSULTORES JURIDICOS | B86: ID_00048750 | C86: ISS_INAC_009787 | D86: 242306 | E86: 05001310500820110041800 | F86: 050013105008201100418 | G86: EJECUTIVO LABORAL | H86: 3642999 | I86: ANIBAL DE JESUS PALACIO MORENO | J86: ISS | K86: ANTIOQUIA | L86: CONTINUA CON LA EJECUCION | M86: 14/12/2011 | N86: SIN FALLO | Z86: SI | AB86: SI | AD86: SI | AF86: SI | AN86: Manuel | AO86: ID_00048750
A87: UNION TEMPORAL VILLEGAS CONSULTORES JURIDICOS | B87: ID_00049035 | C87: ISS_INAC_010072 | D87: 1209451 | E87: 05001310501020110010100 | F87: 050013105010201100101 | G87: EJECUTIVO LABORAL | H87: 8261368 | I87: ALFREDO ANTONIO PEREZ ARANGO | J87: ISS | K87: ANTIOQUIA | L87: CONTINUA CON LA EJECUCION | M87: 4/08/2017 | N87: SIN FALLO | Z87: NO | AA87: No se cargó en la plataforma ekogui la pieza procesal DEMANDA-ORDINARIA. | AB87: SI | AD87: SI | AF87: SI | AH87: ERROR | AN87: Addy | AO87: ID_00049035
A88: UNION TEMPORAL VILLEGAS CONSULTORES JURIDICOS | B88: ID_00049515 | C88: ISS_INAC_010552 | D88: 242769 | E88: 05001310501220060055100 | F88: 050013105012200600551 | G88: EJECUTIVO LABORAL | H88: 21545387 | I88: MARTA MARIA QUINTERO DE MARIN | J88: ISS | K88: ANTIOQUIA | L88: CONTINUA CON LA EJECUCION | M88: 20/08/2008 | N88: SIN FALLO | Z88: SI | AB88: SI | AD88: SI | AF88: SI | AN88: Leonardo | AO88: ID_00049515
A89: UNION TEMPORAL VILLEGAS CONSULTORES JURIDICOS | B89: ID_00049777 | C89: ISS_INAC_010814 | D89: 53442 | E89: 05001310500820090001400 | F89: 050013105008200900014 | G89: EJECUTIVO LABORAL | H89: 8223791 | I89: JESUS ELIVER RAMIREZ NAVARRO | J89: ISS | K89: ANTIOQUIA | L89: CONTINUA CON LA EJECUCION | M89: 19/08/2009 | N89: SIN FALLO | Z89: SI | AB89: SI | AD89: SI | AF89: SI | AN89: Mary | AO89: ID_00049777
A90: WISS CONSULTORIA JURIDICA SAS | B90: ID_00049964 | C90: ISS_INAC_011001 | D90: 54623 | E90: 05001310500920080035500 | F90: 050013105009200800355 | G90: EJECUTIVO LABORAL | H90: 645967 | I90: FRANCISCO LUIS RESTREPO ARBOLEDA | J90: ISS | K90: ANTIOQUIA | L90: CONTINUA CON LA EJECUCION | M90: 28/11/2011 | N90: SIN FALLO | Z90: NO | AA90: No se cargó en la plataforma ekogui la pieza procesal DEMANDA-ORDINARIA. | AB90: NO | AC90: No se cargó en la plataforma ekogui la pieza procesal MANDAMIENTO DE PAGO. | AD90: NO | AE90: No se cargó en la plataforma ekogui la pieza procesal EXCEPCIONES | AF90: NO APLICA | AH90: ERROR | AN90: Addy | AO90: ID_00049964
A91: WISS CONSULTORIA JURIDICA SAS | B91: ID_00050002 | C91: ISS_INAC_011039 | D91: 242410 | E91: 05001310500920090018100 | F91: 050013105009200900181 | G91: EJECUTIVO LABORAL | H91: 3472387 | I91: JOSE MARIA RESTREPO CORREA | J91: ISS | K91: ANTIOQUIA | L91: CONTINUA CON LA EJECUCION | M91: 28/11/2011 | N91: SIN FALLO | Z91: NO | AA91: No se cargó en la plataforma ekogui la pieza procesal DEMANDA QUE DA ORIGEN AL MANDAMIENTO DE PAGO. | AB91: NO | AC91: No se cargó en la plataforma ekogui la pieza procesal MANDAMIENTO DE PAGO. | AD91: SI | AF91: SI | AH91: ERROR | AN91: Leonardo | AO91: ID_00050002
A92: WISS CONSULTORIA JURIDICA SAS | B92: ID_00051187 | C92: ISS_INAC_012224 | D92: 242419 | E92: 05001310500920090064900 | F92: 050013105009200900649 | G92: EJECUTIVO LABORAL | H92: 8246142 | I92: ERNESTO DE JESUS SANCHEZ VELEZ | J92: ISS | K92: ANTIOQUIA | L92: CONTINUA CON LA EJECUCION | M92: 27/02/2012 | N92: SIN FALLO | Z92: NO | AA92: No se cargó en la plataforma ekogui la pieza procesal DEMANDA QUE DA ORIGEN AL MANDAMIENTO DE PAGO. | AB92: SI | AD92: NO | AE92: No se cargó en la plataforma ekogui la pieza procesal EXCEPCIONES | AF92: SI | AH92: ERROR | AN92: Mary | AO92: ID_00051187
A93: UNION TEMPORAL SUPRA LEGAL | B93: ID_00051479 | C93: ISS_INAC_012516 | D93: 241965 | E93: 05001310500420090090200 | F93: 050013105004200900902 | G93: EJECUTIVO LABORAL | H93: 3476439 | I93: LUIS ALFREDO SUAREZ MESA | J93: ISS | K93: ANTIOQUIA | L93: CONTINUA CON LA EJECUCION | M93: 13/06/2012 | N93: SIN FALLO | Z93: SI | AB93: SI | AD93: SI | AF93: SI | AN93: Mary | AO93: ID_00051479
A94: UNION TEMPORAL VILLEGAS CONSULTORES JURIDICOS | B94: ID_00051789 | C94: ISS_INAC_012826 | D94: 241970 | E94: 05001310500520100038300 | F94: 050013105005201000383 | G94: EJECUTIVO LABORAL | H94: 70051903 | I94: JESUS EDUARDO TORO DIEZ | J94: ISS | K94: ANTIOQUIA | L94: CONTINUA CON LA EJECUCION | M94: 16/12/2019 | N94: SIN FALLO | Z94: SI | AB94: SI | AD94: SI | AF94: SI | AN94: Manuel | AO94: ID_00051789
A95: UNION TEMPORAL VILLEGAS CONSULTORES JURIDICOS | B95: ID_00052001 | C95: ISS_INAC_013038 | D95: 242329 | E95: 05001310500820110043200 | F95: 050013105008201100432 | G95: EJECUTIVO LABORAL | H95: 3514751 | I95: JOSE RICARDO URIBE GONZALEZ | J95: ISS | K95: ANTIOQUIA | L95: CONTINUA CON LA EJECUCION | M95: 14/12/2011 | N95: SIN FALLO | Z95: NO | AA95: No se cargó en la plataforma ekogui la pieza procesal DEMANDA-ORDINARIA. | AB95: SI | AD95: SI | AF95: SI | AH95: ERROR | AN95: Addy | AO95: ID_00052001
A96: UNION TEMPORAL VILLEGAS CONSULTORES JURIDICOS | B96: ID_00052120 | C96: ISS_INAC_013157 | D96: 58976 | E96: 05001310501220080003000 | F96: 050013105012200800030 | G96: EJECUTIVO LABORAL | H96: 90313452 | I96: CARLOS JULIO VALBUENA NOVA | J96: ISS | K96: ANTIOQUIA | L96: SIN FALLO | N96: SIN FALLO | Z96: NO | AA96: No se cargó en la plataforma ekogui la pieza procesal DEMANDA QUE DA ORIGEN AL MANDAMIENTO DE PAGO. | AB96: NO | AC96: No se cargó en la plataforma ekogui la pieza procesal MANDAMIENTO DE PAGO. | AD96: NO | AE96: No se cargó en la plataforma ekogui la pieza procesal MANDAMIENTO DE PAGO. | AF96: NO | AG96: No se cargó en la plataforma ekogui la pieza procesal AUTO QUE ORDENA/NO ORDENA CONTINUAR CON LA EJECUCION. | AH96: ERROR | AN96: Leonardo | AO96: ID_00052120
A97: WISS CONSULTORIA JURIDICA SAS | B97: ID_00052357 | C97: ISS_INAC_013394 | D97: 54296 | E97: 05001310500920040063900 | F97: 050013105009200400639 | G97: EJECUTIVO LABORAL | H97: 3440190 | I97: CARLOS ESAU VANEGAS RODRIGUEZ | J97: ISS | K97: ANTIOQUIA | L97: CONTINUA CON LA EJECUCION | M97: 6/05/2005 | N97: SIN FALLO | Z97: SI | AB97: SI | AD97: SI | AF97: SI | AN97: Manuel | AO97: ID_00052357
A98: WISS CONSULTORIA JURIDICA SAS | B98: ID_00052557 | C98: ISS_INAC_013594 | D98: 242426 | E98: 05001310500920100005400 | F98: 050013105009201000054 | G98: EJECUTIVO LABORAL | H98: 8242196 | I98: VICTOR VASQUEZ VALENCIA | J98: ISS | K98: ANTIOQUIA | L98: CONTINUA CON LA EJECUCION | M98: 1/03/2012 | N98: SIN FALLO | Z98: NO | AA98: No se cargó en la plataforma ekogui la pieza procesal DEMANDA-ORDINARIA. | AB98: NO | AC98: No se cargó en la plataforma ekogui la pieza procesal MANDAMIENTO DE PAGO. | AD98: NO | AE98: No se cargó en la plataforma ekogui la pieza procesal EXCEPCIONES | AF98: SI | AH98: ERROR | AN98: Addy | AO98: ID_00052557
A99: UNION TEMPORAL VILLEGAS CONSULTORES JURIDICOS | B99: ID_00052686 | C99: ISS_INAC_013723 | D99: 1209784 | E99: 05001310501020120016900 | F99: 050013105010201200169 | G99: EJECUTIVO LABORAL | H99: 8386036 | I99: JOSE PATRICIO VELASQUEZ VERGARA | J99: ISS | K99: ANTIOQUIA | L99: CONTINUA CON LA EJECUCION | M99: 20/11/2018 | N99: SIN FALLO | Z99: NO | AA99: No se cargó en la plataforma ekogui la pieza procesal DEMANDA QUE DA ORIGEN AL MANDAMIENTO DE PAGO. | AB99: SI | AD99: SI | AF99: SI | AH99: ERROR | AN99: Mary | AO99: ID_00052686
A100: UNION TEMPORAL VILLEGAS CONSULTORES JURIDICOS | B100: ID_00087381 | C100: 2013_4223985 | D100: 540529 | E100: 05001310501820130056300 | F100: 050013105018201300563 | G100: ORDINARIO LABORAL DE PRIMERA INSTANCIA | H100: 70410670 | I100: ROGELIO ZAPATA OCAMPO | J100: COLPENSIONES | K100: ANTIOQUIA | L100: DESFAVORABLE | M100: 5/12/2013 | N100: SIN FALLO | P100: SI | T100: SI | V100: SI | X100: NO APLICA | AN100: Addy | AO100: ID_00087381
...

Sheet Parametros
A1: OBSERVACIÓN DEMANDA | B1: OBSERVACIÓN ACTA_DE_AUDIENCIA | C1: OBSERVACIÓN CONTESTACION_DE_DEMANDA | D1: OBSERVACIÓN SENTENCIA_PRIMERA_INSTANCIA | E1: OBSERVACIÓN SENTENCIA_SEGUNDA_INSTANCIA | F1: OBSERVACIÓN DEMANDA | G1: OBSERVACIÓN MANDAMIENTO_DE_PAGO | H1: OBSERVACIÓN EXCEPCIONES_CONTESTACION | I1: OBSERVACIÓN AUTO_QUE_ORDENA_CONTINUAR/NO_CONTINUAR_CON _LA_EJECUCION
A2: No se cargó en la plataforma ekogui la pieza procesal DEMANDA-ORDINARIA. | B2: No se cargó en la plataforma ekogui la pieza procesal ACTA DE AUDIENCIA. | C2: No se cargó en la plataforma ekogui la pieza procesal CONTESTACION DE LA DEMANDA. | D2: No se cargó en la plataforma ekogui la pieza procesal SENTENCIA. | E2: No se cargó en la plataforma ekogui la pieza procesal SENTENCIA. | F2: No se cargó en la plataforma ekogui la pieza procesal DEMANDA QUE DA ORIGEN AL MANDAMIENTO DE PAGO. | G2: No se cargó en la plataforma ekogui la pieza procesal MANDAMIENTO DE PAGO. | I2: No se cargó en la plataforma ekogui la pieza procesal AUTO QUE ORDENA/NO ORDENA CONTINUAR CON LA EJECUCION.
A3: Se cargó en la plataforma ekogui la pieza procesal DEMANDA-ORDINARIA de forma incompleta. | B3: Se cargó en la plataforma ekogui la pieza procesal ACTA DE AUDIENCIA de forma incompleta. | C3: Se cargó en la plataforma ekogui la pieza procesal CONTESTACION DE LA DEMANDA de forma incompleta. | D3: Se cargó en la plataforma ekogui la pieza procesal SENTENCIA de forma incompleta. | E3: Se cargó en la plataforma ekogui la pieza procesal SENTENCIA de forma incompleta. | F3: Se cargó en la plataforma ekogui la pieza procesal DEMANDA QUE DA ORIGEN AL MANDAMIENTO DE PAGO de forma incompleta. | G3: Se cargó en la plataforma ekogui la pieza procesal MANDAMIENTO DE PAGO de forma incompleta. | H3: Se cargó en la plataforma ekogui la pieza procesal EXCEPCIONES-CONTESTACION AL MANDAMIENTO DE PAGO de forma incompleta. | I3: Se cargó en la plataforma ekogui la pieza procesal AUTO QUE ORDENA/NO ORDENA CONTINUAR CON LA EJECUCION de forma incompleta.
A4: Se cargó en la plataforma ekogui la pieza procesal DEMANDA-ORDINARIA en archivo dañado o no legible | B4: Se cargó en la plataforma ekogui la pieza procesal ACTA DE AUDIENCIA en archivo dañado o no legible | C4: Se cargó en la plataforma ekogui la pieza procesal CONTESTACION DE LA DEMANDA en archivo dañado o no legible. | D4: Se cargó en la plataforma ekogui la pieza procesal SENTENCIA en archivo dañado o no legible. | E4: Se cargó en la plataforma ekogui la pieza procesal SENTENCIA en archivo dañado o no legible. | F4: Se cargó en la plataforma ekogui la pieza procesal DEMANDA QUE DA ORIGEN AL MANDAMIENTO DE PAGO en archivo dañado o no legible | G4: Se cargó en la plataforma ekogui la pieza procesal MANDAMIENTO DE PAGO en archivo dañado o no legible | H4: Se cargó en la plataforma ekogui la pieza procesal EXCEPCIONES-CONTESTACION AL MANDAMIENTO DE PAGO en archivo dañado o no legible | I4: Se cargó en la plataforma ekogui la pieza procesal AUTO QUE ORDENA/NO ORDENA CONTINUAR CON LA EJECUCION en archivo dañado o no legible
A5: Se cargó en la plataforma ekogui la pieza procesal DEMANDA-ORDINARIA, pero no corresponde al proceso actual. | B5: Se cargó en la plataforma ekogui la pieza procesal ACTA DE AUDIENCIA, pero no corresponde al proceso actual. | C5: Se cargó en la plataforma ekogui la pieza procesal CONTESTACION DE LA DEMANDA, sin sello de radicación ante despacho judicial. | D5: Se cargó en la plataforma ekogui la pieza procesal SENTENCIA, pero no corresponde al proceso actual. | E5: Se cargó en la plataforma ekogui la pieza procesal SENTENCIA, pero no corresponde al proceso actual. | F5: Se cargó en la plataforma ekogui la pieza procesal DEMANDA QUE DA ORIGEN AL MANDAMIENTO DE PAGO, pero no corresponde al proceso actual. | G5: Se cargó en la plataforma ekogui la pieza procesal MANDAMIENTO DE PAGO, pero no corresponde al proceso actual. | H5: Se cargó en la plataforma ekogui la pieza procesal EXCEPCIONES-CONTESTACION AL MANDAMIENTO DE PAGO, pero no corresponde al proceso actual. | I5: Se cargó en la plataforma ekogui la pieza procesal AUTO QUE ORDENA/NO ORDENA CONTINUAR CON LA EJECUCION, pero no corresponde al proceso actual.
A6: Se cargó en la plataforma ekogui la pieza procesal DEMANDA-ORDINARIA, pero es un comodín, pantallazo, o es otra pieza procesal. | B6: Se cargó en la plataforma ekogui la pieza procesal ACTA DE AUDIENCIA, pero es un comodín, pantallazo, o es otra pieza procesal. | C6: Se cargó en la plataforma ekogui la pieza procesal CONTESTACION DE LA DEMANDA, pero no corresponde al proceso actual. | D6: Se cargó en la plataforma ekogui la pieza procesal SENTENCIA, pero es un comodín, pantallazo, o es otra pieza procesal. | E6: Se cargó en la plataforma ekogui la pieza procesal SENTENCIA, pero es un comodín, pantallazo, o es otra pieza procesal. | F6: Se cargó en la plataforma ekogui la pieza procesal DEMANDA QUE DA ORIGEN AL MANDAMIENTO DE PAGO, pero es un comodín, pantallazo, o es otra pieza procesal. | G6: Se cargó en la plataforma ekogui la pieza procesal MANDAMIENTO DE PAGO, pero es un comodín, pantallazo, o es otra pieza procesal. | H6: Se cargó en la plataforma ekogui la pieza procesal EXCEPCIONES-CONTESTACION AL MANDAMIENTO DE PAGO, pero es un comodín, pantallazo, o es otra pieza procesal. | I6: Se cargó en la plataforma ekogui la pieza procesal AUTO QUE ORDENA/NO ORDENA CONTINUAR CON LA EJECUCION, pero es un comodín, pantallazo, o es otra pieza procesal.
A7: Se cargó en la plataforma ekogui la pieza procesal DEMANDA-ORDINARIA, pero en formato Word, sin firma y sello. | B7: Se cargó en la plataforma ekogui la pieza procesal ACTA DE AUDIENCIA, pero no fue cargada por parte de firma que representa a Colpensiones. | C7: Se cargó en la plataforma ekogui la pieza procesal CONTESTACION DE LA DEMANDA, pero es un comodín, pantallazo, o es otra pieza procesal. | D7: Se cargó en la plataforma ekogui la pieza procesal SENTENCIA, pero no fue cargada por parte de firma que representa a Colpensiones. | E7: Se cargó en la plataforma ekogui la pieza procesal SENTENCIA, pero no fue cargada por parte de firma que representa a Colpensiones. | F7: Se cargó en la plataforma ekogui la pieza procesal DEMANDA QUE DA ORIGEN AL MANDAMIENTO DE PAGO, pero no fue cargada por parte de firma que representa a Colpensiones. | G7: Se cargó en la plataforma ekogui la pieza procesal MANDAMIENTO DE PAGO, pero en formato Word, sin firma y sello. | H7: Se cargó en la plataforma ekogui la pieza procesal EXCEPCIONES-CONTESTACION AL MANDAMIENTO DE PAGO, pero en formato Word, sin firma y sello. | I7: Se cargó en la plataforma ekogui la pieza procesal AUTO QUE ORDENA/NO ORDENA CONTINUAR CON LA EJECUCION, pero no fue cargada por parte de firma que representa a Colpensiones.
A8: Se cargó en la plataforma ekogui la pieza procesal DEMANDA-ORDINARIA, pero no fue cargada por parte de firma que representa a Colpensiones. | C8: Se cargó en la plataforma ekogui la pieza procesal CONTESTACION DE LA DEMANDA, pero en formato Word, sin firmas y sello. | G8: Se cargó en la plataforma ekogui la pieza procesal MANDAMIENTO DE PAGO, pero no fue cargada por parte de firma que representa a Colpensiones. | H8: Se cargó en la plataforma ekogui la pieza procesal EXCEPCIONES-CONTESTACION AL MANDAMIENTO DE PAGO, pero no fue cargada por parte de firma que representa a Colpensiones.
C9: Se cargó en la plataforma ekogui la pieza procesal CONTESTACION DE LA DEMANDA, pero no fue cargada por parte de firma que representa a Colpensiones.

Sheet BASE
A1: FIRMA | B1: ID_PROCESOS | C1: NO_BIZAGI | D1: ID_EKOGUI | E1: DIGITOS_23 | F1: 21 DIG | G1: TIPO_PROCESO | H1: IDENTIFICACION_DEMANDANTE | I1: NOMBRE_DEMANDANTE | J1: DEMANDADO | K1: REGIONAL | L1: SENTIDO_FALLO_1INSTANCIA | M1: FECHA_FALLO_1INSTANCIA | N1: SENTIDO_FALLO_2INSTANCIA | O1: FECHA_FALLO_2INSTANCIA | P1: SENTIDO_FALLO_RECURSOEXTRAORDINARIO | Q1: FECHA_FALLO_RECURSOEXTRAORDINARIO | R1: DEMANDA | S1: OBSERVACIÓN DEMANDA | T1: ACTA_DE_AUDIENCIA | U1: OBSERVACIÓN ACTA_DE_AUDIENCIA | V1: CONTESTACION_DE_DEMANDA | W1: OBSERVACIÓN CONTESTACION_DE_DEMANDA | X1: SENTENCIA_PRIMERA_INSTANCIA | Y1: OBSERVACIÓN SENTENCIA_PRIMERA_INSTANCIA | Z1: SENTENCIA_SEGUNDA_INSTANCIA | AA1: OBSERVACIÓN SENTENCIA_SEGUNDA_INSTANCIA | AB1: SENTENCIA_CASACIÓN | AC1: OBSERVACIÓN SENTENCIA_CASACIÓN | AD1: DEMANDA_EJECUTIVA | AE1: OBSERVACIÓN DEMANDA_EJECUTIVA | AF1: MANDAMIENTO_DE_PAGO | AG1: OBSERVACIÓN MANDAMIENTO_DE_PAGO | AH1: EXCEPCIONES_CONTESTACION | AI1: OBSERVACIÓN EXCEPCIONES_CONTESTACION | AJ1: AUTO_QUE_ORDENA_CONTINUAR/NO_CONTINUAR_CON _LA_EJECUCION | AK1: OBSERVACIÓN AUTO_QUE_ORDENA_CONTINUAR/NO_CONTINUAR_CON _LA_EJECUCION | AL1: LIQUIDACIÓN_CREDITO | AM1: OBSERVACIÓN LIQUIDACIÓN_CREDITO | AN1: AUTO_APRUEBA_LIQUIDACIÓN_CREDITO | AO1: OBSERVACIÓN AUTO_QUE_APRUEBA_LIQUIDACIÓN_CREDITO | AP1: VALIDACIÓN | AQ1: OBSERVACIÓN ERROR | AR1: PROCEDE / NO PROCEDE ERROR | AS1: RAZÓN POR LA CUAL NO PROCEDE | AT1: OBSERVACIÓN REGIONAL | AU1: CONCLUSIÓN | AV1: ENCARGADO | AW1: RESPONSABLE | AX1: REVISOR REGIONAL
A2: ABOGADO EXTERNO - DIANA CRISTINA BOBADILLA OSORIO | B2: ID_008055411 | C2: 2026_4541951 | D2: 2681003 | E2: 5001310500920250010500 | F2: 050013105009202500105 | G2: ORDINARIO LABORAL DE PRIMERA INSTANCIA | H2: 98573993 | I2: FRANCISCO JAVIER RESTREPO OROZCO | K2: ANTIOQUIA
A3: ARELLANO JARAMILLO & ABOGADOS SAS | B3: ID_007236762 | C3: 2022_9311816 | D3: 2304462 | E3: 5038408900120220002500 | F3: 050384089001202200025 | G3: DIVISION MATERIAL Y/O VENTA DE LA COSA EN COMUN | H3: 8600429455 | I3: CENTRAL DE INVERSIONES S.A. CISA | K3: ANTIOQUIA
A4: CASACIÓN LABORAL ESTUDIO S.A.S | B4: ID_00444659 | C4: 2018_6678760 | D4: 1239362 | E4: 5001310501520180018700 | F4: 050013105015201800187 | G4: ORDINARIO LABORAL DE PRIMERA INSTANCIA | H4: 21429041 | I4: NOREDY ALCIRA ROJAS PANIAGUA | K4: ANTIOQUIA
A5: CASACIÓN LABORAL ESTUDIO S.A.S | B5: ID_007000495 | C5: 2021_5403627 | D5: 2199901 | E5: 5001310502120210003000 | F5: 050013105021202100030 | G5: ORDINARIO LABORAL DE PRIMERA INSTANCIA | H5: 70093888 | I5: RUBEN DARIO ATEHORTUA OSSA | K5: ANTIOQUIA
A6: CASACIÓN LABORAL ESTUDIO S.A.S | B6: ID_007299162 | C6: 2022_14975427 | D6: 2363377 | E6: 5001310501520220043200 | F6: 050013105015202200432 | G6: ORDINARIO LABORAL DE PRIMERA INSTANCIA | H6: 43829506 | I6: LEONOR HELENA MEDINA TORRES | K6: ANTIOQUIA
A7: CASACIÓN LABORAL ESTUDIO S.A.S | B7: ID_007351466 | C7: 2023_1694257 | D7: 2394943 | E7: 5001310501720220052900 | F7: 050013105017202200529 | G7: ORDINARIO LABORAL DE PRIMERA INSTANCIA | H7: 98525550 | I7: SERGIO ALFONSO IBARRA PIEDRAHITA | K7: ANTIOQUIA
A8: CASACIÓN LABORAL ESTUDIO S.A.S | B8: ID_00374466 | C8: 2017_11335576 | D8: 1092060 | E8: 5001310500820170071800 | F8: 050013105008201700718 | G8: ORDINARIO LABORAL DE PRIMERA INSTANCIA | H8: 8274537 | I8: HORACIO HERRON ARENAS | K8: ANTIOQUIA
A9: CASACIÓN LABORAL ESTUDIO S.A.S | B9: ID_007495631 | C9: 2023_16654430 | D9: 2480482 | E9: 5001310502520230026900 | F9: 050013105025202300269 | G9: ORDINARIO LABORAL DE PRIMERA INSTANCIA | H9: 51903147 | I9: MARIA ANA BEIVA GONZALEZ RODRIGUEZ | K9: ANTIOQUIA
A10: CASACIÓN LABORAL ESTUDIO S.A.S | B10: ID_007411893 | C10: 2023_7512343 | D10: 2432653 | E10: 5001310500920230015000 | F10: 050013105009202300150 | G10: ORDINARIO LABORAL DE PRIMERA INSTANCIA | H10: 42996883 | I10: GABRIELA CECILIA OSSA GUTIERREZ | K10: ANTIOQUIA
A11: CASACIÓN LABORAL ESTUDIO S.A.S | B11: ID_00267910 | C11: 2016_8545589 | D11: 908584 | E11: 5001310502220160078400 | F11: 050013105022201600784 | G11: ORDINARIO LABORAL DE PRIMERA INSTANCIA | H11: 43577295 | I11: GLORIA INES ZAPATA GONZALEZ | K11: ANTIOQUIA
A12: CASACIÓN LABORAL ESTUDIO S.A.S | B12: ID_007472361 | C12: 2023_14404553 | D12: 2466967 | E12: 5001310500420230032800 | F12: 050013105004202300328 | G12: ORDINARIO LABORAL DE PRIMERA INSTANCIA | H12: 43508208 | I12: MARIA OLMA SEPULVEDA CARDONA | K12: ANTIOQUIA
A13: CASACIÓN LABORAL ESTUDIO S.A.S | B13: ID_00548393 | C13: 2019_7354777 | D13: 2021460 | E13: 5001310501220190031400 | F13: 050013105012201900314 | G13: ORDINARIO LABORAL DE PRIMERA INSTANCIA | H13: 39183439 | I13: MARIA MANUELA BLANDÓN OTALVARO | K13: ANTIOQUIA
... A767: TABOR ASESORES LEGALES SAS | B767: ID_007984667 | C767: 2025_25171633 | D767: 2698557 | E767: 11001410500120250076600 | F767: 110014105001202500766 | G767: ORDINARIO LABORAL DE UNICA INSTANCIA | H767: 91068158 | I767: ANGEL GONZALO MANCILLA SILVA | K767: BOGOTA
A768: TABOR ASESORES LEGALES SAS | B768: ID_008126681 | C768: 2026_9249572 | D768: 2410273 | G768: ORDINARIO LABORAL DE PRIMERA INSTANCIA | H768: 41635147 | I768: MARIA EUGENIA ANGELA GALLO MAHECHA | K768: BOGOTA
A769: TABOR ASESORES LEGALES SAS | B769: ID_007761565 | C769: 2024_25290224 | D769: 2604332 | E769: 11001310504820240001000 | F769: 110013105048202400010 | G769: ORDINARIO LABORAL DE PRIMERA INSTANCIA | H769: 19361808 | I769: NACIANCENO GOMEZ RUBIO | K769: BOGOTA
A770: TABOR ASESORES LEGALES SAS | B770: ID_007460873 | C770: 2023_13351237 | D770: 2462277 | E770: 11001310500220210046400 | F770: 110013105002202100464 | G770: ORDINARIO LABORAL DE PRIMERA INSTANCIA | H770: 80167600 | I770: NORBERTO VARGAS HORTA | K770: BOGOTA
A771: TABOR ASESORES LEGALES SAS | B771: ID_007742950 | C771: 2024_23398996 | D771: 2599041 | E771: 11001310502320240018700 | F771: 110013105023202400187 | G771: ORDINARIO LABORAL DE PRIMERA INSTANCIA | H771: 91430276 | I771: CARLOS ARTURO ANGULO SOLANO | K771: BOGOTA
A772: TABOR ASESORES LEGALES SAS | B772: ID_007608670 | C772: 2024_7669453 | D772: 2534878 | E772: 11001310503720240001300 | F772: 110013105037202400013 | G772: ORDINARIO LABORAL DE PRIMERA INSTANCIA | H772: 35503692 | I772: OLGA LUCIA ESTEPA ORJUELA | K772: BOGOTA
A773: TABOR ASESORES LEGALES SAS | B773: ID_00678546 | C773: 2020_10440013 | D773: 2155420 | E773: 11001410500520200025400 | F773: 110014105005202000254 | G773: ORDINARIO LABORAL DE UNICA INSTANCIA | H773: 1053818883 | I773: ESTEBAN CASTRO RAMIREZ | K773: BOGOTA
A774: TABOR ASESORES LEGALES SAS | B774: ID_007783036 | C774: 2025_774637 | D774: 2615038 | E774: 11001310505020240002200 | F774: 110013105050202400022 | G774: ORDINARIO LABORAL DE PRIMERA INSTANCIA | H774: 51714870 | I774: ALBA TERESA RIAÑO RODRIGUEZ | K774: BOGOTA
A775: TABOR ASESORES LEGALES SAS | B775: ID_007879187 | C775: 2025_12350064 | D775: 2657354 | E775: 11001310500420250007100 | F775: 110013105004202500071 | G775: ORDINARIO LABORAL DE PRIMERA INSTANCIA | H775: 19377865 | I775: LUIS ERNESTO AGUILAR DOMINGUEZ | K775: BOGOTA
